.version 52 0 
.class public super com/cairn4/moonbase/ui/MiniMap 
.super com/cairn4/moonbase/ui/Menu 
.field private static CHUNKS_RADIUS_FROM_CURRENT I 
.field private static MAX_TILE_DISTANCE F 
.field private final chunkDrawSize I = 100 
.field private final tilePixelSize I = 10 
.field private static MEGA_CHUNK I 
.field public static savedZoom F 
.field private groupOffset Lcom/badlogic/gdx/scenes/scene2d/Group; 
.field private chunkGroup Lcom/badlogic/gdx/scenes/scene2d/Group; 
.field private mapZoomHolder Lcom/badlogic/gdx/scenes/scene2d/Group; 
.field private tileIconGroup Lcom/badlogic/gdx/scenes/scene2d/Group; 
.field navBeacons Lcom/badlogic/gdx/scenes/scene2d/ui/Label; 
.field gameScreen Lcom/cairn4/moonbase/ui/GameScreen; 
.field private chunkFile Lcom/badlogic/gdx/files/FileHandle; 
.field private disposableTextures Ljava/util/ArrayList; .fieldattributes 
    .signature Ljava/util/ArrayList<Lcom/badlogic/gdx/graphics/Texture;>; 
.end fieldattributes 
.field private chunkTextures Ljava/util/HashMap; .fieldattributes 
    .signature Ljava/util/HashMap<Ljava/lang/String;Lcom/badlogic/gdx/graphics/Texture;>; 
.end fieldattributes 
.field private chunkColorState Ljava/util/HashMap; .fieldattributes 
    .signature Ljava/util/HashMap<Lcom/badlogic/gdx/graphics/Texture;Lcom/badlogic/gdx/graphics/Color;>; 
.end fieldattributes 
.field private minChunkX I 
.field private maxChunkX I 
.field private minChunkY I 
.field private maxChunkY I 
.field minMegaChunkX I 
.field maxMegaChunkX I 
.field minMegaChunkY I 
.field maxMegaChunkY I 
.field public mapCenterOffeset Lcom/badlogic/gdx/math/Vector2; 
.field public dragStarPos Lcom/badlogic/gdx/math/Vector2; 
.field public dragOffset Lcom/badlogic/gdx/math/Vector2; 
.field public dragGroupStartPos Lcom/badlogic/gdx/math/Vector2; 
.field private minDragPos Lcom/badlogic/gdx/math/Vector2; 
.field private maxDragPos Lcom/badlogic/gdx/math/Vector2; 
.field private showMapPopup Z 
.field private bg Lcom/badlogic/gdx/scenes/scene2d/ui/Image; 
.field private uiGroup Lcom/badlogic/gdx/scenes/scene2d/Group; 
.field private border Lcom/badlogic/gdx/scenes/scene2d/ui/Image; 
.field private innerBorder Lcom/badlogic/gdx/scenes/scene2d/ui/Image; 
.field private btnClose Lcom/badlogic/gdx/scenes/scene2d/ui/Button; 
.field private btnRecenter Lcom/badlogic/gdx/scenes/scene2d/ui/Button; 
.field private btnZoomIn Lcom/badlogic/gdx/scenes/scene2d/ui/Button; 
.field private zoomDiv Lcom/badlogic/gdx/scenes/scene2d/ui/Image; 
.field private btnZoomOut Lcom/badlogic/gdx/scenes/scene2d/ui/Button; 
.field private hoverLabel Lcom/badlogic/gdx/scenes/scene2d/ui/Label; 
.field private hoverTooltipGroup Lcom/badlogic/gdx/scenes/scene2d/Group; 
.field private hoverInnerGroup Lcom/badlogic/gdx/scenes/scene2d/Group; 
.field private hoverPanel Lcom/badlogic/gdx/scenes/scene2d/ui/Image; 
.field private hoverTooltipTable Lcom/badlogic/gdx/scenes/scene2d/ui/Table; 
.field private pauseLabel Lcom/badlogic/gdx/scenes/scene2d/ui/Label; 
.field private static PAN_SPEED F 
.field private chunkPixmap Lcom/badlogic/gdx/graphics/Pixmap; 
.field private soundPitch F 
.field private soundBasePitch F 
.field private soundPitchVar F 
.field private soundVolume F 
.field private screenMouse Lcom/badlogic/gdx/math/Vector2; 
.field private mapMouse Lcom/badlogic/gdx/math/Vector2; 
.field public zoomDir I 

.method public <init> : (Lcom/cairn4/moonbase/ui/GameScreen;)V 
    .code stack 5 locals 2 
L0:     aload_0 
L1:     aload_1 
L2:     invokespecial Method com/cairn4/moonbase/ui/Menu <init> (Lcom/cairn4/moonbase/ui/BaseScreen;)V 
L5:     aload_0 
L6:     bipush 100 
L8:     putfield Field com/cairn4/moonbase/ui/MiniMap chunkDrawSize I 
L11:    aload_0 
L12:    bipush 10 
L14:    putfield Field com/cairn4/moonbase/ui/MiniMap tilePixelSize I 
L17:    aload_0 
L18:    new java/util/ArrayList 
L21:    dup 
L22:    invokespecial Method java/util/ArrayList <init> ()V 
L25:    putfield Field com/cairn4/moonbase/ui/MiniMap disposableTextures Ljava/util/ArrayList; 
L28:    aload_0 
L29:    new java/util/HashMap 
L32:    dup 
L33:    invokespecial Method java/util/HashMap <init> ()V 
L36:    putfield Field com/cairn4/moonbase/ui/MiniMap chunkTextures Ljava/util/HashMap; 
L39:    aload_0 
L40:    new java/util/HashMap 
L43:    dup 
L44:    invokespecial Method java/util/HashMap <init> ()V 
L47:    putfield Field com/cairn4/moonbase/ui/MiniMap chunkColorState Ljava/util/HashMap; 
L50:    aload_0 
L51:    new com/badlogic/gdx/math/Vector2 
L54:    dup 
L55:    fconst_0 
L56:    fconst_0 
L57:    invokespecial Method com/badlogic/gdx/math/Vector2 <init> (FF)V 
L60:    putfield Field com/cairn4/moonbase/ui/MiniMap mapCenterOffeset Lcom/badlogic/gdx/math/Vector2; 
L63:    aload_0 
L64:    new com/badlogic/gdx/math/Vector2 
L67:    dup 
L68:    fconst_0 
L69:    fconst_0 
L70:    invokespecial Method com/badlogic/gdx/math/Vector2 <init> (FF)V 
L73:    putfield Field com/cairn4/moonbase/ui/MiniMap dragStarPos Lcom/badlogic/gdx/math/Vector2; 
L76:    aload_0 
L77:    new com/badlogic/gdx/math/Vector2 
L80:    dup 
L81:    fconst_0 
L82:    fconst_0 
L83:    invokespecial Method com/badlogic/gdx/math/Vector2 <init> (FF)V 
L86:    putfield Field com/cairn4/moonbase/ui/MiniMap dragOffset Lcom/badlogic/gdx/math/Vector2; 
L89:    aload_0 
L90:    new com/badlogic/gdx/math/Vector2 
L93:    dup 
L94:    fconst_0 
L95:    fconst_0 
L96:    invokespecial Method com/badlogic/gdx/math/Vector2 <init> (FF)V 
L99:    putfield Field com/cairn4/moonbase/ui/MiniMap dragGroupStartPos Lcom/badlogic/gdx/math/Vector2; 
L102:   aload_0 
L103:   new com/badlogic/gdx/math/Vector2 
L106:   dup 
L107:   fconst_0 
L108:   fconst_0 
L109:   invokespecial Method com/badlogic/gdx/math/Vector2 <init> (FF)V 
L112:   putfield Field com/cairn4/moonbase/ui/MiniMap minDragPos Lcom/badlogic/gdx/math/Vector2; 
L115:   aload_0 
L116:   new com/badlogic/gdx/math/Vector2 
L119:   dup 
L120:   fconst_0 
L121:   fconst_0 
L122:   invokespecial Method com/badlogic/gdx/math/Vector2 <init> (FF)V 
L125:   putfield Field com/cairn4/moonbase/ui/MiniMap maxDragPos Lcom/badlogic/gdx/math/Vector2; 
L128:   aload_0 
L129:   iconst_0 
L130:   putfield Field com/cairn4/moonbase/ui/MiniMap showMapPopup Z 
L133:   aload_0 
L134:   ldc +1.5f 
L136:   putfield Field com/cairn4/moonbase/ui/MiniMap soundBasePitch F 
L139:   aload_0 
L140:   ldc +0.11500000208616257f 
L142:   putfield Field com/cairn4/moonbase/ui/MiniMap soundPitchVar F 
L145:   aload_0 
L146:   ldc +0.03500000014901161f 
L148:   putfield Field com/cairn4/moonbase/ui/MiniMap soundVolume F 
L151:   aload_0 
L152:   new com/badlogic/gdx/math/Vector2 
L155:   dup 
L156:   fconst_0 
L157:   fconst_0 
L158:   invokespecial Method com/badlogic/gdx/math/Vector2 <init> (FF)V 
L161:   putfield Field com/cairn4/moonbase/ui/MiniMap screenMouse Lcom/badlogic/gdx/math/Vector2; 
L164:   aload_0 
L165:   new com/badlogic/gdx/math/Vector2 
L168:   dup 
L169:   fconst_0 
L170:   fconst_0 
L171:   invokespecial Method com/badlogic/gdx/math/Vector2 <init> (FF)V 
L174:   putfield Field com/cairn4/moonbase/ui/MiniMap mapMouse Lcom/badlogic/gdx/math/Vector2; 
L177:   aload_0 
L178:   iconst_0 
L179:   putfield Field com/cairn4/moonbase/ui/MiniMap zoomDir I 
L182:   aload_0 
L183:   aload_1 
L184:   putfield Field com/cairn4/moonbase/ui/MiniMap gameScreen Lcom/cairn4/moonbase/ui/GameScreen; 
L187:   aload_1 
L188:   getfield Field com/cairn4/moonbase/ui/GameScreen world Lcom/cairn4/moonbase/World; 
L189:   getfield Field com/cairn4/moonbase/World player Lcom/cairn4/moonbase/Player; 
L190:   getfield Field com/cairn4/moonbase/Player playerStatus Lcom/cairn4/moonbase/PlayerStatus;
L191:   iconst_1
L192:   invokevirtual Method com/cairn4/moonbase/PlayerStatus setFlashlight (Z)V 
L195:   aload_0 
L196:   invokespecial Method com/cairn4/moonbase/ui/Menu setup ()V 
L199:   aload_0 
L200:   invokevirtual Method com/cairn4/moonbase/ui/MiniMap show ()V 
L203:   aload_0 
L204:   invokevirtual Method com/cairn4/moonbase/ui/MiniMap finishedShowAnim ()V 
L207:   return 
L208:   
        .linenumbertable 
            L0 124 
            L5 58 
            L11 59 
            L17 76 
            L28 77 
            L39 78 
            L50 91 
            L63 92 
            L76 93 
            L89 94 
            L102 96 
            L115 97 
            L128 99 
            L133 351 
            L139 352 
            L145 353 
            L151 659 
            L164 660 
            L177 752 
            L182 126 
            L187 128 
            L195 130 
            L199 132 
            L203 133 
            L207 135 
        .end linenumbertable 
        .localvariabletable 
            0 is this Lcom/cairn4/moonbase/ui/MiniMap; from L0 to L208 
            1 is gameScreen Lcom/cairn4/moonbase/ui/GameScreen; from L0 to L208 
        .end localvariabletable 
    .end code 
.end method 

.method private generateMap : ()V 
    .code stack 6 locals 8 
L0:     invokestatic Method java/lang/System currentTimeMillis ()J 
L3:     lstore_1 
L4:     iconst_0 
L5:     istore_3 
L6:     iconst_0 
L7:     istore 4 
L9:     aload_0 
L10:    getfield Field com/cairn4/moonbase/ui/MiniMap minMegaChunkX I 
L13:    istore 5 

        .stack full 
            locals Object com/cairn4/moonbase/ui/MiniMap Long Integer Integer Integer 
            stack 
        .end stack 
L15:    iload 5 
L17:    aload_0 
L18:    getfield Field com/cairn4/moonbase/ui/MiniMap maxMegaChunkX I 
L21:    if_icmpgt L193 
L24:    aload_0 
L25:    getfield Field com/cairn4/moonbase/ui/MiniMap minMegaChunkY I 
L28:    istore 6 

        .stack append Integer 
L30:    iload 6 
L32:    aload_0 
L33:    getfield Field com/cairn4/moonbase/ui/MiniMap maxMegaChunkY I 
L36:    if_icmpgt L187 
L39:    aload_0 
L40:    new com/badlogic/gdx/graphics/Pixmap 
L43:    dup 
L44:    bipush 10 
L46:    getstatic Field com/cairn4/moonbase/ui/MiniMap MEGA_CHUNK I 
L49:    imul 
L50:    bipush 10 
L52:    getstatic Field com/cairn4/moonbase/ui/MiniMap MEGA_CHUNK I 
L55:    imul 
L56:    getstatic Field com/badlogic/gdx/graphics/Pixmap$Format RGBA8888 Lcom/badlogic/gdx/graphics/Pixmap$Format; 
L59:    invokespecial Method com/badlogic/gdx/graphics/Pixmap <init> (IILcom/badlogic/gdx/graphics/Pixmap$Format;)V 
L62:    putfield Field com/cairn4/moonbase/ui/MiniMap chunkPixmap Lcom/badlogic/gdx/graphics/Pixmap; 
L65:    new com/badlogic/gdx/graphics/Texture 
L68:    dup 
L69:    aload_0 
L70:    getfield Field com/cairn4/moonbase/ui/MiniMap chunkPixmap Lcom/badlogic/gdx/graphics/Pixmap; 
L73:    aload_0 
L74:    getfield Field com/cairn4/moonbase/ui/MiniMap gameScreen Lcom/cairn4/moonbase/ui/GameScreen; 
L77:    getfield Field com/cairn4/moonbase/ui/GameScreen world Lcom/cairn4/moonbase/World; 
L80:    iload 5 
L82:    iload 6 
L84:    invokestatic Method com/cairn4/moonbase/WorldDebugMap renderMegaChunk (Lcom/badlogic/gdx/graphics/Pixmap;Lcom/cairn4/moonbase/World;II)Lcom/badlogic/gdx/graphics/Pixmap; 
L87:    invokespecial Method com/badlogic/gdx/graphics/Texture <init> (Lcom/badlogic/gdx/graphics/Pixmap;)V 
L90:    astore 7 
L92:    aload_0 
L93:    getfield Field com/cairn4/moonbase/ui/MiniMap disposableTextures Ljava/util/ArrayList; 
L96:    aload 7 
L98:    invokevirtual Method java/util/ArrayList add (Ljava/lang/Object;)Z 
L101:   pop 
L102:   aload_0 
L103:   getfield Field com/cairn4/moonbase/ui/MiniMap chunkColorState Ljava/util/HashMap; 
L106:   aload 7 
L108:   getstatic Field com/badlogic/gdx/graphics/Color RED Lcom/badlogic/gdx/graphics/Color; 
L111:   invokevirtual Method java/util/HashMap put (Ljava/lang/Object;Ljava/lang/Object;)Ljava/lang/Object; 
L114:   pop 
L115:   iinc 3 1 
L118:   aload_0 
L119:   getfield Field com/cairn4/moonbase/ui/MiniMap chunkPixmap Lcom/badlogic/gdx/graphics/Pixmap; 
L122:   invokevirtual Method com/badlogic/gdx/graphics/Pixmap dispose ()V 
L125:   aload 7 
L127:   ifnull L141 
L130:   aload 7 
L132:   getstatic Field com/badlogic/gdx/graphics/Texture$TextureFilter Nearest Lcom/badlogic/gdx/graphics/Texture$TextureFilter; 
L135:   getstatic Field com/badlogic/gdx/graphics/Texture$TextureFilter Nearest Lcom/badlogic/gdx/graphics/Texture$TextureFilter; 
L138:   invokevirtual Method com/badlogic/gdx/graphics/Texture setFilter (Lcom/badlogic/gdx/graphics/Texture$TextureFilter;Lcom/badlogic/gdx/graphics/Texture$TextureFilter;)V 

        .stack append Object com/badlogic/gdx/graphics/Texture 
L141:   aload_0 
L142:   getfield Field com/cairn4/moonbase/ui/MiniMap chunkTextures Ljava/util/HashMap; 
L145:   new java/lang/StringBuilder 
L148:   dup 
L149:   invokespecial Method java/lang/StringBuilder <init> ()V 
L152:   ldc '' 
L154:   invokevirtual Method java/lang/StringBuilder append (Ljava/lang/String;)Ljava/lang/StringBuilder; 
L157:   iload 5 
L159:   invokevirtual Method java/lang/StringBuilder append (I)Ljava/lang/StringBuilder; 
L162:   ldc ',' 
L164:   invokevirtual Method java/lang/StringBuilder append (Ljava/lang/String;)Ljava/lang/StringBuilder; 
L167:   iload 6 
L169:   invokevirtual Method java/lang/StringBuilder append (I)Ljava/lang/StringBuilder; 
L172:   invokevirtual Method java/lang/StringBuilder toString ()Ljava/lang/String; 
L175:   aload 7 
L177:   invokevirtual Method java/util/HashMap put (Ljava/lang/Object;Ljava/lang/Object;)Ljava/lang/Object; 
L180:   pop 
L181:   iinc 6 1 
L184:   goto L30 

        .stack chop 2 
L187:   iinc 5 1 
L190:   goto L15 

        .stack chop 1 
L193:   invokestatic Method java/lang/System currentTimeMillis ()J 
L196:   lstore 5 
L198:   lload 5 
L200:   lload_1 
L201:   lsub 
L202:   l2f 
L203:   fstore 7 
L205:   fload 7 
L207:   ldc +1000.0f 
L209:   fdiv 
L210:   fstore 7 
L212:   getstatic Field com/badlogic/gdx/Gdx app Lcom/badlogic/gdx/Application; 
L215:   ldc 'MewnBase' 
L217:   new java/lang/StringBuilder 
L220:   dup 
L221:   invokespecial Method java/lang/StringBuilder <init> ()V 
L224:   ldc 'Map took ' 
L226:   invokevirtual Method java/lang/StringBuilder append (Ljava/lang/String;)Ljava/lang/StringBuilder; 
L229:   fload 7 
L231:   invokevirtual Method java/lang/StringBuilder append (F)Ljava/lang/StringBuilder; 
L234:   ldc ' seconds to be created.' 
L236:   invokevirtual Method java/lang/StringBuilder append (Ljava/lang/String;)Ljava/lang/StringBuilder; 
L239:   invokevirtual Method java/lang/StringBuilder toString ()Ljava/lang/String; 
L242:   invokeinterface InterfaceMethod com/badlogic/gdx/Application log (Ljava/lang/String;Ljava/lang/String;)V 3 
L247:   getstatic Field com/badlogic/gdx/Gdx app Lcom/badlogic/gdx/Application; 
L250:   ldc 'MewnBase' 
L252:   new java/lang/StringBuilder 
L255:   dup 
L256:   invokespecial Method java/lang/StringBuilder <init> ()V 
L259:   ldc 'Minimap: ' 
L261:   invokevirtual Method java/lang/StringBuilder append (Ljava/lang/String;)Ljava/lang/StringBuilder; 
L264:   iload_3 
L265:   invokevirtual Method java/lang/StringBuilder append (I)Ljava/lang/StringBuilder; 
L268:   ldc ' mega chunks rendered, ' 
L270:   invokevirtual Method java/lang/StringBuilder append (Ljava/lang/String;)Ljava/lang/StringBuilder; 
L273:   iload 4 
L275:   invokevirtual Method java/lang/StringBuilder append (I)Ljava/lang/StringBuilder; 
L278:   ldc ' chunks from cache.' 
L280:   invokevirtual Method java/lang/StringBuilder append (Ljava/lang/String;)Ljava/lang/StringBuilder; 
L283:   invokevirtual Method java/lang/StringBuilder toString ()Ljava/lang/String; 
L286:   invokeinterface InterfaceMethod com/badlogic/gdx/Application log (Ljava/lang/String;Ljava/lang/String;)V 3 
L291:   return 
L292:   
        .linenumbertable 
            L0 146 
            L4 149 
            L6 150 
            L9 152 
            L24 153 
            L39 156 
            L65 201 
            L92 203 
            L102 204 
            L115 206 
            L118 216 
            L125 218 
            L130 219 
            L141 223 
            L181 153 
            L187 152 
            L193 229 
            L198 230 
            L205 231 
            L212 232 
            L247 233 
            L291 234 
        .end linenumbertable 
        .localvariabletable 
            7 is t Lcom/badlogic/gdx/graphics/Texture; from L92 to L181 
            6 is mY I from L30 to L187 
            5 is mX I from L15 to L193 
            0 is this Lcom/cairn4/moonbase/ui/MiniMap; from L0 to L292 
            1 is startTime J from L4 to L292 
            3 is renderedMapChunks I from L6 to L292 
            4 is cachedMapChunks I from L9 to L292 
            5 is endTime J from L198 to L292 
            7 is amount F from L205 to L292 
        .end localvariabletable 
    .end code 
.end method 

.method private showMap : ()V 
    .code stack 4 locals 9 
L0:     aload_0 
L1:     invokespecial Method com/cairn4/moonbase/ui/MiniMap playMapTileLoadSound ()V 
L4:     aload_0 
L5:     getfield Field com/cairn4/moonbase/ui/MiniMap chunkTextures Ljava/util/HashMap; 
L8:     invokevirtual Method java/util/HashMap entrySet ()Ljava/util/Set; 
L11:    invokeinterface InterfaceMethod java/util/Set iterator ()Ljava/util/Iterator; 1 
L16:    astore_1 

        .stack append Object java/util/Iterator 
L17:    aload_1 
L18:    invokeinterface InterfaceMethod java/util/Iterator hasNext ()Z 1 
L23:    ifeq L159 
L26:    aload_1 
L27:    invokeinterface InterfaceMethod java/util/Iterator next ()Ljava/lang/Object; 1 
L32:    checkcast java/util/Map$Entry 
L35:    astore_2 
L36:    aload_2 
L37:    invokeinterface InterfaceMethod java/util/Map$Entry getKey ()Ljava/lang/Object; 1 
L42:    checkcast java/lang/String 
L45:    ldc ',' 
L47:    invokevirtual Method java/lang/String split (Ljava/lang/String;)[Ljava/lang/String; 
L50:    astore_3 
L51:    aload_3 
L52:    iconst_0 
L53:    aaload 
L54:    invokestatic Method java/lang/Integer parseInt (Ljava/lang/String;)I 
L57:    istore 4 
L59:    aload_3 
L60:    iconst_1 
L61:    aaload 
L62:    invokestatic Method java/lang/Integer parseInt (Ljava/lang/String;)I 
L65:    istore 5 
L67:    new com/badlogic/gdx/scenes/scene2d/ui/Image 
L70:    dup 
L71:    aload_2 
L72:    invokeinterface InterfaceMethod java/util/Map$Entry getValue ()Ljava/lang/Object; 1 
L77:    checkcast com/badlogic/gdx/graphics/Texture 
L80:    invokespecial Method com/badlogic/gdx/scenes/scene2d/ui/Image <init> (Lcom/badlogic/gdx/graphics/Texture;)V 
L83:    astore 6 
L85:    aload 6 
L87:    bipush 100 
L89:    getstatic Field com/cairn4/moonbase/ui/MiniMap MEGA_CHUNK I 
L92:    imul 
L93:    i2f 
L94:    bipush 100 
L96:    getstatic Field com/cairn4/moonbase/ui/MiniMap MEGA_CHUNK I 
L99:    imul 
L100:   i2f 
L101:   invokevirtual Method com/badlogic/gdx/scenes/scene2d/ui/Image setSize (FF)V 
L104:   bipush 100 
L106:   getstatic Field com/cairn4/moonbase/ui/MiniMap MEGA_CHUNK I 
L109:   imul 
L110:   iload 4 
L112:   aload_0 
L113:   getfield Field com/cairn4/moonbase/ui/MiniMap minMegaChunkX I 
L116:   isub 
L117:   imul 
L118:   istore 7 
L120:   bipush 100 
L122:   getstatic Field com/cairn4/moonbase/ui/MiniMap MEGA_CHUNK I 
L125:   imul 
L126:   iload 5 
L128:   aload_0 
L129:   getfield Field com/cairn4/moonbase/ui/MiniMap minMegaChunkY I 
L132:   isub 
L133:   imul 
L134:   istore 8 
L136:   aload 6 
L138:   iload 7 
L140:   i2f 
L141:   iload 8 
L143:   i2f 
L144:   invokevirtual Method com/badlogic/gdx/scenes/scene2d/ui/Image setPosition (FF)V 
L147:   aload_0 
L148:   getfield Field com/cairn4/moonbase/ui/MiniMap groupOffset Lcom/badlogic/gdx/scenes/scene2d/Group; 
L151:   aload 6 
L153:   invokevirtual Method com/badlogic/gdx/scenes/scene2d/Group addActor (Lcom/badlogic/gdx/scenes/scene2d/Actor;)V 
L156:   goto L17 

        .stack same_extended 
L159:   return 
L160:   
        .linenumbertable 
            L0 240 
            L4 242 
            L17 243 
            L26 244 
            L36 246 
            L51 248 
            L59 249 
            L67 251 
            L85 269 
            L104 270 
            L120 271 
            L136 272 
            L147 273 
            L156 277 
            L159 279 
        .end linenumbertable 
        .localvariabletable 
            2 is entry Ljava/util/Map$Entry; from L36 to L156 
            3 is coord [Ljava/lang/String; from L51 to L156 
            4 is mX I from L59 to L156 
            5 is mY I from L67 to L156 
            6 is i Lcom/badlogic/gdx/scenes/scene2d/ui/Image; from L85 to L156 
            7 is xPos I from L120 to L156 
            8 is yPos I from L136 to L156 
            0 is this Lcom/cairn4/moonbase/ui/MiniMap; from L0 to L160 
            1 is chunkIterator Ljava/util/Iterator; from L17 to L160 
        .end localvariabletable 
        .localvariabletypetable 
            2 is entry Ljava/util/Map$Entry<Ljava/lang/String;Lcom/badlogic/gdx/graphics/Texture;>; from L36 to L156 
            1 is chunkIterator Ljava/util/Iterator<Ljava/util/Map$Entry<Ljava/lang/String;Lcom/badlogic/gdx/graphics/Texture;>;>; from L17 to L160 
        .end localvariabletypetable 
    .end code 
.end method 

.method private addTileIcons : (II)V 
    .code stack 4 locals 13 
L0:     iload_1 
L1:     bipush 10 
L3:     imul 
L4:     istore_3 

        .stack append Integer 
L5:     iload_3 
L6:     iload_1 
L7:     bipush 10 
L9:     imul 
L10:    bipush 10 
L12:    iadd 
L13:    if_icmpge L674 
L16:    iload_1 
L17:    bipush 10 
L19:    imul 
L20:    istore 4 

        .stack append Integer 
L22:    iload 4 
L24:    iload_2 
L25:    bipush 10 
L27:    imul 
L28:    bipush 10 
L30:    iadd 
L31:    if_icmpge L668 
L34:    aload_0 
L35:    getfield Field com/cairn4/moonbase/ui/MiniMap gameScreen Lcom/cairn4/moonbase/ui/GameScreen; 
L38:    getfield Field com/cairn4/moonbase/ui/GameScreen world Lcom/cairn4/moonbase/World; 
L41:    iload_3 
L42:    iload 4 
L44:    invokevirtual Method com/cairn4/moonbase/World getChunk (II)Lcom/cairn4/moonbase/Chunk; 
L47:    astore 5 
L49:    aload 5 
L51:    ifnull L662 
L54:    iconst_0 
L55:    istore 6 

        .stack append Object com/cairn4/moonbase/Chunk Integer 
L57:    iload 6 
L59:    bipush 10 
L61:    if_icmpge L662 
L64:    iconst_0 
L65:    istore 7 

        .stack append Integer 
L67:    iload 7 
L69:    bipush 10 
L71:    if_icmpge L656 
L74:    aload_0 
L75:    getfield Field com/cairn4/moonbase/ui/MiniMap gameScreen Lcom/cairn4/moonbase/ui/GameScreen; 
L78:    getfield Field com/cairn4/moonbase/ui/GameScreen world Lcom/cairn4/moonbase/World; 
L81:    iload_3 
L82:    iload 4 
L84:    invokevirtual Method com/cairn4/moonbase/World chunkExists (II)Z 
L87:    ifeq L650 
L90:    aload 5 
L92:    iload 6 
L94:    iload 7 
L96:    invokevirtual Method com/cairn4/moonbase/Chunk getTile (II)Lcom/cairn4/moonbase/tiles/Tile; 
L99:    astore 8 
L101:   aload 8 
L103:   ifnull L650 
L106:   aload 8 
L108:   instanceof com/cairn4/moonbase/tiles/HabitatModule 
L111:   ifeq L277 
L114:   new com/badlogic/gdx/scenes/scene2d/ui/Image 
L117:   dup 
L118:   aload_0 
L119:   getfield Field com/cairn4/moonbase/ui/MiniMap skin Lcom/badlogic/gdx/scenes/scene2d/ui/Skin; 
L122:   ldc 'map/icons/habitat' 
L124:   invokevirtual Method com/badlogic/gdx/scenes/scene2d/ui/Skin getDrawable (Ljava/lang/String;)Lcom/badlogic/gdx/scenes/scene2d/utils/Drawable; 
L127:   invokespecial Method com/badlogic/gdx/scenes/scene2d/ui/Image <init> (Lcom/badlogic/gdx/scenes/scene2d/utils/Drawable;)V 
L130:   astore 9 
L132:   aload 9 
L134:   ldc +14.0f 
L136:   ldc +14.0f 
L138:   invokevirtual Method com/badlogic/gdx/scenes/scene2d/ui/Image setSize (FF)V 
L141:   aload 8 
L143:   getfield Field com/cairn4/moonbase/tiles/Tile worldX I 
L146:   i2f 
L147:   ldc +10.0f 
L149:   fdiv 
L150:   ldc +100.0f 
L152:   fmul 
L153:   aload_0 
L154:   getfield Field com/cairn4/moonbase/ui/MiniMap minMegaChunkX I 
L157:   bipush 10 
L159:   imul 
L160:   bipush 100 
L162:   imul 
L163:   iconst_2 
L164:   iadd 
L165:   i2f 
L166:   fsub 
L167:   fstore 10 
L169:   aload 8 
L171:   getfield Field com/cairn4/moonbase/tiles/Tile worldY I 
L174:   i2f 
L175:   ldc +10.0f 
L177:   fdiv 
L178:   ldc +100.0f 
L180:   fmul 
L181:   aload_0 
L182:   getfield Field com/cairn4/moonbase/ui/MiniMap minMegaChunkY I 
L185:   bipush 10 
L187:   imul 
L188:   bipush 100 
L190:   imul 
L191:   iconst_2 
L192:   iadd 
L193:   i2f 
L194:   fsub 
L195:   fstore 11 
L197:   getstatic Field java/lang/System out Ljava/io/PrintStream; 
L200:   new java/lang/StringBuilder 
L203:   dup 
L204:   invokespecial Method java/lang/StringBuilder <init> ()V 
L207:   ldc 'base: ' 
L209:   invokevirtual Method java/lang/StringBuilder append (Ljava/lang/String;)Ljava/lang/StringBuilder; 
L212:   aload 8 
L214:   getfield Field com/cairn4/moonbase/tiles/Tile worldX I 
L217:   invokevirtual Method java/lang/StringBuilder append (I)Ljava/lang/StringBuilder; 
L220:   ldc ',' 
L222:   invokevirtual Method java/lang/StringBuilder append (Ljava/lang/String;)Ljava/lang/StringBuilder; 
L225:   aload 8 
L227:   getfield Field com/cairn4/moonbase/tiles/Tile worldY I 
L230:   invokevirtual Method java/lang/StringBuilder append (I)Ljava/lang/StringBuilder; 
L233:   ldc '  --> ' 
L235:   invokevirtual Method java/lang/StringBuilder append (Ljava/lang/String;)Ljava/lang/StringBuilder; 
L238:   fload 10 
L240:   invokevirtual Method java/lang/StringBuilder append (F)Ljava/lang/StringBuilder; 
L243:   ldc ',' 
L245:   invokevirtual Method java/lang/StringBuilder append (Ljava/lang/String;)Ljava/lang/StringBuilder; 
L248:   fload 11 
L250:   invokevirtual Method java/lang/StringBuilder append (F)Ljava/lang/StringBuilder; 
L253:   invokevirtual Method java/lang/StringBuilder toString ()Ljava/lang/String; 
L256:   invokevirtual Method java/io/PrintStream println (Ljava/lang/String;)V 
L259:   aload 9 
L261:   fload 10 
L263:   fload 11 
L265:   invokevirtual Method com/badlogic/gdx/scenes/scene2d/ui/Image setPosition (FF)V 
L268:   aload_0 
L269:   getfield Field com/cairn4/moonbase/ui/MiniMap tileIconGroup Lcom/badlogic/gdx/scenes/scene2d/Group; 
L272:   aload 9 
L274:   invokevirtual Method com/badlogic/gdx/scenes/scene2d/Group addActor (Lcom/badlogic/gdx/scenes/scene2d/Actor;)V 

        .stack append Object com/cairn4/moonbase/tiles/Tile 
L277:   aload 8 
L279:   instanceof com/cairn4/moonbase/tiles/ItemDropper 
L282:   ifeq L650 
L285:   aload 8 
L287:   checkcast com/cairn4/moonbase/tiles/ItemDropper 
L290:   astore 9 
L292:   aload 9 
L294:   getfield Field com/cairn4/moonbase/tiles/ItemDropper rdData Lcom/cairn4/moonbase/worlddata/ItemDropperData; 
L297:   getfield Field com/cairn4/moonbase/worlddata/ItemDropperData id Ljava/lang/String; 
L300:   ldc 'plant' 
L302:   invokevirtual Method java/lang/String equals (Ljava/lang/Object;)Z 
L305:   ifeq L471 
L308:   new com/badlogic/gdx/scenes/scene2d/ui/Image 
L311:   dup 
L312:   aload_0 
L313:   getfield Field com/cairn4/moonbase/ui/MiniMap skin Lcom/badlogic/gdx/scenes/scene2d/ui/Skin; 
L316:   ldc 'map/icons/plant' 
L318:   invokevirtual Method com/badlogic/gdx/scenes/scene2d/ui/Skin getDrawable (Ljava/lang/String;)Lcom/badlogic/gdx/scenes/scene2d/utils/Drawable; 
L321:   invokespecial Method com/badlogic/gdx/scenes/scene2d/ui/Image <init> (Lcom/badlogic/gdx/scenes/scene2d/utils/Drawable;)V 
L324:   astore 10 
L326:   aload 10 
L328:   ldc +14.0f 
L330:   ldc +14.0f 
L332:   invokevirtual Method com/badlogic/gdx/scenes/scene2d/ui/Image setSize (FF)V 
L335:   aload 8 
L337:   getfield Field com/cairn4/moonbase/tiles/Tile worldX I 
L340:   i2f 
L341:   ldc +10.0f 
L343:   fdiv 
L344:   ldc +100.0f 
L346:   fmul 
L347:   aload_0 
L348:   getfield Field com/cairn4/moonbase/ui/MiniMap minMegaChunkX I 
L351:   bipush 10 
L353:   imul 
L354:   bipush 100 
L356:   imul 
L357:   iconst_2 
L358:   iadd 
L359:   i2f 
L360:   fsub 
L361:   fstore 11 
L363:   aload 8 
L365:   getfield Field com/cairn4/moonbase/tiles/Tile worldY I 
L368:   i2f 
L369:   ldc +10.0f 
L371:   fdiv 
L372:   ldc +100.0f 
L374:   fmul 
L375:   aload_0 
L376:   getfield Field com/cairn4/moonbase/ui/MiniMap minMegaChunkY I 
L379:   bipush 10 
L381:   imul 
L382:   bipush 100 
L384:   imul 
L385:   iconst_2 
L386:   iadd 
L387:   i2f 
L388:   fsub 
L389:   fstore 12 
L391:   getstatic Field java/lang/System out Ljava/io/PrintStream; 
L394:   new java/lang/StringBuilder 
L397:   dup 
L398:   invokespecial Method java/lang/StringBuilder <init> ()V 
L401:   ldc 'plant: ' 
L403:   invokevirtual Method java/lang/StringBuilder append (Ljava/lang/String;)Ljava/lang/StringBuilder; 
L406:   aload 8 
L408:   getfield Field com/cairn4/moonbase/tiles/Tile worldX I 
L411:   invokevirtual Method java/lang/StringBuilder append (I)Ljava/lang/StringBuilder; 
L414:   ldc ',' 
L416:   invokevirtual Method java/lang/StringBuilder append (Ljava/lang/String;)Ljava/lang/StringBuilder; 
L419:   aload 8 
L421:   getfield Field com/cairn4/moonbase/tiles/Tile worldY I 
L424:   invokevirtual Method java/lang/StringBuilder append (I)Ljava/lang/StringBuilder; 
L427:   ldc '  --> ' 
L429:   invokevirtual Method java/lang/StringBuilder append (Ljava/lang/String;)Ljava/lang/StringBuilder; 
L432:   fload 11 
L434:   invokevirtual Method java/lang/StringBuilder append (F)Ljava/lang/StringBuilder; 
L437:   ldc ',' 
L439:   invokevirtual Method java/lang/StringBuilder append (Ljava/lang/String;)Ljava/lang/StringBuilder; 
L442:   fload 12 
L444:   invokevirtual Method java/lang/StringBuilder append (F)Ljava/lang/StringBuilder; 
L447:   invokevirtual Method java/lang/StringBuilder toString ()Ljava/lang/String; 
L450:   invokevirtual Method java/io/PrintStream println (Ljava/lang/String;)V 
L453:   aload 10 
L455:   fload 11 
L457:   fload 12 
L459:   invokevirtual Method com/badlogic/gdx/scenes/scene2d/ui/Image setPosition (FF)V 
L462:   aload_0 
L463:   getfield Field com/cairn4/moonbase/ui/MiniMap tileIconGroup Lcom/badlogic/gdx/scenes/scene2d/Group; 
L466:   aload 10 
L468:   invokevirtual Method com/badlogic/gdx/scenes/scene2d/Group addActor (Lcom/badlogic/gdx/scenes/scene2d/Actor;)V 

        .stack append Object com/cairn4/moonbase/tiles/ItemDropper 
L471:   aload 9 
L473:   getfield Field com/cairn4/moonbase/tiles/ItemDropper rdData Lcom/cairn4/moonbase/worlddata/ItemDropperData; 
L476:   getfield Field com/cairn4/moonbase/worlddata/ItemDropperData id Ljava/lang/String; 
L479:   ldc 'rock' 
L481:   invokevirtual Method java/lang/String equals (Ljava/lang/Object;)Z 
L484:   ifeq L650 
L487:   new com/badlogic/gdx/scenes/scene2d/ui/Image 
L490:   dup 
L491:   aload_0 
L492:   getfield Field com/cairn4/moonbase/ui/MiniMap skin Lcom/badlogic/gdx/scenes/scene2d/ui/Skin; 
L495:   ldc 'map/icons/big-rock' 
L497:   invokevirtual Method com/badlogic/gdx/scenes/scene2d/ui/Skin getDrawable (Ljava/lang/String;)Lcom/badlogic/gdx/scenes/scene2d/utils/Drawable; 
L500:   invokespecial Method com/badlogic/gdx/scenes/scene2d/ui/Image <init> (Lcom/badlogic/gdx/scenes/scene2d/utils/Drawable;)V 
L503:   astore 10 
L505:   aload 10 
L507:   ldc +14.0f 
L509:   ldc +14.0f 
L511:   invokevirtual Method com/badlogic/gdx/scenes/scene2d/ui/Image setSize (FF)V 
L514:   aload 8 
L516:   getfield Field com/cairn4/moonbase/tiles/Tile worldX I 
L519:   i2f 
L520:   ldc +10.0f 
L522:   fdiv 
L523:   ldc +100.0f 
L525:   fmul 
L526:   aload_0 
L527:   getfield Field com/cairn4/moonbase/ui/MiniMap minMegaChunkX I 
L530:   bipush 10 
L532:   imul 
L533:   bipush 100 
L535:   imul 
L536:   iconst_2 
L537:   iadd 
L538:   i2f 
L539:   fsub 
L540:   fstore 11 
L542:   aload 8 
L544:   getfield Field com/cairn4/moonbase/tiles/Tile worldY I 
L547:   i2f 
L548:   ldc +10.0f 
L550:   fdiv 
L551:   ldc +100.0f 
L553:   fmul 
L554:   aload_0 
L555:   getfield Field com/cairn4/moonbase/ui/MiniMap minMegaChunkY I 
L558:   bipush 10 
L560:   imul 
L561:   bipush 100 
L563:   imul 
L564:   iconst_2 
L565:   iadd 
L566:   i2f 
L567:   fsub 
L568:   fstore 12 
L570:   getstatic Field java/lang/System out Ljava/io/PrintStream; 
L573:   new java/lang/StringBuilder 
L576:   dup 
L577:   invokespecial Method java/lang/StringBuilder <init> ()V 
L580:   ldc 'rock: ' 
L582:   invokevirtual Method java/lang/StringBuilder append (Ljava/lang/String;)Ljava/lang/StringBuilder; 
L585:   aload 8 
L587:   getfield Field com/cairn4/moonbase/tiles/Tile worldX I 
L590:   invokevirtual Method java/lang/StringBuilder append (I)Ljava/lang/StringBuilder; 
L593:   ldc ',' 
L595:   invokevirtual Method java/lang/StringBuilder append (Ljava/lang/String;)Ljava/lang/StringBuilder; 
L598:   aload 8 
L600:   getfield Field com/cairn4/moonbase/tiles/Tile worldY I 
L603:   invokevirtual Method java/lang/StringBuilder append (I)Ljava/lang/StringBuilder; 
L606:   ldc '  --> ' 
L608:   invokevirtual Method java/lang/StringBuilder append (Ljava/lang/String;)Ljava/lang/StringBuilder; 
L611:   fload 11 
L613:   invokevirtual Method java/lang/StringBuilder append (F)Ljava/lang/StringBuilder; 
L616:   ldc ',' 
L618:   invokevirtual Method java/lang/StringBuilder append (Ljava/lang/String;)Ljava/lang/StringBuilder; 
L621:   fload 12 
L623:   invokevirtual Method java/lang/StringBuilder append (F)Ljava/lang/StringBuilder; 
L626:   invokevirtual Method java/lang/StringBuilder toString ()Ljava/lang/String; 
L629:   invokevirtual Method java/io/PrintStream println (Ljava/lang/String;)V 
L632:   aload 10 
L634:   fload 11 
L636:   fload 12 
L638:   invokevirtual Method com/badlogic/gdx/scenes/scene2d/ui/Image setPosition (FF)V 
L641:   aload_0 
L642:   getfield Field com/cairn4/moonbase/ui/MiniMap tileIconGroup Lcom/badlogic/gdx/scenes/scene2d/Group; 
L645:   aload 10 
L647:   invokevirtual Method com/badlogic/gdx/scenes/scene2d/Group addActor (Lcom/badlogic/gdx/scenes/scene2d/Actor;)V 

        .stack chop 2 
L650:   iinc 7 1 
L653:   goto L67 

        .stack chop 1 
L656:   iinc 6 1 
L659:   goto L57 

        .stack chop 2 
L662:   iinc 4 1 
L665:   goto L22 

        .stack chop 1 
L668:   iinc 3 1 
L671:   goto L5 

        .stack chop 1 
L674:   return 
L675:   
        .linenumbertable 
            L0 284 
            L16 285 
            L34 286 
            L49 287 
            L54 288 
            L64 289 
            L74 290 
            L90 291 
            L101 292 
            L106 293 
            L114 294 
            L132 295 
            L141 297 
            L169 298 
            L197 299 
            L259 302 
            L268 303 
            L277 307 
            L285 308 
            L292 309 
            L308 311 
            L326 312 
            L335 314 
            L363 315 
            L391 316 
            L453 319 
            L462 320 
            L471 324 
            L487 326 
            L505 327 
            L514 329 
            L542 330 
            L570 331 
            L632 334 
            L641 335 
            L650 289 
            L656 288 
            L662 285 
            L668 284 
            L674 345 
        .end linenumbertable 
        .localvariabletable 
            9 is baseIcon Lcom/badlogic/gdx/scenes/scene2d/ui/Image; from L132 to L277 
            10 is tx F from L169 to L277 
            11 is ty F from L197 to L277 
            10 is baseIcon Lcom/badlogic/gdx/scenes/scene2d/ui/Image; from L326 to L471 
            11 is tx F from L363 to L471 
            12 is ty F from L391 to L471 
            10 is baseIcon Lcom/badlogic/gdx/scenes/scene2d/ui/Image; from L505 to L650 
            11 is tx F from L542 to L650 
            12 is ty F from L570 to L650 
            9 is id Lcom/cairn4/moonbase/tiles/ItemDropper; from L292 to L650 
            8 is t Lcom/cairn4/moonbase/tiles/Tile; from L101 to L650 
            7 is y I from L67 to L656 
            6 is x I from L57 to L662 
            5 is c Lcom/cairn4/moonbase/Chunk; from L49 to L662 
            4 is cy I from L22 to L668 
            3 is cx I from L5 to L674 
            0 is this Lcom/cairn4/moonbase/ui/MiniMap; from L0 to L675 
            1 is superChunkX I from L0 to L675 
            2 is superChunkY I from L0 to L675 
        .end localvariabletable 
    .end code 
.end method 

.method private playMapTileLoadSound : ()V 
    .code stack 4 locals 1 
L0:     aload_0 
L1:     aload_0 
L2:     getfield Field com/cairn4/moonbase/ui/MiniMap soundBasePitch F 
L5:     aload_0 
L6:     getfield Field com/cairn4/moonbase/ui/MiniMap soundPitchVar F 
L9:     fsub 
L10:    aload_0 
L11:    getfield Field com/cairn4/moonbase/ui/MiniMap soundBasePitch F 
L14:    aload_0 
L15:    getfield Field com/cairn4/moonbase/ui/MiniMap soundPitchVar F 
L18:    fadd 
L19:    invokestatic Method com/badlogic/gdx/math/MathUtils random (FF)F 
L22:    putfield Field com/cairn4/moonbase/ui/MiniMap soundPitch F 
L25:    invokestatic Method com/cairn4/moonbase/Audio getInstance ()Lcom/cairn4/moonbase/Audio; 
L28:    ldc 'sounds/textAnimator2.ogg' 
L30:    aload_0 
L31:    getfield Field com/cairn4/moonbase/ui/MiniMap soundVolume F 
L34:    aload_0 
L35:    getfield Field com/cairn4/moonbase/ui/MiniMap soundPitch F 
L38:    invokevirtual Method com/cairn4/moonbase/Audio playSound (Ljava/lang/String;FF)J 
L41:    pop2 
L42:    return 
L43:    
        .linenumbertable 
            L0 356 
            L25 357 
            L42 358 
        .end linenumbertable 
        .localvariabletable 
            0 is this Lcom/cairn4/moonbase/ui/MiniMap; from L0 to L43 
        .end localvariabletable 
    .end code 
.end method 

.method private showDisasters : (IIII)V 
    .code stack 7 locals 15 
L0:     new com/badlogic/gdx/math/Rectangle 
L3:     dup 
L4:     iload_1 
L5:     bipush 10 
L7:     imul 
L8:     iconst_1 
L9:     isub 
L10:    i2f 
L11:    iload_2 
L12:    bipush 10 
L14:    imul 
L15:    iconst_1 
L16:    isub 
L17:    i2f 
L18:    iload_3 
L19:    bipush 10 
L21:    imul 
L22:    iconst_1 
L23:    iadd 
L24:    i2f 
L25:    iload 4 
L27:    bipush 10 
L29:    imul 
L30:    iconst_1 
L31:    iadd 
L32:    i2f 
L33:    invokespecial Method com/badlogic/gdx/math/Rectangle <init> (FFFF)V 
L36:    astore 5 
L38:    aload_0 
L39:    getfield Field com/cairn4/moonbase/ui/MiniMap gameScreen Lcom/cairn4/moonbase/ui/GameScreen; 
L42:    getfield Field com/cairn4/moonbase/ui/GameScreen world Lcom/cairn4/moonbase/World; 
L45:    getfield Field com/cairn4/moonbase/World baseManager Lcom/cairn4/moonbase/BaseManager; 
L48:    invokevirtual Method com/cairn4/moonbase/BaseManager getBaseGroupList ()Ljava/util/ArrayList; 
L51:    invokevirtual Method java/util/ArrayList iterator ()Ljava/util/Iterator; 
L54:    astore 6 

        .stack append Object com/badlogic/gdx/math/Rectangle Object java/util/Iterator 
L56:    aload 6 
L58:    invokeinterface InterfaceMethod java/util/Iterator hasNext ()Z 1 
L63:    ifeq L344 
L66:    aload 6 
L68:    invokeinterface InterfaceMethod java/util/Iterator next ()Ljava/lang/Object; 1 
L73:    checkcast com/cairn4/moonbase/BaseGroup 
L76:    astore 7 
L78:    aload 7 
L80:    getfield Field com/cairn4/moonbase/BaseGroup baseModuleList Ljava/util/ArrayList; 
L83:    invokevirtual Method java/util/ArrayList iterator ()Ljava/util/Iterator; 
L86:    astore 8 

        .stack append Object com/cairn4/moonbase/BaseGroup Object java/util/Iterator 
L88:    aload 8 
L90:    invokeinterface InterfaceMethod java/util/Iterator hasNext ()Z 1 
L95:    ifeq L341 
L98:    aload 8 
L100:   invokeinterface InterfaceMethod java/util/Iterator next ()Ljava/lang/Object; 1 
L105:   checkcast com/cairn4/moonbase/tiles/BaseModule 
L108:   astore 9 
L110:   aload 9 
L112:   getfield Field com/cairn4/moonbase/tiles/BaseModule baseDisaster Lcom/cairn4/moonbase/tiles/disasters/BaseDisaster; 
L115:   ifnull L338 
L118:   aload 5 
L120:   aload 9 
L122:   getfield Field com/cairn4/moonbase/tiles/BaseModule worldX I 
L125:   i2f 
L126:   aload 9 
L128:   getfield Field com/cairn4/moonbase/tiles/BaseModule worldY I 
L131:   i2f 
L132:   invokevirtual Method com/badlogic/gdx/math/Rectangle contains (FF)Z 
L135:   ifeq L338 
L138:   getstatic Field java/lang/System out Ljava/io/PrintStream; 
L141:   new java/lang/StringBuilder 
L144:   dup 
L145:   invokespecial Method java/lang/StringBuilder <init> ()V 
L148:   ldc 'Found disaster at : ' 
L150:   invokevirtual Method java/lang/StringBuilder append (Ljava/lang/String;)Ljava/lang/StringBuilder; 
L153:   aload 9 
L155:   getfield Field com/cairn4/moonbase/tiles/BaseModule worldX I 
L158:   invokevirtual Method java/lang/StringBuilder append (I)Ljava/lang/StringBuilder; 
L161:   ldc ', ' 
L163:   invokevirtual Method java/lang/StringBuilder append (Ljava/lang/String;)Ljava/lang/StringBuilder; 
L166:   aload 9 
L168:   getfield Field com/cairn4/moonbase/tiles/BaseModule worldY I 
L171:   invokevirtual Method java/lang/StringBuilder append (I)Ljava/lang/StringBuilder; 
L174:   invokevirtual Method java/lang/StringBuilder toString ()Ljava/lang/String; 
L177:   invokevirtual Method java/io/PrintStream println (Ljava/lang/String;)V 
L180:   new com/badlogic/gdx/scenes/scene2d/ui/Image 
L183:   dup 
L184:   aload_0 
L185:   getfield Field com/cairn4/moonbase/ui/MiniMap gameScreen Lcom/cairn4/moonbase/ui/GameScreen; 
L188:   getfield Field com/cairn4/moonbase/ui/GameScreen skin Lcom/badlogic/gdx/scenes/scene2d/ui/Skin; 
L191:   ldc 'white' 
L193:   invokevirtual Method com/badlogic/gdx/scenes/scene2d/ui/Skin getDrawable (Ljava/lang/String;)Lcom/badlogic/gdx/scenes/scene2d/utils/Drawable; 
L196:   invokespecial Method com/badlogic/gdx/scenes/scene2d/ui/Image <init> (Lcom/badlogic/gdx/scenes/scene2d/utils/Drawable;)V 
L199:   astore 10 
L201:   aload 10 
L203:   ldc +10.0f 
L205:   ldc +10.0f 
L207:   invokevirtual Method com/badlogic/gdx/scenes/scene2d/ui/Image setSize (FF)V 
L210:   aload 10 
L212:   iconst_1 
L213:   invokevirtual Method com/badlogic/gdx/scenes/scene2d/ui/Image setOrigin (I)V 
L216:   aload 10 
L218:   getstatic Field com/badlogic/gdx/graphics/Color RED Lcom/badlogic/gdx/graphics/Color; 
L221:   invokevirtual Method com/badlogic/gdx/scenes/scene2d/ui/Image setColor (Lcom/badlogic/gdx/graphics/Color;)V 
L224:   aload 10 
L226:   ldc +45.0f 
L228:   invokevirtual Method com/badlogic/gdx/scenes/scene2d/ui/Image setRotation (F)V 
L231:   aload_0 
L232:   getfield Field com/cairn4/moonbase/ui/MiniMap groupOffset Lcom/badlogic/gdx/scenes/scene2d/Group; 
L235:   aload 10 
L237:   invokevirtual Method com/badlogic/gdx/scenes/scene2d/Group addActor (Lcom/badlogic/gdx/scenes/scene2d/Actor;)V 
L240:   aload 9 
L242:   getfield Field com/cairn4/moonbase/tiles/BaseModule worldX I 
L245:   i2f 
L246:   ldc +10.0f 
L248:   fdiv 
L249:   iload_1 
L250:   i2f 
L251:   fsub 
L252:   fstore 11 
L254:   fload 11 
L256:   ldc +100.0f 
L258:   fmul 
L259:   fstore 12 
L261:   aload 9 
L263:   getfield Field com/cairn4/moonbase/tiles/BaseModule worldY I 
L266:   i2f 
L267:   ldc +10.0f 
L269:   fdiv 
L270:   iload_2 
L271:   i2f 
L272:   fsub 
L273:   fstore 13 
L275:   fload 13 
L277:   ldc +100.0f 
L279:   fmul 
L280:   fstore 14 
L282:   aload 10 
L284:   fload 12 
L286:   fload 14 
L288:   bipush 12 
L290:   invokevirtual Method com/badlogic/gdx/scenes/scene2d/ui/Image setPosition (FFI)V 
L293:   aload 10 
L295:   fconst_1 
L296:   fconst_1 
L297:   invokestatic Method com/badlogic/gdx/scenes/scene2d/actions/Actions scaleTo (FF)Lcom/badlogic/gdx/scenes/scene2d/actions/ScaleToAction; 
L300:   fconst_1 
L301:   invokestatic Method com/badlogic/gdx/scenes/scene2d/actions/Actions alpha (F)Lcom/badlogic/gdx/scenes/scene2d/actions/AlphaAction; 
L304:   ldc +8.0f 
L306:   ldc +8.0f 
L308:   ldc +0.4000000059604645f 
L310:   getstatic Field com/badlogic/gdx/math/Interpolation sine Lcom/badlogic/gdx/math/Interpolation; 
L313:   invokestatic Method com/badlogic/gdx/scenes/scene2d/actions/Actions scaleTo (FFFLcom/badlogic/gdx/math/Interpolation;)Lcom/badlogic/gdx/scenes/scene2d/actions/ScaleToAction; 
L316:   ldc +0.4000000059604645f 
L318:   invokestatic Method com/badlogic/gdx/scenes/scene2d/actions/Actions fadeOut (F)Lcom/badlogic/gdx/scenes/scene2d/actions/AlphaAction; 
L321:   invokestatic Method com/badlogic/gdx/scenes/scene2d/actions/Actions parallel (Lcom/badlogic/gdx/scenes/scene2d/Action;Lcom/badlogic/gdx/scenes/scene2d/Action;)Lcom/badlogic/gdx/scenes/scene2d/actions/ParallelAction; 
L324:   ldc +0.4000000059604645f 
L326:   invokestatic Method com/badlogic/gdx/scenes/scene2d/actions/Actions delay (F)Lcom/badlogic/gdx/scenes/scene2d/actions/DelayAction; 
L329:   invokestatic Method com/badlogic/gdx/scenes/scene2d/actions/Actions sequence (Lcom/badlogic/gdx/scenes/scene2d/Action;Lcom/badlogic/gdx/scenes/scene2d/Action;Lcom/badlogic/gdx/scenes/scene2d/Action;Lcom/badlogic/gdx/scenes/scene2d/Action;)Lcom/badlogic/gdx/scenes/scene2d/actions/SequenceAction; 
L332:   invokestatic Method com/badlogic/gdx/scenes/scene2d/actions/Actions forever (Lcom/badlogic/gdx/scenes/scene2d/Action;)Lcom/badlogic/gdx/scenes/scene2d/actions/RepeatAction; 
L335:   invokevirtual Method com/badlogic/gdx/scenes/scene2d/ui/Image addAction (Lcom/badlogic/gdx/scenes/scene2d/Action;)V 

        .stack same_extended 
L338:   goto L88 

        .stack chop 2 
L341:   goto L56 

        .stack chop 1 
L344:   return 
L345:   
        .linenumbertable 
            L0 364 
            L38 371 
            L78 373 
            L110 375 
            L118 378 
            L138 380 
            L180 383 
            L201 384 
            L210 385 
            L216 386 
            L224 387 
            L231 388 
            L240 390 
            L254 391 
            L261 393 
            L275 394 
            L282 396 
            L293 398 
            L297 400 
            L301 401 
            L313 403 
            L318 404 
            L321 402 
            L326 406 
            L329 399 
            L332 398 
            L338 412 
            L341 413 
            L344 414 
        .end linenumbertable 
        .localvariabletable 
            10 is disasterBase Lcom/badlogic/gdx/scenes/scene2d/ui/Image; from L201 to L338 
            11 is tX F from L254 to L338 
            12 is drawX F from L261 to L338 
            13 is tY F from L275 to L338 
            14 is drawY F from L282 to L338 
            9 is b Lcom/cairn4/moonbase/tiles/BaseModule; from L110 to L338 
            7 is g Lcom/cairn4/moonbase/BaseGroup; from L78 to L341 
            0 is this Lcom/cairn4/moonbase/ui/MiniMap; from L0 to L345 
            1 is minChunkX I from L0 to L345 
            2 is minChunkY I from L0 to L345 
            3 is horzChunks I from L0 to L345 
            4 is vertChunks I from L0 to L345 
            5 is mapLimitCoords Lcom/badlogic/gdx/math/Rectangle; from L38 to L345 
        .end localvariabletable 
    .end code 
.end method 

.method private showBuggies : ()V 
    .code stack 4 locals 7 
L0:     aload_0 
L1:     getfield Field com/cairn4/moonbase/ui/MiniMap gameScreen Lcom/cairn4/moonbase/ui/GameScreen; 
L4:     getfield Field com/cairn4/moonbase/ui/GameScreen world Lcom/cairn4/moonbase/World; 
L7:     getfield Field com/cairn4/moonbase/World entityList Ljava/util/ArrayList; 
L10:    invokevirtual Method java/util/ArrayList iterator ()Ljava/util/Iterator; 
L13:    astore_1 

        .stack append Object java/util/Iterator 
L14:    aload_1 
L15:    invokeinterface InterfaceMethod java/util/Iterator hasNext ()Z 1 
L20:    ifeq L221 
L23:    aload_1 
L24:    invokeinterface InterfaceMethod java/util/Iterator next ()Ljava/lang/Object; 1 
L29:    checkcast com/cairn4/moonbase/Entity 
L32:    astore_2 
L33:    aload_2 
L34:    instanceof com/cairn4/moonbase/Buggie 
L37:    ifne L47 
L40:    aload_2 
L41:    instanceof com/cairn4/moonbase/Tank 
L44:    ifeq L218 

        .stack append Object com/cairn4/moonbase/Entity 
L47:    aload_2 
L48:    checkcast com/cairn4/moonbase/Vehicle 
L51:    astore_3 
L52:    getstatic Field com/badlogic/gdx/Gdx app Lcom/badlogic/gdx/Application; 
L55:    ldc 'MewnBase' 
L57:    new java/lang/StringBuilder 
L60:    dup 
L61:    invokespecial Method java/lang/StringBuilder <init> ()V 
L64:    ldc 'Adding buggie/tank to map at: ' 
L66:    invokevirtual Method java/lang/StringBuilder append (Ljava/lang/String;)Ljava/lang/StringBuilder; 
L69:    aload_3 
L70:    invokevirtual Method com/cairn4/moonbase/Vehicle getWorldXTile ()I 
L73:    invokevirtual Method java/lang/StringBuilder append (I)Ljava/lang/StringBuilder; 
L76:    ldc ', ' 
L78:    invokevirtual Method java/lang/StringBuilder append (Ljava/lang/String;)Ljava/lang/StringBuilder; 
L81:    aload_3 
L82:    invokevirtual Method com/cairn4/moonbase/Vehicle getWorldYTile ()I 
L85:    invokevirtual Method java/lang/StringBuilder append (I)Ljava/lang/StringBuilder; 
L88:    invokevirtual Method java/lang/StringBuilder toString ()Ljava/lang/String; 
L91:    invokeinterface InterfaceMethod com/badlogic/gdx/Application debug (Ljava/lang/String;Ljava/lang/String;)V 3 
L96:    new com/badlogic/gdx/scenes/scene2d/Group 
L99:    dup 
L100:   invokespecial Method com/badlogic/gdx/scenes/scene2d/Group <init> ()V 
L103:   astore 4 
L105:   aload_0 
L106:   getfield Field com/cairn4/moonbase/ui/MiniMap groupOffset Lcom/badlogic/gdx/scenes/scene2d/Group; 
L109:   aload 4 
L111:   invokevirtual Method com/badlogic/gdx/scenes/scene2d/Group addActor (Lcom/badlogic/gdx/scenes/scene2d/Actor;)V 
L114:   new com/badlogic/gdx/scenes/scene2d/ui/Image 
L117:   dup 
L118:   aload_0 
L119:   getfield Field com/cairn4/moonbase/ui/MiniMap gameScreen Lcom/cairn4/moonbase/ui/GameScreen; 
L122:   getfield Field com/cairn4/moonbase/ui/GameScreen skin Lcom/badlogic/gdx/scenes/scene2d/ui/Skin; 
L125:   ldc 'map/icons/map-buggie-icon' 
L127:   invokevirtual Method com/badlogic/gdx/scenes/scene2d/ui/Skin getDrawable (Ljava/lang/String;)Lcom/badlogic/gdx/scenes/scene2d/utils/Drawable; 
L130:   invokespecial Method com/badlogic/gdx/scenes/scene2d/ui/Image <init> (Lcom/badlogic/gdx/scenes/scene2d/utils/Drawable;)V 
L133:   astore 5 
L135:   aload 5 
L137:   ldc +32.0f 
L139:   ldc +32.0f 
L141:   invokevirtual Method com/badlogic/gdx/scenes/scene2d/ui/Image setSize (FF)V 
L144:   aload 5 
L146:   iconst_1 
L147:   invokevirtual Method com/badlogic/gdx/scenes/scene2d/ui/Image setOrigin (I)V 
L150:   aload 5 
L152:   aload_3 
L153:   invokevirtual Method com/cairn4/moonbase/Vehicle getRotation ()F 
L156:   invokevirtual Method com/badlogic/gdx/scenes/scene2d/ui/Image setRotation (F)V 
L159:   aload 5 
L161:   getstatic Field com/badlogic/gdx/graphics/Color WHITE Lcom/badlogic/gdx/graphics/Color; 
L164:   invokevirtual Method com/badlogic/gdx/scenes/scene2d/ui/Image setColor (Lcom/badlogic/gdx/graphics/Color;)V 
L167:   aload 5 
L169:   fconst_0 
L170:   fconst_0 
L171:   iconst_1 
L172:   invokevirtual Method com/badlogic/gdx/scenes/scene2d/ui/Image setPosition (FFI)V 
L175:   aload 4 
L177:   aload 5 
L179:   invokevirtual Method com/badlogic/gdx/scenes/scene2d/Group addActor (Lcom/badlogic/gdx/scenes/scene2d/Actor;)V 
L182:   aload_0 
L183:   aload_3 
L184:   invokevirtual Method com/cairn4/moonbase/Vehicle getWorldXTile ()I 
L187:   aload_3 
L188:   invokevirtual Method com/cairn4/moonbase/Vehicle getWorldYTile ()I 
L191:   invokespecial Method com/cairn4/moonbase/ui/MiniMap worldTileToMapPos (II)Lcom/badlogic/gdx/math/Vector2; 
L194:   astore 6 
L196:   aload 4 
L198:   aload 6 
L200:   getfield Field com/badlogic/gdx/math/Vector2 x F 
L203:   ldc +5.0f 
L205:   fadd 
L206:   aload 6 
L208:   getfield Field com/badlogic/gdx/math/Vector2 y F 
L211:   ldc +5.0f 
L213:   fadd 
L214:   iconst_1 
L215:   invokevirtual Method com/badlogic/gdx/scenes/scene2d/Group setPosition (FFI)V 

        .stack chop 1 
L218:   goto L14 

        .stack chop 1 
L221:   return 
L222:   
        .linenumbertable 
            L0 420 
            L33 421 
            L47 423 
            L52 425 
            L96 427 
            L105 428 
            L114 430 
            L135 432 
            L144 433 
            L150 435 
            L159 436 
            L167 437 
            L175 438 
            L182 440 
            L196 442 
            L218 444 
            L221 450 
        .end linenumbertable 
        .localvariabletable 
            3 is vehicle Lcom/cairn4/moonbase/Vehicle; from L52 to L218 
            4 is buggieGroup Lcom/badlogic/gdx/scenes/scene2d/Group; from L105 to L218 
            5 is buggieIcon Lcom/badlogic/gdx/scenes/scene2d/ui/Image; from L135 to L218 
            6 is buggieMapPos Lcom/badlogic/gdx/math/Vector2; from L196 to L218 
            2 is e Lcom/cairn4/moonbase/Entity; from L33 to L218 
            0 is this Lcom/cairn4/moonbase/ui/MiniMap; from L0 to L222 
        .end localvariabletable 
    .end code 
.end method 

.method private showLander : (FF)V 
    .code stack 7 locals 7 
L0:     new com/badlogic/gdx/math/Rectangle 
L3:     dup 
L4:     getstatic Field com/cairn4/moonbase/MoonBase SCREEN_WIDTH I 
L7:     iconst_2 
L8:     idiv 
L9:     i2f 
L10:    getstatic Field com/cairn4/moonbase/MoonBase SCREEN_HEIGHT I 
L13:    iconst_2 
L14:    idiv 
L15:    i2f 
L16:    getstatic Field com/cairn4/moonbase/MoonBase SCREEN_WIDTH I 
L19:    bipush 90 
L21:    isub 
L22:    i2f 
L23:    getstatic Field com/cairn4/moonbase/MoonBase SCREEN_HEIGHT I 
L26:    bipush 90 
L28:    isub 
L29:    i2f 
L30:    invokespecial Method com/badlogic/gdx/math/Rectangle <init> (FFFF)V 
L33:    astore_3 
L34:    new com/badlogic/gdx/scenes/scene2d/ui/Image 
L37:    dup 
L38:    aload_0 
L39:    getfield Field com/cairn4/moonbase/ui/MiniMap gameScreen Lcom/cairn4/moonbase/ui/GameScreen; 
L42:    getfield Field com/cairn4/moonbase/ui/GameScreen skin Lcom/badlogic/gdx/scenes/scene2d/ui/Skin; 
L45:    ldc 'map/icons/map-lander-icon' 
L47:    invokevirtual Method com/badlogic/gdx/scenes/scene2d/ui/Skin getDrawable (Ljava/lang/String;)Lcom/badlogic/gdx/scenes/scene2d/utils/Drawable; 
L50:    invokespecial Method com/badlogic/gdx/scenes/scene2d/ui/Image <init> (Lcom/badlogic/gdx/scenes/scene2d/utils/Drawable;)V 
L53:    astore 4 
L55:    aload 4 
L57:    ldc +50.0f 
L59:    ldc +50.0f 
L61:    invokevirtual Method com/badlogic/gdx/scenes/scene2d/ui/Image setSize (FF)V 
L64:    aload 4 
L66:    iconst_1 
L67:    invokevirtual Method com/badlogic/gdx/scenes/scene2d/ui/Image setOrigin (I)V 
L70:    aload_0 
L71:    getfield Field com/cairn4/moonbase/ui/MiniMap groupOffset Lcom/badlogic/gdx/scenes/scene2d/Group; 
L74:    aload 4 
L76:    invokevirtual Method com/badlogic/gdx/scenes/scene2d/Group addActor (Lcom/badlogic/gdx/scenes/scene2d/Actor;)V 
L79:    aload_0 
L80:    getfield Field com/cairn4/moonbase/ui/MiniMap gameScreen Lcom/cairn4/moonbase/ui/GameScreen; 
L83:    getfield Field com/cairn4/moonbase/ui/GameScreen world Lcom/cairn4/moonbase/World; 
L86:    pop 
L87:    aload_0 
L88:    getfield Field com/cairn4/moonbase/ui/MiniMap gameScreen Lcom/cairn4/moonbase/ui/GameScreen; 
L91:    getfield Field com/cairn4/moonbase/ui/GameScreen world Lcom/cairn4/moonbase/World; 
L94:    getfield Field com/cairn4/moonbase/World lander Lcom/cairn4/moonbase/tiles/Lander; 
L97:    getfield Field com/cairn4/moonbase/tiles/Lander worldX I 
L100:   aload_0 
L101:   getfield Field com/cairn4/moonbase/ui/MiniMap gameScreen Lcom/cairn4/moonbase/ui/GameScreen; 
L104:   getfield Field com/cairn4/moonbase/ui/GameScreen world Lcom/cairn4/moonbase/World; 
L107:   getfield Field com/cairn4/moonbase/World lander Lcom/cairn4/moonbase/tiles/Lander; 
L110:   getfield Field com/cairn4/moonbase/tiles/Lander worldY I 
L113:   invokestatic Method com/cairn4/moonbase/World getGridPointFromPoolAndSet (II)Lcom/badlogic/gdx/math/GridPoint2; 
L116:   astore 5 
L118:   aload_0 
L119:   aload 5 
L121:   getfield Field com/badlogic/gdx/math/GridPoint2 x I 
L124:   aload 5 
L126:   getfield Field com/badlogic/gdx/math/GridPoint2 y I 
L129:   invokespecial Method com/cairn4/moonbase/ui/MiniMap worldTileToMapPos (II)Lcom/badlogic/gdx/math/Vector2; 
L132:   astore 6 
L134:   aload 4 
L136:   aload 6 
L138:   getfield Field com/badlogic/gdx/math/Vector2 x F 
L141:   ldc +5.0f 
L143:   fadd 
L144:   aload 6 
L146:   getfield Field com/badlogic/gdx/math/Vector2 y F 
L149:   ldc +5.0f 
L151:   fadd 
L152:   iconst_1 
L153:   invokevirtual Method com/badlogic/gdx/scenes/scene2d/ui/Image setPosition (FFI)V 
L156:   return 
L157:   
        .linenumbertable 
            L0 455 
            L34 463 
            L55 464 
            L64 465 
            L70 466 
            L79 468 
            L118 469 
            L134 470 
            L156 472 
        .end linenumbertable 
        .localvariabletable 
            0 is this Lcom/cairn4/moonbase/ui/MiniMap; from L0 to L157 
            1 is minChunkX F from L0 to L157 
            2 is minChunkY F from L0 to L157 
            3 is screenLimitCoords Lcom/badlogic/gdx/math/Rectangle; from L34 to L157 
            4 is poi Lcom/badlogic/gdx/scenes/scene2d/ui/Image; from L55 to L157 
            5 is gp Lcom/badlogic/gdx/math/GridPoint2; from L118 to L157 
            6 is landerMapPos Lcom/badlogic/gdx/math/Vector2; from L134 to L157 
        .end localvariabletable 
    .end code 
.end method 

.method private showNavBeacons : (FFII)V 
    .code stack 7 locals 16 
L0:     new com/badlogic/gdx/math/Rectangle 
L3:     dup 
L4:     getstatic Field com/cairn4/moonbase/MoonBase SCREEN_WIDTH I 
L7:     iconst_2 
L8:     idiv 
L9:     i2f 
L10:    getstatic Field com/cairn4/moonbase/MoonBase SCREEN_HEIGHT I 
L13:    iconst_2 
L14:    idiv 
L15:    i2f 
L16:    getstatic Field com/cairn4/moonbase/MoonBase SCREEN_WIDTH I 
L19:    bipush 90 
L21:    isub 
L22:    i2f 
L23:    getstatic Field com/cairn4/moonbase/MoonBase SCREEN_HEIGHT I 
L26:    bipush 90 
L28:    isub 
L29:    i2f 
L30:    invokespecial Method com/badlogic/gdx/math/Rectangle <init> (FFFF)V 
L33:    astore 5 
L35:    ldc 'Nav Beacons:\n' 
L37:    astore 6 
L39:    aload_0 
L40:    getfield Field com/cairn4/moonbase/ui/MiniMap gameScreen Lcom/cairn4/moonbase/ui/GameScreen; 
L43:    getfield Field com/cairn4/moonbase/ui/GameScreen world Lcom/cairn4/moonbase/World; 
L46:    getfield Field com/cairn4/moonbase/World baseManager Lcom/cairn4/moonbase/BaseManager; 
L49:    invokevirtual Method com/cairn4/moonbase/BaseManager getNavBeacons ()Ljava/util/ArrayList; 
L52:    invokevirtual Method java/util/ArrayList iterator ()Ljava/util/Iterator; 
L55:    astore 7 

        .stack append Object com/badlogic/gdx/math/Rectangle Object java/lang/String Object java/util/Iterator 
L57:    aload 7 
L59:    invokeinterface InterfaceMethod java/util/Iterator hasNext ()Z 1 
L64:    ifeq L369 
L67:    aload 7 
L69:    invokeinterface InterfaceMethod java/util/Iterator next ()Ljava/lang/Object; 1 
L74:    checkcast com/badlogic/gdx/math/GridPoint2 
L77:    astore 8 
L79:    new java/lang/StringBuilder 
L82:    dup 
L83:    invokespecial Method java/lang/StringBuilder <init> ()V 
L86:    aload 6 
L88:    invokevirtual Method java/lang/StringBuilder append (Ljava/lang/String;)Ljava/lang/StringBuilder; 
L91:    ldc '(' 
L93:    invokevirtual Method java/lang/StringBuilder append (Ljava/lang/String;)Ljava/lang/StringBuilder; 
L96:    aload 8 
L98:    getfield Field com/badlogic/gdx/math/GridPoint2 x I 
L101:   invokevirtual Method java/lang/StringBuilder append (I)Ljava/lang/StringBuilder; 
L104:   ldc ', ' 
L106:   invokevirtual Method java/lang/StringBuilder append (Ljava/lang/String;)Ljava/lang/StringBuilder; 
L109:   aload 8 
L111:   getfield Field com/badlogic/gdx/math/GridPoint2 y I 
L114:   invokevirtual Method java/lang/StringBuilder append (I)Ljava/lang/StringBuilder; 
L117:   ldc ')\n' 
L119:   invokevirtual Method java/lang/StringBuilder append (Ljava/lang/String;)Ljava/lang/StringBuilder; 
L122:   invokevirtual Method java/lang/StringBuilder toString ()Ljava/lang/String; 
L125:   astore 6 
L127:   new com/cairn4/moonbase/AdditiveImage 
L130:   dup 
L131:   aload_0 
L132:   getfield Field com/cairn4/moonbase/ui/MiniMap gameScreen Lcom/cairn4/moonbase/ui/GameScreen; 
L135:   getfield Field com/cairn4/moonbase/ui/GameScreen skin Lcom/badlogic/gdx/scenes/scene2d/ui/Skin; 
L138:   ldc 'white' 
L140:   invokevirtual Method com/badlogic/gdx/scenes/scene2d/ui/Skin getDrawable (Ljava/lang/String;)Lcom/badlogic/gdx/scenes/scene2d/utils/Drawable; 
L143:   invokespecial Method com/cairn4/moonbase/AdditiveImage <init> (Lcom/badlogic/gdx/scenes/scene2d/utils/Drawable;)V 
L146:   astore 9 
L148:   aload 9 
L150:   ldc +10.0f 
L152:   ldc +10.0f 
L154:   invokevirtual Method com/badlogic/gdx/scenes/scene2d/ui/Image setSize (FF)V 
L157:   aload 9 
L159:   iconst_1 
L160:   invokevirtual Method com/badlogic/gdx/scenes/scene2d/ui/Image setOrigin (I)V 
L163:   aload 9 
L165:   ldc +45.0f 
L167:   invokevirtual Method com/badlogic/gdx/scenes/scene2d/ui/Image setRotation (F)V 
L170:   aload 9 
L172:   getstatic Field com/badlogic/gdx/graphics/Color CYAN Lcom/badlogic/gdx/graphics/Color; 
L175:   invokevirtual Method com/badlogic/gdx/scenes/scene2d/ui/Image setColor (Lcom/badlogic/gdx/graphics/Color;)V 
L178:   aload_0 
L179:   getfield Field com/cairn4/moonbase/ui/MiniMap groupOffset Lcom/badlogic/gdx/scenes/scene2d/Group; 
L182:   aload 9 
L184:   invokevirtual Method com/badlogic/gdx/scenes/scene2d/Group addActor (Lcom/badlogic/gdx/scenes/scene2d/Actor;)V 
L187:   aload 8 
L189:   getfield Field com/badlogic/gdx/math/GridPoint2 x I 
L192:   i2f 
L193:   ldc +10.0f 
L195:   fdiv 
L196:   fload_1 
L197:   fsub 
L198:   fstore 10 
L200:   fload 10 
L202:   ldc +100.0f 
L204:   fmul 
L205:   fstore 11 
L207:   aload 8 
L209:   getfield Field com/badlogic/gdx/math/GridPoint2 y I 
L212:   i2f 
L213:   ldc +10.0f 
L215:   fdiv 
L216:   fload_2 
L217:   fsub 
L218:   fstore 12 
L220:   fload 12 
L222:   ldc +100.0f 
L224:   fmul 
L225:   fstore 13 
L227:   aload_0 
L228:   aload 8 
L230:   getfield Field com/badlogic/gdx/math/GridPoint2 x I 
L233:   aload 8 
L235:   getfield Field com/badlogic/gdx/math/GridPoint2 y I 
L238:   invokespecial Method com/cairn4/moonbase/ui/MiniMap worldTileToMapPos (II)Lcom/badlogic/gdx/math/Vector2; 
L241:   astore 14 
L243:   aload_0 
L244:   getfield Field com/cairn4/moonbase/ui/MiniMap groupOffset Lcom/badlogic/gdx/scenes/scene2d/Group; 
L247:   aload 14 
L249:   invokevirtual Method com/badlogic/gdx/math/Vector2 cpy ()Lcom/badlogic/gdx/math/Vector2; 
L252:   invokevirtual Method com/badlogic/gdx/scenes/scene2d/Group localToStageCoordinates (Lcom/badlogic/gdx/math/Vector2;)Lcom/badlogic/gdx/math/Vector2; 
L255:   astore 15 
L257:   getstatic Field java/lang/System out Ljava/io/PrintStream; 
L260:   new java/lang/StringBuilder 
L263:   dup 
L264:   invokespecial Method java/lang/StringBuilder <init> ()V 
L267:   ldc 'nav: ' 
L269:   invokevirtual Method java/lang/StringBuilder append (Ljava/lang/String;)Ljava/lang/StringBuilder; 
L272:   aload 15 
L274:   invokevirtual Method java/lang/StringBuilder append (Ljava/lang/Object;)Ljava/lang/StringBuilder; 
L277:   invokevirtual Method java/lang/StringBuilder toString ()Ljava/lang/String; 
L280:   invokevirtual Method java/io/PrintStream println (Ljava/lang/String;)V 
L283:   getstatic Field java/lang/System out Ljava/io/PrintStream; 
L286:   ldc 'nav: inside rect' 
L288:   invokevirtual Method java/io/PrintStream println (Ljava/lang/String;)V 
L291:   aload 9 
L293:   aload 14 
L295:   getfield Field com/badlogic/gdx/math/Vector2 x F 
L298:   ldc +5.0f 
L300:   fadd 
L301:   aload 14 
L303:   getfield Field com/badlogic/gdx/math/Vector2 y F 
L306:   ldc +5.0f 
L308:   fadd 
L309:   iconst_1 
L310:   invokevirtual Method com/badlogic/gdx/scenes/scene2d/ui/Image setPosition (FFI)V 
L313:   aload 9 
L315:   fconst_1 
L316:   fconst_1 
L317:   invokestatic Method com/badlogic/gdx/scenes/scene2d/actions/Actions scaleTo (FF)Lcom/badlogic/gdx/scenes/scene2d/actions/ScaleToAction; 
L320:   fconst_1 
L321:   invokestatic Method com/badlogic/gdx/scenes/scene2d/actions/Actions alpha (F)Lcom/badlogic/gdx/scenes/scene2d/actions/AlphaAction; 
L324:   ldc +8.0f 
L326:   ldc +8.0f 
L328:   ldc +0.699999988079071f 
L330:   getstatic Field com/badlogic/gdx/math/Interpolation sine Lcom/badlogic/gdx/math/Interpolation; 
L333:   invokestatic Method com/badlogic/gdx/scenes/scene2d/actions/Actions scaleTo (FFFLcom/badlogic/gdx/math/Interpolation;)Lcom/badlogic/gdx/scenes/scene2d/actions/ScaleToAction; 
L336:   ldc +0.10000000149011612f 
L338:   invokestatic Method com/badlogic/gdx/scenes/scene2d/actions/Actions fadeOut (F)Lcom/badlogic/gdx/scenes/scene2d/actions/AlphaAction; 
L341:   ldc +0.6000000238418579f 
L343:   invokestatic Method com/badlogic/gdx/scenes/scene2d/actions/Actions fadeOut (F)Lcom/badlogic/gdx/scenes/scene2d/actions/AlphaAction; 
L346:   invokestatic Method com/badlogic/gdx/scenes/scene2d/actions/Actions parallel (Lcom/badlogic/gdx/scenes/scene2d/Action;Lcom/badlogic/gdx/scenes/scene2d/Action;)Lcom/badlogic/gdx/scenes/scene2d/actions/ParallelAction; 
L349:   invokestatic Method com/badlogic/gdx/scenes/scene2d/actions/Actions parallel (Lcom/badlogic/gdx/scenes/scene2d/Action;Lcom/badlogic/gdx/scenes/scene2d/Action;)Lcom/badlogic/gdx/scenes/scene2d/actions/ParallelAction; 
L352:   ldc +0.4000000059604645f 
L354:   invokestatic Method com/badlogic/gdx/scenes/scene2d/actions/Actions delay (F)Lcom/badlogic/gdx/scenes/scene2d/actions/DelayAction; 
L357:   invokestatic Method com/badlogic/gdx/scenes/scene2d/actions/Actions sequence (Lcom/badlogic/gdx/scenes/scene2d/Action;Lcom/badlogic/gdx/scenes/scene2d/Action;Lcom/badlogic/gdx/scenes/scene2d/Action;Lcom/badlogic/gdx/scenes/scene2d/Action;)Lcom/badlogic/gdx/scenes/scene2d/actions/SequenceAction; 
L360:   invokestatic Method com/badlogic/gdx/scenes/scene2d/actions/Actions forever (Lcom/badlogic/gdx/scenes/scene2d/Action;)Lcom/badlogic/gdx/scenes/scene2d/actions/RepeatAction; 
L363:   invokevirtual Method com/badlogic/gdx/scenes/scene2d/ui/Image addAction (Lcom/badlogic/gdx/scenes/scene2d/Action;)V 
L366:   goto L57 

        .stack chop 1 
L369:   return 
L370:   
        .linenumbertable 
            L0 479 
            L35 486 
            L39 488 
            L79 490 
            L127 492 
            L148 493 
            L157 494 
            L163 495 
            L170 496 
            L178 497 
            L187 499 
            L200 500 
            L207 502 
            L220 503 
            L227 506 
            L243 518 
            L257 519 
            L283 524 
            L291 526 
            L313 570 
            L317 574 
            L321 575 
            L333 577 
            L338 579 
            L343 580 
            L346 578 
            L349 576 
            L354 584 
            L357 573 
            L360 572 
            L363 570 
            L366 591 
            L369 594 
        .end linenumbertable 
        .localvariabletable 
            9 is navBeacon Lcom/badlogic/gdx/scenes/scene2d/ui/Image; from L148 to L366 
            10 is tX F from L200 to L366 
            11 is drawX F from L207 to L366 
            12 is tY F from L220 to L366 
            13 is drawY F from L227 to L366 
            14 is navBeaconMapPos Lcom/badlogic/gdx/math/Vector2; from L243 to L366 
            15 is navBeaconStagePos Lcom/badlogic/gdx/math/Vector2; from L257 to L366 
            8 is gp Lcom/badlogic/gdx/math/GridPoint2; from L79 to L366 
            0 is this Lcom/cairn4/moonbase/ui/MiniMap; from L0 to L370 
            1 is minChunkX F from L0 to L370 
            2 is minChunkY F from L0 to L370 
            3 is horzChunks I from L0 to L370 
            4 is vertChunks I from L0 to L370 
            5 is screenLimitCoords Lcom/badlogic/gdx/math/Rectangle; from L35 to L370 
            6 is navText Ljava/lang/String; from L39 to L370 
        .end localvariabletable 
    .end code 
.end method 

.method public update : (F)V 
    .code stack 4 locals 4 
L0:     iconst_0 
L1:     istore_2 
L2:     invokestatic Method com/cairn4/moonbase/PlayerInput scrolledDown ()Z 
L5:     ifeq L16 
L8:     aload_0 
L9:     iconst_m1 
L10:    fload_1 
L11:    invokespecial Method com/cairn4/moonbase/ui/MiniMap zoomMap (IF)V 
L14:    iconst_1 
L15:    istore_2 

        .stack append Integer 
L16:    invokestatic Method com/cairn4/moonbase/PlayerInput scrolledUp ()Z 
L19:    ifeq L30 
L22:    aload_0 
L23:    iconst_1 
L24:    fload_1 
L25:    invokespecial Method com/cairn4/moonbase/ui/MiniMap zoomMap (IF)V 
L28:    iconst_1 
L29:    istore_2 

        .stack same 
L30:    iload_2 
L31:    ifne L40 
L34:    aload_0 
L35:    iconst_0 
L36:    fload_1 
L37:    invokespecial Method com/cairn4/moonbase/ui/MiniMap zoomMap (IF)V 

        .stack same 
L40:    iconst_0 
L41:    istore_2 
L42:    aload_0 
L43:    invokespecial Method com/cairn4/moonbase/ui/MiniMap hoverUpdate ()V 
L46:    new com/badlogic/gdx/math/Vector2 
L49:    dup 
L50:    fconst_0 
L51:    fconst_0 
L52:    invokespecial Method com/badlogic/gdx/math/Vector2 <init> (FF)V 
L55:    astore_3 
L56:    iconst_0 
L57:    invokestatic Method com/cairn4/moonbase/PlayerInput isDown (I)Z 
L60:    ifeq L69 
L63:    aload_3 
L64:    ldc -1.0f 
L66:    putfield Field com/badlogic/gdx/math/Vector2 x F 

        .stack append Object com/badlogic/gdx/math/Vector2 
L69:    iconst_1 
L70:    invokestatic Method com/cairn4/moonbase/PlayerInput isDown (I)Z 
L73:    ifeq L81 
L76:    aload_3 
L77:    fconst_1 
L78:    putfield Field com/badlogic/gdx/math/Vector2 x F 

        .stack same 
L81:    iconst_2 
L82:    invokestatic Method com/cairn4/moonbase/PlayerInput isDown (I)Z 
L85:    ifeq L93 
L88:    aload_3 
L89:    fconst_1 
L90:    putfield Field com/badlogic/gdx/math/Vector2 y F 

        .stack same 
L93:    iconst_3 
L94:    invokestatic Method com/cairn4/moonbase/PlayerInput isDown (I)Z 
L97:    ifeq L106 
L100:   aload_3 
L101:   ldc -1.0f 
L103:   putfield Field com/badlogic/gdx/math/Vector2 y F 

        .stack same 
L106:   aload_0 
L107:   aload_3 
L108:   getfield Field com/badlogic/gdx/math/Vector2 x F 
L111:   aload_3 
L112:   getfield Field com/badlogic/gdx/math/Vector2 y F 
L115:   invokespecial Method com/cairn4/moonbase/ui/MiniMap panMap (FF)V 
L118:   return 
L119:   
        .linenumbertable 
            L0 601 
            L2 603 
            L8 604 
            L14 605 
            L16 608 
            L22 609 
            L28 610 
            L30 613 
            L34 614 
            L40 617 
            L42 620 
            L46 623 
            L56 624 
            L63 625 
            L69 628 
            L76 629 
            L81 632 
            L88 633 
            L93 636 
            L100 637 
            L106 640 
            L118 642 
        .end linenumbertable 
        .localvariabletable 
            0 is this Lcom/cairn4/moonbase/ui/MiniMap; from L0 to L119 
            1 is delta F from L0 to L119 
            2 is scrolling Z from L2 to L119 
            3 is panDir Lcom/badlogic/gdx/math/Vector2; from L56 to L119 
        .end localvariabletable 
    .end code 
.end method 

.method private panMap : (FF)V 
    .code stack 4 locals 5 
L0:     aload_0 
L1:     getfield Field com/cairn4/moonbase/ui/MiniMap groupOffset Lcom/badlogic/gdx/scenes/scene2d/Group; 
L4:     invokevirtual Method com/badlogic/gdx/scenes/scene2d/Group getX ()F 
L7:     fstore_3 
L8:     aload_0 
L9:     getfield Field com/cairn4/moonbase/ui/MiniMap groupOffset Lcom/badlogic/gdx/scenes/scene2d/Group; 
L12:    invokevirtual Method com/badlogic/gdx/scenes/scene2d/Group getY ()F 
L15:    fstore 4 
L17:    fload_1 
L18:    getstatic Field com/badlogic/gdx/Gdx graphics Lcom/badlogic/gdx/Graphics; 
L21:    invokeinterface InterfaceMethod com/badlogic/gdx/Graphics getDeltaTime ()F 1 
L26:    getstatic Field com/cairn4/moonbase/ui/MiniMap PAN_SPEED F 
L29:    fmul 
L30:    fmul 
L31:    fstore_1 
L32:    fload_2 
L33:    getstatic Field com/badlogic/gdx/Gdx graphics Lcom/badlogic/gdx/Graphics; 
L36:    invokeinterface InterfaceMethod com/badlogic/gdx/Graphics getDeltaTime ()F 1 
L41:    getstatic Field com/cairn4/moonbase/ui/MiniMap PAN_SPEED F 
L44:    fmul 
L45:    fmul 
L46:    fstore_2 
L47:    fload_1 
L48:    getstatic Field com/cairn4/moonbase/ui/MiniMap savedZoom F 
L51:    fdiv 
L52:    fstore_1 
L53:    fload_2 
L54:    getstatic Field com/cairn4/moonbase/ui/MiniMap savedZoom F 
L57:    fdiv 
L58:    fstore_2 
L59:    aload_0 
L60:    getfield Field com/cairn4/moonbase/ui/MiniMap groupOffset Lcom/badlogic/gdx/scenes/scene2d/Group; 
L63:    fload_3 
L64:    fload_1 
L65:    fsub 
L66:    fload 4 
L68:    fload_2 
L69:    fsub 
L70:    invokevirtual Method com/badlogic/gdx/scenes/scene2d/Group setPosition (FF)V 
L73:    return 
L74:    
        .linenumbertable 
            L0 646 
            L8 647 
            L17 649 
            L32 650 
            L47 652 
            L53 653 
            L59 655 
            L73 656 
        .end linenumbertable 
        .localvariabletable 
            0 is this Lcom/cairn4/moonbase/ui/MiniMap; from L0 to L74 
            1 is x F from L0 to L74 
            2 is y F from L0 to L74 
            3 is curX F from L8 to L74 
            4 is curY F from L17 to L74 
        .end localvariabletable 
    .end code 
.end method 

.method private hoverUpdate : ()V 
    .code stack 4 locals 8 
L0:     getstatic Field com/badlogic/gdx/Gdx input Lcom/badlogic/gdx/Input; 
L3:     invokeinterface InterfaceMethod com/badlogic/gdx/Input getX ()I 1 
L8:     i2f 
L9:     fstore_1 
L10:    getstatic Field com/badlogic/gdx/Gdx input Lcom/badlogic/gdx/Input; 
L13:    invokeinterface InterfaceMethod com/badlogic/gdx/Input getY ()I 1 
L18:    i2f 
L19:    fstore_2 
L20:    aload_0 
L21:    getfield Field com/cairn4/moonbase/ui/MiniMap screenMouse Lcom/badlogic/gdx/math/Vector2; 
L24:    fload_1 
L25:    fload_2 
L26:    invokevirtual Method com/badlogic/gdx/math/Vector2 set (FF)Lcom/badlogic/gdx/math/Vector2; 
L29:    pop 
L30:    aload_0 
L31:    getfield Field com/cairn4/moonbase/ui/MiniMap mapMouse Lcom/badlogic/gdx/math/Vector2; 
L34:    aload_0 
L35:    getfield Field com/cairn4/moonbase/ui/MiniMap groupOffset Lcom/badlogic/gdx/scenes/scene2d/Group; 
L38:    aload_0 
L39:    getfield Field com/cairn4/moonbase/ui/MiniMap screenMouse Lcom/badlogic/gdx/math/Vector2; 
L42:    invokevirtual Method com/badlogic/gdx/scenes/scene2d/Group screenToLocalCoordinates (Lcom/badlogic/gdx/math/Vector2;)Lcom/badlogic/gdx/math/Vector2; 
L45:    invokevirtual Method com/badlogic/gdx/math/Vector2 set (Lcom/badlogic/gdx/math/Vector2;)Lcom/badlogic/gdx/math/Vector2; 
L48:    pop 
L49:    aload_0 
L50:    getfield Field com/cairn4/moonbase/ui/MiniMap mapMouse Lcom/badlogic/gdx/math/Vector2; 
L53:    getfield Field com/badlogic/gdx/math/Vector2 x F 
L56:    ldc +10.0f 
L58:    fdiv 
L59:    invokestatic Method com/badlogic/gdx/math/MathUtils floor (F)I 
L62:    istore_3 
L63:    aload_0 
L64:    getfield Field com/cairn4/moonbase/ui/MiniMap mapMouse Lcom/badlogic/gdx/math/Vector2; 
L67:    getfield Field com/badlogic/gdx/math/Vector2 y F 
L70:    ldc +10.0f 
L72:    fdiv 
L73:    invokestatic Method com/badlogic/gdx/math/MathUtils floor (F)I 
L76:    istore 4 
L78:    ldc '' 
L80:    astore 5 
L82:    iload_3 
L83:    aload_0 
L84:    getfield Field com/cairn4/moonbase/ui/MiniMap minMegaChunkX I 
L87:    bipush 100 
L89:    imul 
L90:    iadd 
L91:    istore_3 
L92:    iload 4 
L94:    aload_0 
L95:    getfield Field com/cairn4/moonbase/ui/MiniMap minMegaChunkY I 
L98:    bipush 100 
L100:   imul 
L101:   iadd 
L102:   istore 4 
L104:   aload_0 
L105:   getfield Field com/cairn4/moonbase/ui/MiniMap gameScreen Lcom/cairn4/moonbase/ui/GameScreen; 
L108:   getfield Field com/cairn4/moonbase/ui/GameScreen world Lcom/cairn4/moonbase/World; 
L111:   iload_3 
L112:   iload 4 
L114:   invokevirtual Method com/cairn4/moonbase/World getTile (II)Lcom/cairn4/moonbase/tiles/Tile; 
L117:   astore 6 
L119:   aload 6 
L121:   ifnull L232 
L124:   aload 6 
L126:   getfield Field com/cairn4/moonbase/tiles/Tile chunk Lcom/cairn4/moonbase/Chunk; 
L129:   getfield Field com/cairn4/moonbase/Chunk gtDiscoveryArray [Z 
L132:   aload 6 
L134:   getfield Field com/cairn4/moonbase/tiles/Tile y I 
L137:   bipush 10 
L139:   imul 
L140:   aload 6 
L142:   getfield Field com/cairn4/moonbase/tiles/Tile x I 
L145:   iadd 
L146:   baload 
L147:   ifeq L232 
L150:   new java/lang/StringBuilder 
L153:   dup 
L154:   invokespecial Method java/lang/StringBuilder <init> ()V 
L157:   aload 5 
L159:   invokevirtual Method java/lang/StringBuilder append (Ljava/lang/String;)Ljava/lang/StringBuilder; 
L162:   aload 6 
L164:   invokevirtual Method com/cairn4/moonbase/tiles/Tile getMapName ()Ljava/lang/String; 
L167:   invokevirtual Method java/lang/StringBuilder append (Ljava/lang/String;)Ljava/lang/StringBuilder; 
L170:   invokevirtual Method java/lang/StringBuilder toString ()Ljava/lang/String; 
L173:   astore 5 
L175:   aload_0 
L176:   getfield Field com/cairn4/moonbase/ui/MiniMap hoverLabel Lcom/badlogic/gdx/scenes/scene2d/ui/Label; 
L179:   aload 5 
L181:   invokevirtual Method com/badlogic/gdx/scenes/scene2d/ui/Label setText (Ljava/lang/CharSequence;)V 
L184:   aload_0 
L185:   getfield Field com/cairn4/moonbase/ui/MiniMap hoverPanel Lcom/badlogic/gdx/scenes/scene2d/ui/Image; 
L188:   aload_0 
L189:   getfield Field com/cairn4/moonbase/ui/MiniMap hoverLabel Lcom/badlogic/gdx/scenes/scene2d/ui/Label; 
L192:   invokevirtual Method com/badlogic/gdx/scenes/scene2d/ui/Label getPrefWidth ()F 
L195:   ldc +30.0f 
L197:   fadd 
L198:   aload_0 
L199:   getfield Field com/cairn4/moonbase/ui/MiniMap hoverLabel Lcom/badlogic/gdx/scenes/scene2d/ui/Label; 
L202:   invokevirtual Method com/badlogic/gdx/scenes/scene2d/ui/Label getPrefHeight ()F 
L205:   ldc +20.0f 
L207:   fadd 
L208:   invokevirtual Method com/badlogic/gdx/scenes/scene2d/ui/Image setSize (FF)V 
L211:   aload_0 
L212:   getfield Field com/cairn4/moonbase/ui/MiniMap hoverPanel Lcom/badlogic/gdx/scenes/scene2d/ui/Image; 
L215:   fconst_0 
L216:   fconst_0 
L217:   iconst_1 
L218:   invokevirtual Method com/badlogic/gdx/scenes/scene2d/ui/Image setPosition (FFI)V 
L221:   aload_0 
L222:   getfield Field com/cairn4/moonbase/ui/MiniMap hoverTooltipGroup Lcom/badlogic/gdx/scenes/scene2d/Group; 
L225:   iconst_1 
L226:   invokevirtual Method com/badlogic/gdx/scenes/scene2d/Group setVisible (Z)V 
L229:   goto L368 

        .stack full 
            locals Object com/cairn4/moonbase/ui/MiniMap Float Float Integer Integer Object java/lang/String Object com/cairn4/moonbase/tiles/Tile 
            stack 
        .end stack 
L232:   aload_0 
L233:   getfield Field com/cairn4/moonbase/ui/MiniMap gameScreen Lcom/cairn4/moonbase/ui/GameScreen; 
L236:   getfield Field com/cairn4/moonbase/ui/GameScreen world Lcom/cairn4/moonbase/World; 
L239:   iload_3 
L240:   iload 4 
L242:   invokevirtual Method com/cairn4/moonbase/World getFloorTile (II)Lcom/cairn4/moonbase/tiles/Tile; 
L245:   astore 7 
L247:   aload 7 
L249:   ifnull L360 
L252:   aload 7 
L254:   getfield Field com/cairn4/moonbase/tiles/Tile chunk Lcom/cairn4/moonbase/Chunk; 
L257:   getfield Field com/cairn4/moonbase/Chunk gtDiscoveryArray [Z 
L260:   aload 7 
L262:   getfield Field com/cairn4/moonbase/tiles/Tile y I 
L265:   bipush 10 
L267:   imul 
L268:   aload 7 
L270:   getfield Field com/cairn4/moonbase/tiles/Tile x I 
L273:   iadd 
L274:   baload 
L275:   ifeq L360 
L278:   new java/lang/StringBuilder 
L281:   dup 
L282:   invokespecial Method java/lang/StringBuilder <init> ()V 
L285:   aload 5 
L287:   invokevirtual Method java/lang/StringBuilder append (Ljava/lang/String;)Ljava/lang/StringBuilder; 
L290:   aload 7 
L292:   invokevirtual Method com/cairn4/moonbase/tiles/Tile getMapName ()Ljava/lang/String; 
L295:   invokevirtual Method java/lang/StringBuilder append (Ljava/lang/String;)Ljava/lang/StringBuilder; 
L298:   invokevirtual Method java/lang/StringBuilder toString ()Ljava/lang/String; 
L301:   astore 5 
L303:   aload_0 
L304:   getfield Field com/cairn4/moonbase/ui/MiniMap hoverLabel Lcom/badlogic/gdx/scenes/scene2d/ui/Label; 
L307:   aload 5 
L309:   invokevirtual Method com/badlogic/gdx/scenes/scene2d/ui/Label setText (Ljava/lang/CharSequence;)V 
L312:   aload_0 
L313:   getfield Field com/cairn4/moonbase/ui/MiniMap hoverPanel Lcom/badlogic/gdx/scenes/scene2d/ui/Image; 
L316:   aload_0 
L317:   getfield Field com/cairn4/moonbase/ui/MiniMap hoverLabel Lcom/badlogic/gdx/scenes/scene2d/ui/Label; 
L320:   invokevirtual Method com/badlogic/gdx/scenes/scene2d/ui/Label getPrefWidth ()F 
L323:   ldc +30.0f 
L325:   fadd 
L326:   aload_0 
L327:   getfield Field com/cairn4/moonbase/ui/MiniMap hoverLabel Lcom/badlogic/gdx/scenes/scene2d/ui/Label; 
L330:   invokevirtual Method com/badlogic/gdx/scenes/scene2d/ui/Label getPrefHeight ()F 
L333:   ldc +20.0f 
L335:   fadd 
L336:   invokevirtual Method com/badlogic/gdx/scenes/scene2d/ui/Image setSize (FF)V 
L339:   aload_0 
L340:   getfield Field com/cairn4/moonbase/ui/MiniMap hoverPanel Lcom/badlogic/gdx/scenes/scene2d/ui/Image; 
L343:   fconst_0 
L344:   fconst_0 
L345:   iconst_1 
L346:   invokevirtual Method com/badlogic/gdx/scenes/scene2d/ui/Image setPosition (FFI)V 
L349:   aload_0 
L350:   getfield Field com/cairn4/moonbase/ui/MiniMap hoverTooltipGroup Lcom/badlogic/gdx/scenes/scene2d/Group; 
L353:   iconst_1 
L354:   invokevirtual Method com/badlogic/gdx/scenes/scene2d/Group setVisible (Z)V 
L357:   goto L368 

        .stack append Object com/cairn4/moonbase/tiles/Tile 
L360:   aload_0 
L361:   getfield Field com/cairn4/moonbase/ui/MiniMap hoverTooltipGroup Lcom/badlogic/gdx/scenes/scene2d/Group; 
L364:   iconst_0 
L365:   invokevirtual Method com/badlogic/gdx/scenes/scene2d/Group setVisible (Z)V 

        .stack chop 1 
L368:   return 
L369:   
        .linenumbertable 
            L0 676 
            L10 677 
            L20 678 
            L30 679 
            L49 683 
            L63 684 
            L78 692 
            L82 697 
            L92 698 
            L104 702 
            L119 703 
            L150 704 
            L175 705 
            L184 706 
            L211 707 
            L221 708 
            L232 711 
            L247 712 
            L278 713 
            L303 714 
            L312 715 
            L339 716 
            L349 717 
            L360 720 
            L368 723 
        .end linenumbertable 
        .localvariabletable 
            7 is ft Lcom/cairn4/moonbase/tiles/Tile; from L247 to L368 
            0 is this Lcom/cairn4/moonbase/ui/MiniMap; from L0 to L369 
            1 is x F from L10 to L369 
            2 is y F from L20 to L369 
            3 is tileX I from L63 to L369 
            4 is tileY I from L78 to L369 
            5 is info Ljava/lang/String; from L82 to L369 
            6 is t Lcom/cairn4/moonbase/tiles/Tile; from L119 to L369 
        .end localvariabletable 
    .end code 
.end method 

.method private limitDrag : ()V 
    .code stack 3 locals 1 
L0:     getstatic Field java/lang/System out Ljava/io/PrintStream; 
L3:     new java/lang/StringBuilder 
L6:     dup 
L7:     invokespecial Method java/lang/StringBuilder <init> ()V 
L10:    aload_0 
L11:    getfield Field com/cairn4/moonbase/ui/MiniMap groupOffset Lcom/badlogic/gdx/scenes/scene2d/Group; 
L14:    invokevirtual Method com/badlogic/gdx/scenes/scene2d/Group getX ()F 
L17:    invokevirtual Method java/lang/StringBuilder append (F)Ljava/lang/StringBuilder; 
L20:    ldc ', ' 
L22:    invokevirtual Method java/lang/StringBuilder append (Ljava/lang/String;)Ljava/lang/StringBuilder; 
L25:    aload_0 
L26:    getfield Field com/cairn4/moonbase/ui/MiniMap groupOffset Lcom/badlogic/gdx/scenes/scene2d/Group; 
L29:    invokevirtual Method com/badlogic/gdx/scenes/scene2d/Group getY ()F 
L32:    invokevirtual Method java/lang/StringBuilder append (F)Ljava/lang/StringBuilder; 
L35:    invokevirtual Method java/lang/StringBuilder toString ()Ljava/lang/String; 
L38:    invokevirtual Method java/io/PrintStream println (Ljava/lang/String;)V 
L41:    return 
L42:    
        .linenumbertable 
            L0 746 
            L41 747 
        .end linenumbertable 
        .localvariabletable 
            0 is this Lcom/cairn4/moonbase/ui/MiniMap; from L0 to L42 
        .end localvariabletable 
    .end code 
.end method 

.method private zoomMap : (IF)V 
    .code stack 3 locals 4 
L0:     iload_1 
L1:     ifeq L74 
L4:     aload_0 
L5:     getfield Field com/cairn4/moonbase/ui/MiniMap mapZoomHolder Lcom/badlogic/gdx/scenes/scene2d/Group; 
L8:     invokevirtual Method com/badlogic/gdx/scenes/scene2d/Group getScaleX ()F 
L11:    fstore_3 
L12:    iload_1 
L13:    iconst_1 
L14:    if_icmpne L26 
L17:    fload_3 
L18:    fconst_1 
L19:    fload_2 
L20:    fmul 
L21:    fsub 
L22:    fstore_3 
L23:    goto L37 

        .stack append Float 
L26:    iload_1 
L27:    iconst_m1 
L28:    if_icmpne L37 
L31:    fload_3 
L32:    fconst_1 
L33:    fload_2 
L34:    fmul 
L35:    fadd 
L36:    fstore_3 

        .stack same 
L37:    fload_3 
L38:    ldc +0.25f 
L40:    fcmpg 
L41:    ifge L47 
L44:    ldc +0.25f 
L46:    fstore_3 

        .stack same 
L47:    fload_3 
L48:    fconst_2 
L49:    fcmpl 
L50:    ifle L55 
L53:    fconst_2 
L54:    fstore_3 

        .stack same 
L55:    fload_3 
L56:    putstatic Field com/cairn4/moonbase/ui/MiniMap savedZoom F 
L59:    aload_0 
L60:    invokespecial Method com/cairn4/moonbase/ui/MiniMap updateOffsetOrigin ()V 
L63:    aload_0 
L64:    getfield Field com/cairn4/moonbase/ui/MiniMap mapZoomHolder Lcom/badlogic/gdx/scenes/scene2d/Group; 
L67:    fload_3 
L68:    invokevirtual Method com/badlogic/gdx/scenes/scene2d/Group setScale (F)V 
L71:    goto L154 

        .stack chop 1 
L74:    aload_0 
L75:    getfield Field com/cairn4/moonbase/ui/MiniMap zoomDir I 
L78:    ifeq L154 
L81:    aload_0 
L82:    getfield Field com/cairn4/moonbase/ui/MiniMap mapZoomHolder Lcom/badlogic/gdx/scenes/scene2d/Group; 
L85:    invokevirtual Method com/badlogic/gdx/scenes/scene2d/Group getScaleX ()F 
L88:    fstore_3 
L89:    aload_0 
L90:    getfield Field com/cairn4/moonbase/ui/MiniMap zoomDir I 
L93:    iconst_1 
L94:    if_icmpne L106 
L97:    fload_3 
L98:    fconst_1 
L99:    fload_2 
L100:   fmul 
L101:   fsub 
L102:   fstore_3 
L103:   goto L120 

        .stack append Float 
L106:   aload_0 
L107:   getfield Field com/cairn4/moonbase/ui/MiniMap zoomDir I 
L110:   iconst_m1 
L111:   if_icmpne L120 
L114:   fload_3 
L115:   fconst_1 
L116:   fload_2 
L117:   fmul 
L118:   fadd 
L119:   fstore_3 

        .stack same 
L120:   fload_3 
L121:   ldc +0.25f 
L123:   fcmpg 
L124:   ifge L130 
L127:   ldc +0.25f 
L129:   fstore_3 

        .stack same 
L130:   fload_3 
L131:   fconst_2 
L132:   fcmpl 
L133:   ifle L138 
L136:   fconst_2 
L137:   fstore_3 

        .stack same 
L138:   fload_3 
L139:   putstatic Field com/cairn4/moonbase/ui/MiniMap savedZoom F 
L142:   aload_0 
L143:   invokespecial Method com/cairn4/moonbase/ui/MiniMap updateOffsetOrigin ()V 
L146:   aload_0 
L147:   getfield Field com/cairn4/moonbase/ui/MiniMap mapZoomHolder Lcom/badlogic/gdx/scenes/scene2d/Group; 
L150:   fload_3 
L151:   invokevirtual Method com/badlogic/gdx/scenes/scene2d/Group setScale (F)V 

        .stack chop 1 
L154:   return 
L155:   
        .linenumbertable 
            L0 758 
            L4 760 
            L12 762 
            L17 763 
            L26 764 
            L31 765 
            L37 768 
            L44 769 
            L47 772 
            L53 773 
            L55 776 
            L59 777 
            L63 778 
            L71 780 
            L74 781 
            L81 783 
            L89 785 
            L97 786 
            L106 787 
            L114 788 
            L120 791 
            L127 792 
            L130 795 
            L136 796 
            L138 799 
            L142 800 
            L146 801 
            L154 807 
        .end linenumbertable 
        .localvariabletable 
            3 is currentScale F from L12 to L71 
            3 is currentScale F from L89 to L154 
            0 is this Lcom/cairn4/moonbase/ui/MiniMap; from L0 to L155 
            1 is dir I from L0 to L155 
            2 is delta F from L0 to L155 
        .end localvariabletable 
    .end code 
.end method 

.method public show : ()V 
    .code stack 7 locals 14 
L0:     aload_0 
L1:     invokespecial Method com/cairn4/moonbase/ui/Menu show ()V 
L4:     aload_0 
L5:     new com/badlogic/gdx/scenes/scene2d/Group 
L8:     dup 
L9:     invokespecial Method com/badlogic/gdx/scenes/scene2d/Group <init> ()V 
L12:    putfield Field com/cairn4/moonbase/ui/MiniMap chunkGroup Lcom/badlogic/gdx/scenes/scene2d/Group; 
L15:    aload_0 
L16:    getfield Field com/cairn4/moonbase/ui/MiniMap menuGroup Lcom/badlogic/gdx/scenes/scene2d/Group; 
L19:    aload_0 
L20:    getfield Field com/cairn4/moonbase/ui/MiniMap chunkGroup Lcom/badlogic/gdx/scenes/scene2d/Group; 
L23:    invokevirtual Method com/badlogic/gdx/scenes/scene2d/Group addActor (Lcom/badlogic/gdx/scenes/scene2d/Actor;)V 
L26:    aload_0 
L27:    getfield Field com/cairn4/moonbase/ui/MiniMap chunkGroup Lcom/badlogic/gdx/scenes/scene2d/Group; 
L30:    fconst_0 
L31:    invokestatic Method com/badlogic/gdx/scenes/scene2d/actions/Actions alpha (F)Lcom/badlogic/gdx/scenes/scene2d/actions/AlphaAction; 
L34:    ldc +0.25f 
L36:    invokestatic Method com/badlogic/gdx/scenes/scene2d/actions/Actions fadeIn (F)Lcom/badlogic/gdx/scenes/scene2d/actions/AlphaAction; 
L39:    invokestatic Method com/badlogic/gdx/scenes/scene2d/actions/Actions sequence (Lcom/badlogic/gdx/scenes/scene2d/Action;Lcom/badlogic/gdx/scenes/scene2d/Action;)Lcom/badlogic/gdx/scenes/scene2d/actions/SequenceAction; 
L42:    invokevirtual Method com/badlogic/gdx/scenes/scene2d/Group addAction (Lcom/badlogic/gdx/scenes/scene2d/Action;)V 
L45:    aload_0 
L46:    new com/badlogic/gdx/scenes/scene2d/ui/Image 
L49:    dup 
L50:    aload_0 
L51:    getfield Field com/cairn4/moonbase/ui/MiniMap skin Lcom/badlogic/gdx/scenes/scene2d/ui/Skin; 
L54:    ldc 'map/map-bg' 
L56:    invokevirtual Method com/badlogic/gdx/scenes/scene2d/ui/Skin getDrawable (Ljava/lang/String;)Lcom/badlogic/gdx/scenes/scene2d/utils/Drawable; 
L59:    invokespecial Method com/badlogic/gdx/scenes/scene2d/ui/Image <init> (Lcom/badlogic/gdx/scenes/scene2d/utils/Drawable;)V 
L62:    putfield Field com/cairn4/moonbase/ui/MiniMap bg Lcom/badlogic/gdx/scenes/scene2d/ui/Image; 
L65:    aload_0 
L66:    getfield Field com/cairn4/moonbase/ui/MiniMap bg Lcom/badlogic/gdx/scenes/scene2d/ui/Image; 
L69:    fconst_0 
L70:    ldc +0.699999988079071f 
L72:    fconst_1 
L73:    fconst_1 
L74:    invokevirtual Method com/badlogic/gdx/scenes/scene2d/ui/Image setColor (FFFF)V 
L77:    aload_0 
L78:    getfield Field com/cairn4/moonbase/ui/MiniMap bg Lcom/badlogic/gdx/scenes/scene2d/ui/Image; 
L81:    getstatic Field com/cairn4/moonbase/MoonBase SCREEN_WIDTH I 
L84:    bipush 10 
L86:    iadd 
L87:    i2f 
L88:    getstatic Field com/cairn4/moonbase/MoonBase SCREEN_HEIGHT I 
L91:    bipush 10 
L93:    iadd 
L94:    i2f 
L95:    invokevirtual Method com/badlogic/gdx/scenes/scene2d/ui/Image setSize (FF)V 
L98:    aload_0 
L99:    getfield Field com/cairn4/moonbase/ui/MiniMap bg Lcom/badlogic/gdx/scenes/scene2d/ui/Image; 
L102:   ldc_w -5.0f 
L105:   ldc_w -5.0f 
L108:   invokevirtual Method com/badlogic/gdx/scenes/scene2d/ui/Image setPosition (FF)V 
L111:   aload_0 
L112:   getfield Field com/cairn4/moonbase/ui/MiniMap chunkGroup Lcom/badlogic/gdx/scenes/scene2d/Group; 
L115:   aload_0 
L116:   getfield Field com/cairn4/moonbase/ui/MiniMap bg Lcom/badlogic/gdx/scenes/scene2d/ui/Image; 
L119:   invokevirtual Method com/badlogic/gdx/scenes/scene2d/Group addActor (Lcom/badlogic/gdx/scenes/scene2d/Actor;)V 
L122:   aload_0 
L123:   getfield Field com/cairn4/moonbase/ui/MiniMap bg Lcom/badlogic/gdx/scenes/scene2d/ui/Image; 
L126:   invokevirtual Method com/badlogic/gdx/scenes/scene2d/ui/Image toBack ()V 
L129:   aload_0 
L130:   new com/badlogic/gdx/scenes/scene2d/Group 
L133:   dup 
L134:   invokespecial Method com/badlogic/gdx/scenes/scene2d/Group <init> ()V 
L137:   putfield Field com/cairn4/moonbase/ui/MiniMap mapZoomHolder Lcom/badlogic/gdx/scenes/scene2d/Group; 
L140:   aload_0 
L141:   getfield Field com/cairn4/moonbase/ui/MiniMap mapZoomHolder Lcom/badlogic/gdx/scenes/scene2d/Group; 
L144:   getstatic Field com/cairn4/moonbase/MoonBase SCREEN_WIDTH I 
L147:   iconst_2 
L148:   idiv 
L149:   i2f 
L150:   getstatic Field com/cairn4/moonbase/MoonBase SCREEN_HEIGHT I 
L153:   iconst_2 
L154:   idiv 
L155:   i2f 
L156:   invokevirtual Method com/badlogic/gdx/scenes/scene2d/Group setPosition (FF)V 
L159:   aload_0 
L160:   getfield Field com/cairn4/moonbase/ui/MiniMap chunkGroup Lcom/badlogic/gdx/scenes/scene2d/Group; 
L163:   aload_0 
L164:   getfield Field com/cairn4/moonbase/ui/MiniMap mapZoomHolder Lcom/badlogic/gdx/scenes/scene2d/Group; 
L167:   invokevirtual Method com/badlogic/gdx/scenes/scene2d/Group addActor (Lcom/badlogic/gdx/scenes/scene2d/Actor;)V 
L170:   aload_0 
L171:   new com/badlogic/gdx/scenes/scene2d/Group 
L174:   dup 
L175:   invokespecial Method com/badlogic/gdx/scenes/scene2d/Group <init> ()V 
L178:   putfield Field com/cairn4/moonbase/ui/MiniMap groupOffset Lcom/badlogic/gdx/scenes/scene2d/Group; 
L181:   aload_0 
L182:   getfield Field com/cairn4/moonbase/ui/MiniMap mapZoomHolder Lcom/badlogic/gdx/scenes/scene2d/Group; 
L185:   aload_0 
L186:   getfield Field com/cairn4/moonbase/ui/MiniMap groupOffset Lcom/badlogic/gdx/scenes/scene2d/Group; 
L189:   invokevirtual Method com/badlogic/gdx/scenes/scene2d/Group addActor (Lcom/badlogic/gdx/scenes/scene2d/Actor;)V 
L192:   aload_0 
L193:   new com/badlogic/gdx/scenes/scene2d/Group 
L196:   dup 
L197:   invokespecial Method com/badlogic/gdx/scenes/scene2d/Group <init> ()V 
L200:   putfield Field com/cairn4/moonbase/ui/MiniMap tileIconGroup Lcom/badlogic/gdx/scenes/scene2d/Group; 
L203:   aload_0 
L204:   getfield Field com/cairn4/moonbase/ui/MiniMap groupOffset Lcom/badlogic/gdx/scenes/scene2d/Group; 
L207:   aload_0 
L208:   getfield Field com/cairn4/moonbase/ui/MiniMap tileIconGroup Lcom/badlogic/gdx/scenes/scene2d/Group; 
L211:   invokevirtual Method com/badlogic/gdx/scenes/scene2d/Group addActor (Lcom/badlogic/gdx/scenes/scene2d/Actor;)V 
L214:   aload_0 
L215:   new com/badlogic/gdx/scenes/scene2d/Group 
L218:   dup 
L219:   invokespecial Method com/badlogic/gdx/scenes/scene2d/Group <init> ()V 
L222:   putfield Field com/cairn4/moonbase/ui/MiniMap uiGroup Lcom/badlogic/gdx/scenes/scene2d/Group; 
L225:   aload_0 
L226:   getfield Field com/cairn4/moonbase/ui/MiniMap menuGroup Lcom/badlogic/gdx/scenes/scene2d/Group; 
L229:   aload_0 
L230:   getfield Field com/cairn4/moonbase/ui/MiniMap uiGroup Lcom/badlogic/gdx/scenes/scene2d/Group; 
L233:   invokevirtual Method com/badlogic/gdx/scenes/scene2d/Group addActor (Lcom/badlogic/gdx/scenes/scene2d/Actor;)V 
L236:   new com/badlogic/gdx/graphics/g2d/NinePatch 
L239:   dup 
L240:   aload_0 
L241:   getfield Field com/cairn4/moonbase/ui/MiniMap baseScreen Lcom/cairn4/moonbase/ui/BaseScreen; 
L244:   getfield Field com/cairn4/moonbase/ui/BaseScreen skin Lcom/badlogic/gdx/scenes/scene2d/ui/Skin; 
L247:   ldc_w 'map/map-border' 
L250:   invokevirtual Method com/badlogic/gdx/scenes/scene2d/ui/Skin getRegion (Ljava/lang/String;)Lcom/badlogic/gdx/graphics/g2d/TextureRegion; 
L253:   bipush 100 
L255:   bipush 100 
L257:   bipush 120 
L259:   bipush 120 
L261:   invokespecial Method com/badlogic/gdx/graphics/g2d/NinePatch <init> (Lcom/badlogic/gdx/graphics/g2d/TextureRegion;IIII)V 
L264:   astore_1 
L265:   aload_0 
L266:   new com/badlogic/gdx/scenes/scene2d/ui/Image 
L269:   dup 
L270:   aload_1 
L271:   invokespecial Method com/badlogic/gdx/scenes/scene2d/ui/Image <init> (Lcom/badlogic/gdx/graphics/g2d/NinePatch;)V 
L274:   putfield Field com/cairn4/moonbase/ui/MiniMap border Lcom/badlogic/gdx/scenes/scene2d/ui/Image; 
L277:   aload_0 
L278:   getfield Field com/cairn4/moonbase/ui/MiniMap border Lcom/badlogic/gdx/scenes/scene2d/ui/Image; 
L281:   getstatic Field com/cairn4/moonbase/MoonBase SCREEN_WIDTH I 
L284:   iconst_4 
L285:   iadd 
L286:   i2f 
L287:   getstatic Field com/cairn4/moonbase/MoonBase SCREEN_HEIGHT I 
L290:   iconst_4 
L291:   iadd 
L292:   i2f 
L293:   invokevirtual Method com/badlogic/gdx/scenes/scene2d/ui/Image setSize (FF)V 
L296:   aload_0 
L297:   getfield Field com/cairn4/moonbase/ui/MiniMap border Lcom/badlogic/gdx/scenes/scene2d/ui/Image; 
L300:   ldc_w -2.0f 
L303:   ldc_w -2.0f 
L306:   invokevirtual Method com/badlogic/gdx/scenes/scene2d/ui/Image setPosition (FF)V 
L309:   aload_0 
L310:   getfield Field com/cairn4/moonbase/ui/MiniMap border Lcom/badlogic/gdx/scenes/scene2d/ui/Image; 
L313:   getstatic Field com/badlogic/gdx/scenes/scene2d/Touchable disabled Lcom/badlogic/gdx/scenes/scene2d/Touchable; 
L316:   invokevirtual Method com/badlogic/gdx/scenes/scene2d/ui/Image setTouchable (Lcom/badlogic/gdx/scenes/scene2d/Touchable;)V 
L319:   aload_0 
L320:   getfield Field com/cairn4/moonbase/ui/MiniMap uiGroup Lcom/badlogic/gdx/scenes/scene2d/Group; 
L323:   aload_0 
L324:   getfield Field com/cairn4/moonbase/ui/MiniMap border Lcom/badlogic/gdx/scenes/scene2d/ui/Image; 
L327:   invokevirtual Method com/badlogic/gdx/scenes/scene2d/Group addActor (Lcom/badlogic/gdx/scenes/scene2d/Actor;)V 
L330:   aload_0 
L331:   getfield Field com/cairn4/moonbase/ui/MiniMap border Lcom/badlogic/gdx/scenes/scene2d/ui/Image; 
L334:   new com/badlogic/gdx/graphics/Color 
L337:   dup 
L338:   fconst_0 
L339:   fconst_0 
L340:   fconst_0 
L341:   fconst_0 
L342:   invokespecial Method com/badlogic/gdx/graphics/Color <init> (FFFF)V 
L345:   invokestatic Method com/badlogic/gdx/scenes/scene2d/actions/Actions color (Lcom/badlogic/gdx/graphics/Color;)Lcom/badlogic/gdx/scenes/scene2d/actions/ColorAction; 
L348:   ldc_w +0.20000000298023224f 
L351:   invokestatic Method com/badlogic/gdx/scenes/scene2d/actions/Actions delay (F)Lcom/badlogic/gdx/scenes/scene2d/actions/DelayAction; 
L354:   getstatic Field com/badlogic/gdx/graphics/Color WHITE Lcom/badlogic/gdx/graphics/Color; 
L357:   ldc_w +0.20000000298023224f 
L360:   invokestatic Method com/badlogic/gdx/scenes/scene2d/actions/Actions color (Lcom/badlogic/gdx/graphics/Color;F)Lcom/badlogic/gdx/scenes/scene2d/actions/ColorAction; 
L363:   invokestatic Method com/badlogic/gdx/scenes/scene2d/actions/Actions sequence (Lcom/badlogic/gdx/scenes/scene2d/Action;Lcom/badlogic/gdx/scenes/scene2d/Action;Lcom/badlogic/gdx/scenes/scene2d/Action;)Lcom/badlogic/gdx/scenes/scene2d/actions/SequenceAction; 
L366:   invokevirtual Method com/badlogic/gdx/scenes/scene2d/ui/Image addAction (Lcom/badlogic/gdx/scenes/scene2d/Action;)V 
L369:   new com/badlogic/gdx/graphics/g2d/NinePatch 
L372:   dup 
L373:   aload_0 
L374:   getfield Field com/cairn4/moonbase/ui/MiniMap baseScreen Lcom/cairn4/moonbase/ui/BaseScreen; 
L377:   getfield Field com/cairn4/moonbase/ui/BaseScreen skin Lcom/badlogic/gdx/scenes/scene2d/ui/Skin; 
L380:   ldc_w 'map/map-inner-border' 
L383:   invokevirtual Method com/badlogic/gdx/scenes/scene2d/ui/Skin getRegion (Ljava/lang/String;)Lcom/badlogic/gdx/graphics/g2d/TextureRegion; 
L386:   sipush 200 
L389:   sipush 200 
L392:   bipush 105 
L394:   bipush 10 
L396:   invokespecial Method com/badlogic/gdx/graphics/g2d/NinePatch <init> (Lcom/badlogic/gdx/graphics/g2d/TextureRegion;IIII)V 
L399:   astore_2 
L400:   aload_0 
L401:   new com/badlogic/gdx/scenes/scene2d/ui/Image 
L404:   dup 
L405:   aload_2 
L406:   invokespecial Method com/badlogic/gdx/scenes/scene2d/ui/Image <init> (Lcom/badlogic/gdx/graphics/g2d/NinePatch;)V 
L409:   putfield Field com/cairn4/moonbase/ui/MiniMap innerBorder Lcom/badlogic/gdx/scenes/scene2d/ui/Image; 
L412:   aload_0 
L413:   getfield Field com/cairn4/moonbase/ui/MiniMap innerBorder Lcom/badlogic/gdx/scenes/scene2d/ui/Image; 
L416:   getstatic Field com/cairn4/moonbase/MoonBase SCREEN_WIDTH I 
L419:   iconst_4 
L420:   iadd 
L421:   bipush 88 
L423:   isub 
L424:   i2f 
L425:   getstatic Field com/cairn4/moonbase/MoonBase SCREEN_HEIGHT I 
L428:   iconst_4 
L429:   iadd 
L430:   bipush 100 
L432:   isub 
L433:   i2f 
L434:   invokevirtual Method com/badlogic/gdx/scenes/scene2d/ui/Image setSize (FF)V 
L437:   aload_0 
L438:   getfield Field com/cairn4/moonbase/ui/MiniMap innerBorder Lcom/badlogic/gdx/scenes/scene2d/ui/Image; 
L441:   ldc_w +44.0f 
L444:   ldc +50.0f 
L446:   invokevirtual Method com/badlogic/gdx/scenes/scene2d/ui/Image setPosition (FF)V 
L449:   aload_0 
L450:   getfield Field com/cairn4/moonbase/ui/MiniMap innerBorder Lcom/badlogic/gdx/scenes/scene2d/ui/Image; 
L453:   getstatic Field com/badlogic/gdx/scenes/scene2d/Touchable disabled Lcom/badlogic/gdx/scenes/scene2d/Touchable; 
L456:   invokevirtual Method com/badlogic/gdx/scenes/scene2d/ui/Image setTouchable (Lcom/badlogic/gdx/scenes/scene2d/Touchable;)V 
L459:   aload_0 
L460:   getfield Field com/cairn4/moonbase/ui/MiniMap uiGroup Lcom/badlogic/gdx/scenes/scene2d/Group; 
L463:   aload_0 
L464:   getfield Field com/cairn4/moonbase/ui/MiniMap innerBorder Lcom/badlogic/gdx/scenes/scene2d/ui/Image; 
L467:   invokevirtual Method com/badlogic/gdx/scenes/scene2d/Group addActor (Lcom/badlogic/gdx/scenes/scene2d/Actor;)V 
L470:   aload_0 
L471:   getfield Field com/cairn4/moonbase/ui/MiniMap innerBorder Lcom/badlogic/gdx/scenes/scene2d/ui/Image; 
L474:   fconst_0 
L475:   invokestatic Method com/badlogic/gdx/scenes/scene2d/actions/Actions alpha (F)Lcom/badlogic/gdx/scenes/scene2d/actions/AlphaAction; 
L478:   ldc +0.25f 
L480:   invokestatic Method com/badlogic/gdx/scenes/scene2d/actions/Actions delay (F)Lcom/badlogic/gdx/scenes/scene2d/actions/DelayAction; 
L483:   fconst_1 
L484:   ldc +0.25f 
L486:   invokestatic Method com/badlogic/gdx/scenes/scene2d/actions/Actions alpha (FF)Lcom/badlogic/gdx/scenes/scene2d/actions/AlphaAction; 
L489:   invokestatic Method com/badlogic/gdx/scenes/scene2d/actions/Actions sequence (Lcom/badlogic/gdx/scenes/scene2d/Action;Lcom/badlogic/gdx/scenes/scene2d/Action;Lcom/badlogic/gdx/scenes/scene2d/Action;)Lcom/badlogic/gdx/scenes/scene2d/actions/SequenceAction; 
L492:   invokevirtual Method com/badlogic/gdx/scenes/scene2d/ui/Image addAction (Lcom/badlogic/gdx/scenes/scene2d/Action;)V 
L495:   new com/badlogic/gdx/graphics/g2d/NinePatch 
L498:   dup 
L499:   aload_0 
L500:   getfield Field com/cairn4/moonbase/ui/MiniMap baseScreen Lcom/cairn4/moonbase/ui/BaseScreen; 
L503:   getfield Field com/cairn4/moonbase/ui/BaseScreen skin Lcom/badlogic/gdx/scenes/scene2d/ui/Skin; 
L506:   ldc_w 'map/map-border-intro' 
L509:   invokevirtual Method com/badlogic/gdx/scenes/scene2d/ui/Skin getRegion (Ljava/lang/String;)Lcom/badlogic/gdx/graphics/g2d/TextureRegion; 
L512:   bipush 50 
L514:   bipush 50 
L516:   bipush 50 
L518:   bipush 50 
L520:   invokespecial Method com/badlogic/gdx/graphics/g2d/NinePatch <init> (Lcom/badlogic/gdx/graphics/g2d/TextureRegion;IIII)V 
L523:   astore_3 
L524:   new com/badlogic/gdx/scenes/scene2d/ui/Image 
L527:   dup 
L528:   aload_3 
L529:   invokespecial Method com/badlogic/gdx/scenes/scene2d/ui/Image <init> (Lcom/badlogic/gdx/graphics/g2d/NinePatch;)V 
L532:   astore 4 
L534:   aload 4 
L536:   getstatic Field com/cairn4/moonbase/MoonBase SCREEN_WIDTH I 
L539:   bipush 60 
L541:   isub 
L542:   i2f 
L543:   getstatic Field com/cairn4/moonbase/MoonBase SCREEN_HEIGHT I 
L546:   bipush 60 
L548:   isub 
L549:   i2f 
L550:   invokevirtual Method com/badlogic/gdx/scenes/scene2d/ui/Image setSize (FF)V 
L553:   aload 4 
L555:   getstatic Field com/cairn4/moonbase/MoonBase SCREEN_WIDTH I 
L558:   iconst_2 
L559:   idiv 
L560:   i2f 
L561:   getstatic Field com/cairn4/moonbase/MoonBase SCREEN_HEIGHT I 
L564:   iconst_2 
L565:   idiv 
L566:   i2f 
L567:   iconst_1 
L568:   invokevirtual Method com/badlogic/gdx/scenes/scene2d/ui/Image setPosition (FFI)V 
L571:   aload 4 
L573:   iconst_1 
L574:   invokevirtual Method com/badlogic/gdx/scenes/scene2d/ui/Image setOrigin (I)V 
L577:   aload 4 
L579:   getstatic Field com/badlogic/gdx/scenes/scene2d/Touchable disabled Lcom/badlogic/gdx/scenes/scene2d/Touchable; 
L582:   invokevirtual Method com/badlogic/gdx/scenes/scene2d/ui/Image setTouchable (Lcom/badlogic/gdx/scenes/scene2d/Touchable;)V 
L585:   aload_0 
L586:   getfield Field com/cairn4/moonbase/ui/MiniMap uiGroup Lcom/badlogic/gdx/scenes/scene2d/Group; 
L589:   aload 4 
L591:   invokevirtual Method com/badlogic/gdx/scenes/scene2d/Group addActor (Lcom/badlogic/gdx/scenes/scene2d/Actor;)V 
L594:   aload 4 
L596:   fconst_0 
L597:   invokestatic Method com/badlogic/gdx/scenes/scene2d/actions/Actions alpha (F)Lcom/badlogic/gdx/scenes/scene2d/actions/AlphaAction; 
L600:   ldc_w +0.8799999952316284f 
L603:   ldc_w +0.8799999952316284f 
L606:   invokestatic Method com/badlogic/gdx/scenes/scene2d/actions/Actions scaleTo (FF)Lcom/badlogic/gdx/scenes/scene2d/actions/ScaleToAction; 
L609:   fconst_1 
L610:   fconst_1 
L611:   ldc_w +0.30000001192092896f 
L614:   getstatic Field com/badlogic/gdx/math/Interpolation sineOut Lcom/badlogic/gdx/math/Interpolation; 
L617:   invokestatic Method com/badlogic/gdx/scenes/scene2d/actions/Actions scaleTo (FFFLcom/badlogic/gdx/math/Interpolation;)Lcom/badlogic/gdx/scenes/scene2d/actions/ScaleToAction; 
L620:   ldc_w +0.800000011920929f 
L623:   ldc_w +0.20000000298023224f 
L626:   invokestatic Method com/badlogic/gdx/scenes/scene2d/actions/Actions alpha (FF)Lcom/badlogic/gdx/scenes/scene2d/actions/AlphaAction; 
L629:   ldc +0.10000000149011612f 
L631:   invokestatic Method com/badlogic/gdx/scenes/scene2d/actions/Actions fadeOut (F)Lcom/badlogic/gdx/scenes/scene2d/actions/AlphaAction; 
L634:   invokestatic Method com/badlogic/gdx/scenes/scene2d/actions/Actions sequence (Lcom/badlogic/gdx/scenes/scene2d/Action;Lcom/badlogic/gdx/scenes/scene2d/Action;)Lcom/badlogic/gdx/scenes/scene2d/actions/SequenceAction; 
L637:   invokestatic Method com/badlogic/gdx/scenes/scene2d/actions/Actions parallel (Lcom/badlogic/gdx/scenes/scene2d/Action;Lcom/badlogic/gdx/scenes/scene2d/Action;)Lcom/badlogic/gdx/scenes/scene2d/actions/ParallelAction; 
L640:   ldc_w +0.5f 
L643:   invokestatic Method com/badlogic/gdx/scenes/scene2d/actions/Actions delay (F)Lcom/badlogic/gdx/scenes/scene2d/actions/DelayAction; 
L646:   invokestatic Method com/badlogic/gdx/scenes/scene2d/actions/Actions sequence (Lcom/badlogic/gdx/scenes/scene2d/Action;Lcom/badlogic/gdx/scenes/scene2d/Action;Lcom/badlogic/gdx/scenes/scene2d/Action;Lcom/badlogic/gdx/scenes/scene2d/Action;)Lcom/badlogic/gdx/scenes/scene2d/actions/SequenceAction; 
L649:   invokevirtual Method com/badlogic/gdx/scenes/scene2d/ui/Image addAction (Lcom/badlogic/gdx/scenes/scene2d/Action;)V 
L652:   new com/badlogic/gdx/scenes/scene2d/Group 
L655:   dup 
L656:   invokespecial Method com/badlogic/gdx/scenes/scene2d/Group <init> ()V 
L659:   astore 5 
L661:   aload_0 
L662:   getfield Field com/cairn4/moonbase/ui/MiniMap uiGroup Lcom/badlogic/gdx/scenes/scene2d/Group; 
L665:   aload 5 
L667:   invokevirtual Method com/badlogic/gdx/scenes/scene2d/Group addActor (Lcom/badlogic/gdx/scenes/scene2d/Actor;)V 
L670:   aload 5 
L672:   fconst_0 
L673:   invokestatic Method com/badlogic/gdx/scenes/scene2d/actions/Actions alpha [u1118] 
L676:   ldc_w +0.20000000298023224f 
L679:   invokestatic Method com/badlogic/gdx/scenes/scene2d/actions/Actions delay (F)Lcom/badlogic/gdx/scenes/scene2d/actions/DelayAction; 
L682:   ldc +0.25f 
L684:   invokestatic Method com/badlogic/gdx/scenes/scene2d/actions/Actions fadeIn [u1118] 
L687:   invokestatic Method com/badlogic/gdx/scenes/scene2d/actions/Actions sequence (Lcom/badlogic/gdx/scenes/scene2d/Action;Lcom/badlogic/gdx/scenes/scene2d/Action;Lcom/badlogic/gdx/scenes/scene2d/Action;)Lcom/badlogic/gdx/scenes/scene2d/actions/SequenceAction; 
L690:   invokevirtual Method com/badlogic/gdx/scenes/scene2d/Group addAction (Lcom/badlogic/gdx/scenes/scene2d/Action;)V 
L693:   new com/badlogic/gdx/scenes/scene2d/ui/Image 
L696:   dup 
L697:   aload_0 
L698:   getfield Field com/cairn4/moonbase/ui/MiniMap baseScreen Lcom/cairn4/moonbase/ui/BaseScreen; 
L701:   getfield Field com/cairn4/moonbase/ui/BaseScreen skin Lcom/badlogic/gdx/scenes/scene2d/ui/Skin; 
L704:   ldc_w 'map/map-planet' 
L707:   invokevirtual Method com/badlogic/gdx/scenes/scene2d/ui/Skin getDrawable (Ljava/lang/String;)Lcom/badlogic/gdx/scenes/scene2d/utils/Drawable; 
L710:   invokespecial Method com/badlogic/gdx/scenes/scene2d/ui/Image <init> (Lcom/badlogic/gdx/scenes/scene2d/utils/Drawable;)V 
L713:   astore 6 
L715:   aload 6 
L717:   iconst_1 
L718:   invokevirtual Method com/badlogic/gdx/scenes/scene2d/ui/Image setOrigin (I)V 
L721:   aload 6 
L723:   ldc +30.0f 
L725:   getstatic Field com/cairn4/moonbase/MoonBase SCREEN_HEIGHT I 
L728:   bipush 26 
L730:   isub 
L731:   i2f 
L732:   bipush 10 
L734:   invokevirtual Method com/badlogic/gdx/scenes/scene2d/ui/Image setPosition (FFI)V 
L737:   aload 6 
L739:   getstatic Field com/badlogic/gdx/scenes/scene2d/Touchable disabled Lcom/badlogic/gdx/scenes/scene2d/Touchable; 
L742:   invokevirtual Method com/badlogic/gdx/scenes/scene2d/ui/Image setTouchable (Lcom/badlogic/gdx/scenes/scene2d/Touchable;)V 
L745:   aload 5 
L747:   aload 6 
L749:   invokevirtual Method com/badlogic/gdx/scenes/scene2d/Group addActor (Lcom/badlogic/gdx/scenes/scene2d/Actor;)V 
L752:   new com/badlogic/gdx/scenes/scene2d/ui/Button$ButtonStyle 
L755:   dup 
L756:   invokespecial Method com/badlogic/gdx/scenes/scene2d/ui/Button$ButtonStyle <init> ()V 
L759:   astore 7 
L761:   aload 7 
L763:   aload_0 
L764:   getfield Field com/cairn4/moonbase/ui/MiniMap skin Lcom/badlogic/gdx/scenes/scene2d/ui/Skin; 
L767:   ldc_w 'map/map-close-x' 
L770:   invokevirtual Method com/badlogic/gdx/scenes/scene2d/ui/Skin getDrawable (Ljava/lang/String;)Lcom/badlogic/gdx/scenes/scene2d/utils/Drawable; 
L773:   putfield Field com/badlogic/gdx/scenes/scene2d/ui/Button$ButtonStyle up Lcom/badlogic/gdx/scenes/scene2d/utils/Drawable; 
L776:   aload 7 
L778:   aload_0 
L779:   getfield Field com/cairn4/moonbase/ui/MiniMap skin Lcom/badlogic/gdx/scenes/scene2d/ui/Skin; 
L782:   ldc_w 'map/map-close-x-hover' 
L785:   invokevirtual Method com/badlogic/gdx/scenes/scene2d/ui/Skin getDrawable [u1078] 
L788:   putfield Field com/badlogic/gdx/scenes/scene2d/ui/Button$ButtonStyle over Lcom/badlogic/gdx/scenes/scene2d/utils/Drawable; 
L791:   aload 7 
L793:   aload_0 
L794:   getfield Field com/cairn4/moonbase/ui/MiniMap skin Lcom/badlogic/gdx/scenes/scene2d/ui/Skin; 
L797:   ldc_w 'map/map-close-x-pressed' 
L800:   invokevirtual Method com/badlogic/gdx/scenes/scene2d/ui/Skin getDrawable [u1078] 
L803:   putfield Field com/badlogic/gdx/scenes/scene2d/ui/Button$ButtonStyle down Lcom/badlogic/gdx/scenes/scene2d/utils/Drawable; 
L806:   aload_0 
L807:   new com/badlogic/gdx/scenes/scene2d/ui/Button 
L810:   dup 
L811:   aload 7 
L813:   invokespecial Method com/badlogic/gdx/scenes/scene2d/ui/Button <init> (Lcom/badlogic/gdx/scenes/scene2d/ui/Button$ButtonStyle;)V 
L816:   putfield Field com/cairn4/moonbase/ui/MiniMap btnClose Lcom/badlogic/gdx/scenes/scene2d/ui/Button; 
L819:   aload_0 
L820:   getfield Field com/cairn4/moonbase/ui/MiniMap btnClose Lcom/badlogic/gdx/scenes/scene2d/ui/Button; 
L823:   getstatic Field com/cairn4/moonbase/MoonBase SCREEN_WIDTH I 
L826:   bipush 70 
L828:   isub 
L829:   i2f 
L830:   getstatic Field com/cairn4/moonbase/MoonBase SCREEN_HEIGHT I 
L833:   bipush 68 
L835:   isub 
L836:   i2f 
L837:   bipush 18 
L839:   invokevirtual Method com/badlogic/gdx/scenes/scene2d/ui/Button setPosition (FFI)V 
L842:   aload_0 
L843:   getfield Field com/cairn4/moonbase/ui/MiniMap btnClose Lcom/badlogic/gdx/scenes/scene2d/ui/Button; 
L846:   new com/cairn4/moonbase/ui/MiniMap$1 
L849:   dup 
L850:   aload_0 
L851:   invokespecial Method com/cairn4/moonbase/ui/MiniMap$1 <init> (Lcom/cairn4/moonbase/ui/MiniMap;)V 
L854:   invokevirtual Method com/badlogic/gdx/scenes/scene2d/ui/Button addListener (Lcom/badlogic/gdx/scenes/scene2d/EventListener;)Z 
L857:   pop 
L858:   aload 5 
L860:   aload_0 
L861:   getfield Field com/cairn4/moonbase/ui/MiniMap btnClose Lcom/badlogic/gdx/scenes/scene2d/ui/Button; 
L864:   invokevirtual Method com/badlogic/gdx/scenes/scene2d/Group addActor (Lcom/badlogic/gdx/scenes/scene2d/Actor;)V 
L867:   new com/badlogic/gdx/scenes/scene2d/Group 
L870:   dup 
L871:   invokespecial Method com/badlogic/gdx/scenes/scene2d/Group <init> ()V 
L874:   astore 8 
L876:   aload 8 
L878:   ldc_w +60.0f 
L881:   ldc_w +69.0f 
L884:   invokevirtual Method com/badlogic/gdx/scenes/scene2d/Group setPosition (FF)V 
L887:   aload 5 
L889:   aload 8 
L891:   invokevirtual Method com/badlogic/gdx/scenes/scene2d/Group addActor (Lcom/badlogic/gdx/scenes/scene2d/Actor;)V 
L894:   new com/badlogic/gdx/scenes/scene2d/ui/Button$ButtonStyle 
L897:   dup 
L898:   invokespecial Method com/badlogic/gdx/scenes/scene2d/ui/Button$ButtonStyle <init> ()V 
L901:   astore 9 
L903:   aload 9 
L905:   aload_0 
L906:   getfield Field com/cairn4/moonbase/ui/MiniMap skin Lcom/badlogic/gdx/scenes/scene2d/ui/Skin; 
L909:   ldc_w 'map/map-zoom-in' 
L912:   invokevirtual Method com/badlogic/gdx/scenes/scene2d/ui/Skin getDrawable [u1078] 
L915:   putfield Field com/badlogic/gdx/scenes/scene2d/ui/Button$ButtonStyle up Lcom/badlogic/gdx/scenes/scene2d/utils/Drawable; 
L918:   aload 9 
L920:   aload_0 
L921:   getfield Field com/cairn4/moonbase/ui/MiniMap skin Lcom/badlogic/gdx/scenes/scene2d/ui/Skin; 
L924:   ldc_w 'map/map-zoom-in-hover' 
L927:   invokevirtual Method com/badlogic/gdx/scenes/scene2d/ui/Skin getDrawable [u1078] 
L930:   putfield Field com/badlogic/gdx/scenes/scene2d/ui/Button$ButtonStyle over Lcom/badlogic/gdx/scenes/scene2d/utils/Drawable; 
L933:   aload 9 
L935:   aload_0 
L936:   getfield Field com/cairn4/moonbase/ui/MiniMap skin Lcom/badlogic/gdx/scenes/scene2d/ui/Skin; 
L939:   ldc_w 'map/map-zoom-in' 
L942:   invokevirtual Method com/badlogic/gdx/scenes/scene2d/ui/Skin getDrawable [u1078] 
L945:   putfield Field com/badlogic/gdx/scenes/scene2d/ui/Button$ButtonStyle down Lcom/badlogic/gdx/scenes/scene2d/utils/Drawable; 
L948:   aload_0 
L949:   new com/badlogic/gdx/scenes/scene2d/ui/Button 
L952:   dup 
L953:   aload 9 
L955:   invokespecial Method com/badlogic/gdx/scenes/scene2d/ui/Button <init> (Lcom/badlogic/gdx/scenes/scene2d/ui/Button$ButtonStyle;)V 
L958:   putfield Field com/cairn4/moonbase/ui/MiniMap btnZoomIn Lcom/badlogic/gdx/scenes/scene2d/ui/Button; 
L961:   aload_0 
L962:   getfield Field com/cairn4/moonbase/ui/MiniMap btnZoomIn Lcom/badlogic/gdx/scenes/scene2d/ui/Button; 
L965:   new com/cairn4/moonbase/ui/MiniMap$2 
L968:   dup 
L969:   aload_0 
L970:   invokespecial Method com/cairn4/moonbase/ui/MiniMap$2 <init> (Lcom/cairn4/moonbase/ui/MiniMap;)V 
L973:   invokevirtual Method com/badlogic/gdx/scenes/scene2d/ui/Button addListener (Lcom/badlogic/gdx/scenes/scene2d/EventListener;)Z 
L976:   pop 
L977:   aload 8 
L979:   aload_0 
L980:   getfield Field com/cairn4/moonbase/ui/MiniMap btnZoomIn Lcom/badlogic/gdx/scenes/scene2d/ui/Button; 
L983:   invokevirtual Method com/badlogic/gdx/scenes/scene2d/Group addActor (Lcom/badlogic/gdx/scenes/scene2d/Actor;)V 
L986:   aload_0 
L987:   new com/badlogic/gdx/scenes/scene2d/ui/Image 
L990:   dup 
L991:   aload_0 
L992:   getfield Field com/cairn4/moonbase/ui/MiniMap baseScreen Lcom/cairn4/moonbase/ui/BaseScreen; 
L995:   getfield Field com/cairn4/moonbase/ui/BaseScreen skin Lcom/badlogic/gdx/scenes/scene2d/ui/Skin; 
L998:   ldc_w 'map/map-zoom-div' 
L1001:  invokevirtual Method com/badlogic/gdx/scenes/scene2d/ui/Skin getDrawable [u1078] 
L1004:  invokespecial Method com/badlogic/gdx/scenes/scene2d/ui/Image <init> (Lcom/badlogic/gdx/scenes/scene2d/utils/Drawable;)V 
L1007:  putfield Field com/cairn4/moonbase/ui/MiniMap zoomDiv Lcom/badlogic/gdx/scenes/scene2d/ui/Image; 
L1010:  aload_0 
L1011:  getfield Field com/cairn4/moonbase/ui/MiniMap zoomDiv Lcom/badlogic/gdx/scenes/scene2d/ui/Image; 
L1014:  ldc_w +62.0f 
L1017:  ldc_w -5.0f 
L1020:  invokevirtual Method com/badlogic/gdx/scenes/scene2d/ui/Image setPosition (FF)V 
L1023:  aload 8 
L1025:  aload_0 
L1026:  getfield Field com/cairn4/moonbase/ui/MiniMap zoomDiv Lcom/badlogic/gdx/scenes/scene2d/ui/Image; 
L1029:  invokevirtual Method com/badlogic/gdx/scenes/scene2d/Group addActor (Lcom/badlogic/gdx/scenes/scene2d/Actor;)V 
L1032:  new [c287] 
L1035:  dup 
L1036:  invokespecial Method [c287] <init> ()V 
L1039:  astore 10 
L1041:  aload 10 
L1043:  aload_0 
L1044:  getfield Field com/cairn4/moonbase/ui/MiniMap skin Lcom/badlogic/gdx/scenes/scene2d/ui/Skin; 
L1047:  ldc_w 'map/map-zoom-out' 
L1050:  invokevirtual Method com/badlogic/gdx/scenes/scene2d/ui/Skin getDrawable [u1078] 
L1053:  putfield Field [c287] up Lcom/badlogic/gdx/scenes/scene2d/utils/Drawable; 
L1056:  aload 10 
L1058:  aload_0 
L1059:  getfield Field com/cairn4/moonbase/ui/MiniMap skin Lcom/badlogic/gdx/scenes/scene2d/ui/Skin; 
L1062:  ldc_w 'map/map-zoom-out-hover' 
L1065:  invokevirtual Method com/badlogic/gdx/scenes/scene2d/ui/Skin getDrawable [u1078] 
L1068:  putfield Field [c287] over Lcom/badlogic/gdx/scenes/scene2d/utils/Drawable; 
L1071:  aload 10 
L1073:  aload_0 
L1074:  getfield Field com/cairn4/moonbase/ui/MiniMap skin Lcom/badlogic/gdx/scenes/scene2d/ui/Skin; 
L1077:  ldc_w 'map/map-zoom-out' 
L1080:  invokevirtual Method com/badlogic/gdx/scenes/scene2d/ui/Skin getDrawable [u1078] 
L1083:  putfield Field [c287] down Lcom/badlogic/gdx/scenes/scene2d/utils/Drawable; 
L1086:  aload_0 
L1087:  new com/badlogic/gdx/scenes/scene2d/ui/Button 
L1090:  dup 
L1091:  aload 10 
L1093:  invokespecial Method com/badlogic/gdx/scenes/scene2d/ui/Button <init> (Lcom/badlogic/gdx/scenes/scene2d/ui/Button$ButtonStyle;)V 
L1096:  putfield Field com/cairn4/moonbase/ui/MiniMap btnZoomOut Lcom/badlogic/gdx/scenes/scene2d/ui/Button; 
L1099:  aload_0 
L1100:  getfield Field com/cairn4/moonbase/ui/MiniMap btnZoomOut Lcom/badlogic/gdx/scenes/scene2d/ui/Button; 
L1103:  ldc_w +62.0f 
L1106:  aload_0 
L1107:  getfield Field com/cairn4/moonbase/ui/MiniMap zoomDiv Lcom/badlogic/gdx/scenes/scene2d/ui/Image; 
L1110:  invokevirtual Method com/badlogic/gdx/scenes/scene2d/ui/Image getWidth ()F 
L1113:  fadd 
L1114:  ldc +5.0f 
L1116:  fsub 
L1117:  ldc_w +3.0f 
L1120:  fadd 
L1121:  ldc_w +16.0f 
L1124:  invokevirtual Method com/badlogic/gdx/scenes/scene2d/ui/Button setPosition (FF)V 
L1127:  aload_0 
L1128:  getfield Field com/cairn4/moonbase/ui/MiniMap btnZoomOut Lcom/badlogic/gdx/scenes/scene2d/ui/Button; 
L1131:  new com/cairn4/moonbase/ui/MiniMap$3 
L1134:  dup 
L1135:  aload_0 
L1136:  invokespecial Method com/cairn4/moonbase/ui/MiniMap$3 <init> (Lcom/cairn4/moonbase/ui/MiniMap;)V 
L1139:  invokevirtual Method com/badlogic/gdx/scenes/scene2d/ui/Button addListener (Lcom/badlogic/gdx/scenes/scene2d/EventListener;)Z 
L1142:  pop 
L1143:  aload 8 
L1145:  aload_0 
L1146:  getfield Field com/cairn4/moonbase/ui/MiniMap btnZoomOut Lcom/badlogic/gdx/scenes/scene2d/ui/Button; 
L1149:  invokevirtual Method com/badlogic/gdx/scenes/scene2d/Group addActor (Lcom/badlogic/gdx/scenes/scene2d/Actor;)V 
L1152:  new [c287] 
L1155:  dup 
L1156:  invokespecial Method [c287] <init> ()V 
L1159:  astore 11 
L1161:  aload 11 
L1163:  aload_0 
L1164:  getfield Field com/cairn4/moonbase/ui/MiniMap skin Lcom/badlogic/gdx/scenes/scene2d/ui/Skin; 
L1167:  ldc_w 'map/map-locate' 
L1170:  invokevirtual Method com/badlogic/gdx/scenes/scene2d/ui/Skin getDrawable [u1078] 
L1173:  putfield Field [c287] up Lcom/badlogic/gdx/scenes/scene2d/utils/Drawable; 
L1176:  aload 11 
L1178:  aload_0 
L1179:  getfield Field com/cairn4/moonbase/ui/MiniMap skin Lcom/badlogic/gdx/scenes/scene2d/ui/Skin; 
L1182:  ldc_w 'map/map-locate-hover' 
L1185:  invokevirtual Method com/badlogic/gdx/scenes/scene2d/ui/Skin getDrawable [u1078] 
L1188:  putfield Field [c287] over Lcom/badlogic/gdx/scenes/scene2d/utils/Drawable; 
L1191:  aload 11 
L1193:  aload_0 
L1194:  getfield Field com/cairn4/moonbase/ui/MiniMap skin Lcom/badlogic/gdx/scenes/scene2d/ui/Skin; 
L1197:  ldc_w 'map/map-locate' 
L1200:  invokevirtual Method com/badlogic/gdx/scenes/scene2d/ui/Skin getDrawable [u1078] 
L1203:  putfield Field [c287] down Lcom/badlogic/gdx/scenes/scene2d/utils/Drawable; 
L1206:  aload_0 
L1207:  new com/badlogic/gdx/scenes/scene2d/ui/Button 
L1210:  dup 
L1211:  aload 11 
L1213:  invokespecial Method com/badlogic/gdx/scenes/scene2d/ui/Button <init> (Lcom/badlogic/gdx/scenes/scene2d/ui/Button$ButtonStyle;)V 
L1216:  putfield Field com/cairn4/moonbase/ui/MiniMap btnRecenter Lcom/badlogic/gdx/scenes/scene2d/ui/Button; 
L1219:  aload_0 
L1220:  getfield Field com/cairn4/moonbase/ui/MiniMap btnRecenter Lcom/badlogic/gdx/scenes/scene2d/ui/Button; 
L1223:  getstatic Field com/cairn4/moonbase/MoonBase SCREEN_WIDTH I 
L1226:  bipush 55 
L1228:  isub 
L1229:  i2f 
L1230:  ldc_w +59.0f 
L1233:  bipush 20 
L1235:  invokevirtual Method com/badlogic/gdx/scenes/scene2d/ui/Button setPosition (FFI)V 
L1238:  aload_0 
L1239:  getfield Field com/cairn4/moonbase/ui/MiniMap btnRecenter Lcom/badlogic/gdx/scenes/scene2d/ui/Button; 
L1242:  new com/cairn4/moonbase/ui/MiniMap$4 
L1245:  dup 
L1246:  aload_0 
L1247:  invokespecial Method com/cairn4/moonbase/ui/MiniMap$4 <init> (Lcom/cairn4/moonbase/ui/MiniMap;)V 
L1250:  invokevirtual Method com/badlogic/gdx/scenes/scene2d/ui/Button addListener (Lcom/badlogic/gdx/scenes/scene2d/EventListener;)Z 
L1253:  pop 
L1254:  aload 5 
L1256:  aload_0 
L1257:  getfield Field com/cairn4/moonbase/ui/MiniMap btnRecenter Lcom/badlogic/gdx/scenes/scene2d/ui/Button; 
L1260:  invokevirtual Method com/badlogic/gdx/scenes/scene2d/Group addActor (Lcom/badlogic/gdx/scenes/scene2d/Actor;)V 
L1263:  new com/badlogic/gdx/scenes/scene2d/ui/Label 
L1266:  dup 
L1267:  ldc_w 'map_planetSurvey' 
L1270:  invokestatic Method com/cairn4/moonbase/ui/Localization get (Ljava/lang/String;)Ljava/lang/String; 
L1273:  aload_0 
L1274:  getfield Field com/cairn4/moonbase/ui/MiniMap labelStyle Lcom/badlogic/gdx/scenes/scene2d/ui/Label$LabelStyle; 
L1277:  invokespecial Method com/badlogic/gdx/scenes/scene2d/ui/Label <init> (Ljava/lang/CharSequence;Lcom/badlogic/gdx/scenes/scene2d/ui/Label$LabelStyle;)V 
L1280:  astore 12 
L1282:  aload 12 
L1284:  ldc_w +0.3499999940395355f 
L1287:  invokevirtual Method com/badlogic/gdx/scenes/scene2d/ui/Label setFontScale (F)V 
L1290:  aload 12 
L1292:  getstatic Field com/cairn4/moonbase/ui/Menu MENU_COLOR Lcom/badlogic/gdx/graphics/Color; 
L1295:  invokevirtual Method com/badlogic/gdx/scenes/scene2d/ui/Label setColor (Lcom/badlogic/gdx/graphics/Color;)V 
L1298:  aload 12 
L1300:  ldc_w +172.0f 
L1303:  getstatic Field com/cairn4/moonbase/MoonBase SCREEN_HEIGHT I 
L1306:  bipush 85 
L1308:  isub 
L1309:  i2f 
L1310:  bipush 8 
L1312:  invokevirtual Method com/badlogic/gdx/scenes/scene2d/ui/Label setPosition (FFI)V 
L1315:  aload 5 
L1317:  aload 12 
L1319:  invokevirtual Method com/badlogic/gdx/scenes/scene2d/Group addActor (Lcom/badlogic/gdx/scenes/scene2d/Actor;)V 
L1322:  new com/badlogic/gdx/scenes/scene2d/ui/Label 
L1325:  dup 
L1326:  aload_0 
L1327:  getfield Field com/cairn4/moonbase/ui/MiniMap gameScreen Lcom/cairn4/moonbase/ui/GameScreen; 
L1330:  getfield Field com/cairn4/moonbase/ui/GameScreen game Lcom/cairn4/moonbase/MoonBase; 
L1333:  pop 
L1334:  invokestatic Method com/cairn4/moonbase/MoonBase getCurrentMission ()Lcom/cairn4/moonbase/Mission; 
L1337:  invokevirtual Method com/cairn4/moonbase/Mission getPlanetName ()Ljava/lang/String; 
L1340:  aload_0 
L1341:  getfield Field com/cairn4/moonbase/ui/MiniMap labelStyle Lcom/badlogic/gdx/scenes/scene2d/ui/Label$LabelStyle; 
L1344:  invokespecial Method com/badlogic/gdx/scenes/scene2d/ui/Label <init> (Ljava/lang/CharSequence;Lcom/badlogic/gdx/scenes/scene2d/ui/Label$LabelStyle;)V 
L1347:  astore 13 
L1349:  aload 13 
L1351:  ldc_w +0.5f 
L1354:  invokevirtual Method com/badlogic/gdx/scenes/scene2d/ui/Label setFontScale (F)V 
L1357:  aload 13 
L1359:  getstatic Field com/cairn4/moonbase/ui/Menu MENU_COLOR Lcom/badlogic/gdx/graphics/Color; 
L1362:  invokevirtual Method com/badlogic/gdx/scenes/scene2d/ui/Label setColor (Lcom/badlogic/gdx/graphics/Color;)V 
L1365:  aload 13 
L1367:  ldc_w +172.0f 
L1370:  getstatic Field com/cairn4/moonbase/MoonBase SCREEN_HEIGHT I 
L1373:  bipush 113 
L1375:  isub 
L1376:  i2f 
L1377:  bipush 8 
L1379:  invokevirtual Method com/badlogic/gdx/scenes/scene2d/ui/Label setPosition (FFI)V 
L1382:  aload 5 
L1384:  aload 13 
L1386:  invokevirtual Method com/badlogic/gdx/scenes/scene2d/Group addActor (Lcom/badlogic/gdx/scenes/scene2d/Actor;)V 
L1389:  aload_0 
L1390:  new com/badlogic/gdx/scenes/scene2d/ui/Label 
L1393:  dup 
L1394:  new java/lang/StringBuilder 
L1397:  dup 
L1398:  invokespecial Method java/lang/StringBuilder <init> ()V 
L1401:  ldc_w '- ' 
L1404:  invokevirtual Method java/lang/StringBuilder append (Ljava/lang/String;)Ljava/lang/StringBuilder; 
L1407:  ldc_w 'paused' 
L1410:  invokestatic Method com/cairn4/moonbase/ui/Localization get (Ljava/lang/String;)Ljava/lang/String; 
L1413:  invokevirtual Method java/lang/StringBuilder append (Ljava/lang/String;)Ljava/lang/StringBuilder; 
L1416:  ldc_w ' -' 
L1419:  invokevirtual Method java/lang/StringBuilder append (Ljava/lang/String;)Ljava/lang/StringBuilder; 
L1422:  invokevirtual Method java/lang/StringBuilder toString ()Ljava/lang/String; 
L1425:  aload_0 
L1426:  getfield Field com/cairn4/moonbase/ui/MiniMap labelStyle Lcom/badlogic/gdx/scenes/scene2d/ui/Label$LabelStyle; 
L1429:  invokespecial Method com/badlogic/gdx/scenes/scene2d/ui/Label <init> (Ljava/lang/CharSequence;Lcom/badlogic/gdx/scenes/scene2d/ui/Label$LabelStyle;)V 
L1432:  putfield Field com/cairn4/moonbase/ui/MiniMap pauseLabel Lcom/badlogic/gdx/scenes/scene2d/ui/Label; 
L1435:  aload_0 
L1436:  getfield Field com/cairn4/moonbase/ui/MiniMap pauseLabel Lcom/badlogic/gdx/scenes/scene2d/ui/Label; 
L1439:  ldc_w +0.5f 
L1442:  invokevirtual Method com/badlogic/gdx/scenes/scene2d/ui/Label setFontScale (F)V 
L1445:  aload_0 
L1446:  getfield Field com/cairn4/moonbase/ui/MiniMap pauseLabel Lcom/badlogic/gdx/scenes/scene2d/ui/Label; 
L1449:  iconst_1 
L1450:  invokevirtual Method com/badlogic/gdx/scenes/scene2d/ui/Label setAlignment (I)V 
L1453:  aload_0 
L1454:  getfield Field com/cairn4/moonbase/ui/MiniMap pauseLabel Lcom/badlogic/gdx/scenes/scene2d/ui/Label; 
L1457:  getstatic Field com/cairn4/moonbase/ui/Menu MENU_COLOR Lcom/badlogic/gdx/graphics/Color; 
L1460:  invokevirtual Method com/badlogic/gdx/scenes/scene2d/ui/Label setColor (Lcom/badlogic/gdx/graphics/Color;)V 
L1463:  aload_0 
L1464:  getfield Field com/cairn4/moonbase/ui/MiniMap pauseLabel Lcom/badlogic/gdx/scenes/scene2d/ui/Label; 
L1467:  getstatic Field com/cairn4/moonbase/MoonBase SCREEN_WIDTH I 
L1470:  iconst_2 
L1471:  idiv 
L1472:  i2f 
L1473:  getstatic Field com/cairn4/moonbase/MoonBase SCREEN_HEIGHT I 
L1476:  bipush 85 
L1478:  isub 
L1479:  i2f 
L1480:  iconst_1 
L1481:  invokevirtual Method com/badlogic/gdx/scenes/scene2d/ui/Label setPosition (FFI)V 
L1484:  aload 5 
L1486:  aload_0 
L1487:  getfield Field com/cairn4/moonbase/ui/MiniMap pauseLabel Lcom/badlogic/gdx/scenes/scene2d/ui/Label; 

L1493:  aload_0 
L1494:  invokespecial Method com/cairn4/moonbase/ui/MiniMap setupHoverLabel ()V 
L1497:  return 
L1498:  
        .linenumbertable 
            L0 813 
            L4 817 
            L15 819 
            L26 824 
            L31 825 
            L36 826 
            L39 824 
            L45 830 
            L65 831 
            L77 832 
            L98 833 
            L111 834 
            L122 835 
            L129 840 
            L140 841 
            L159 842 
            L170 844 
            L181 845 
            L192 848 
            L203 849 
            L214 855 
            L225 856 
            L236 862 
            L265 864 
            L277 865 
            L296 866 
            L309 867 
            L319 868 
            L330 871 
            L345 872 
            L351 873 
            L360 874 
            L363 871 
            L369 878 
            L400 880 
            L412 881 
            L437 882 
            L449 883 
            L459 884 
            L470 886 
            L475 887 
            L480 888 
            L486 889 
            L489 886 
            L495 898 
            L524 900 
            L534 901 
            L553 902 
            L571 903 
            L577 904 
            L585 905 
            L594 907 
            L597 909 
            L606 910 
            L617 912 
            L626 914 
            L631 915 
            L634 913 
            L637 911 
            L643 918 
            L646 908 
            L649 907 
            L652 924 
            L661 925 
            L670 926 
            L673 927 
            L679 928 
            L684 929 
            L687 926 
            L693 933 
            L715 934 
            L721 935 
            L737 936 
            L745 937 
            L752 940 
            L761 941 
            L776 942 
            L791 943 
            L806 945 
            L819 946 
            L842 947 
            L858 952 
            L867 955 
            L876 956 
            L887 957 
            L894 959 
            L903 960 
            L918 961 
            L933 962 
            L948 964 
            L961 965 
            L977 978 
            L986 981 
            L1010 982 
            L1023 983 
            L1032 986 
            L1041 987 
            L1056 988 
            L1071 989 
            L1086 991 
            L1099 992 
            L1127 993 
            L1143 1006 
            L1152 1011 
            L1161 1012 
            L1176 1013 
            L1191 1014 
            L1206 1016 
            L1219 1017 
            L1238 1018 
            L1254 1025 
            L1263 1045 
            L1282 1046 
            L1290 1047 
            L1298 1048 
            L1315 1049 
            L1322 1051 
            L1349 1052 
            L1357 1053 
            L1365 1054 
            L1382 1055 
            L1389 1057 
            L1435 1058 
            L1445 1059 
            L1453 1060 
            L1463 1061 
            L1484 1062 
            L1493 1065 
            L1497 1069 
        .end linenumbertable 
        .localvariabletable 
            0 is this Lcom/cairn4/moonbase/ui/MiniMap; from L0 to L1498 
            1 is borderPatch Lcom/badlogic/gdx/graphics/g2d/NinePatch; from L265 to L1498 
            2 is innerBorderPatch Lcom/badlogic/gdx/graphics/g2d/NinePatch; from L400 to L1498 
            3 is introBorderPatch Lcom/badlogic/gdx/graphics/g2d/NinePatch; from L524 to L1498 
            4 is introBorder Lcom/badlogic/gdx/scenes/scene2d/ui/Image; from L534 to L1498 
            5 is widgetGroup Lcom/badlogic/gdx/scenes/scene2d/Group; from L661 to L1498 
            6 is planet Lcom/badlogic/gdx/scenes/scene2d/ui/Image; from L715 to L1498 
            7 is bs Lcom/badlogic/gdx/scenes/scene2d/ui/Button$ButtonStyle; from L761 to L1498 
            8 is zoomGroup Lcom/badlogic/gdx/scenes/scene2d/Group; from L876 to L1498 
            9 is bstyleZoomIn Lcom/badlogic/gdx/scenes/scene2d/ui/Button$ButtonStyle; from L903 to L1498 
            10 is bstyleZoomOut Lcom/badlogic/gdx/scenes/scene2d/ui/Button$ButtonStyle; from L1041 to L1498 
            11 is bstyleCenter Lcom/badlogic/gdx/scenes/scene2d/ui/Button$ButtonStyle; from L1161 to L1498 
            12 is planetSurvey Lcom/badlogic/gdx/scenes/scene2d/ui/Label; from L1282 to L1498 
            13 is planetName Lcom/badlogic/gdx/scenes/scene2d/ui/Label; from L1349 to L1498 
        .end localvariabletable 
    .end code 
.end method 

.method private setupHoverLabel : ()V 
    .code stack 7 locals 2 
L0:     aload_0 
L1:     new com/badlogic/gdx/scenes/scene2d/Group 
L4:     dup 
L5:     invokespecial Method com/badlogic/gdx/scenes/scene2d/Group <init> ()V 
L8:     putfield Field com/cairn4/moonbase/ui/MiniMap hoverTooltipGroup Lcom/badlogic/gdx/scenes/scene2d/Group; 
L11:    aload_0 
L12:    getfield Field com/cairn4/moonbase/ui/MiniMap hoverTooltipGroup Lcom/badlogic/gdx/scenes/scene2d/Group; 
L15:    getstatic Field com/cairn4/moonbase/MoonBase SCREEN_WIDTH I 
L18:    iconst_2 
L19:    idiv 
L20:    i2f 
L21:    ldc_w +85.0f 
L24:    invokevirtual Method com/badlogic/gdx/scenes/scene2d/Group setPosition (FF)V 
L27:    aload_0 
L28:    getfield Field com/cairn4/moonbase/ui/MiniMap uiGroup Lcom/badlogic/gdx/scenes/scene2d/Group; 
L31:    aload_0 
L32:    getfield Field com/cairn4/moonbase/ui/MiniMap hoverTooltipGroup Lcom/badlogic/gdx/scenes/scene2d/Group; 
L35:    invokevirtual Method com/badlogic/gdx/scenes/scene2d/Group addActor (Lcom/badlogic/gdx/scenes/scene2d/Actor;)V 
L38:    aload_0 
L39:    new com/badlogic/gdx/scenes/scene2d/Group 
L42:    dup 
L43:    invokespecial Method com/badlogic/gdx/scenes/scene2d/Group <init> ()V 
L46:    putfield Field com/cairn4/moonbase/ui/MiniMap hoverInnerGroup Lcom/badlogic/gdx/scenes/scene2d/Group; 
L49:    aload_0 
L50:    getfield Field com/cairn4/moonbase/ui/MiniMap hoverInnerGroup Lcom/badlogic/gdx/scenes/scene2d/Group; 
L53:    ldc_w +15.0f 
L56:    ldc_w +15.0f 
L59:    invokevirtual Method com/badlogic/gdx/scenes/scene2d/Group setPosition (FF)V 
L62:    aload_0 
L63:    getfield Field com/cairn4/moonbase/ui/MiniMap hoverTooltipGroup Lcom/badlogic/gdx/scenes/scene2d/Group; 
L66:    aload_0 
L67:    getfield Field com/cairn4/moonbase/ui/MiniMap hoverInnerGroup Lcom/badlogic/gdx/scenes/scene2d/Group; 
L70:    invokevirtual Method com/badlogic/gdx/scenes/scene2d/Group addActor (Lcom/badlogic/gdx/scenes/scene2d/Actor;)V 
L73:    new com/badlogic/gdx/graphics/g2d/NinePatch 
L76:    dup 
L77:    aload_0 
L78:    getfield Field com/cairn4/moonbase/ui/MiniMap baseScreen Lcom/cairn4/moonbase/ui/BaseScreen; 
L81:    getfield Field com/cairn4/moonbase/ui/BaseScreen skin Lcom/badlogic/gdx/scenes/scene2d/ui/Skin; 
L84:    ldc_w 'roundedbox' 
L87:    invokevirtual Method com/badlogic/gdx/scenes/scene2d/ui/Skin getRegion (Ljava/lang/String;)Lcom/badlogic/gdx/graphics/g2d/TextureRegion; 
L90:    bipush 18 
L92:    bipush 18 
L94:    bipush 18 
L96:    bipush 18 
L98:    invokespecial Method com/badlogic/gdx/graphics/g2d/NinePatch <init> (Lcom/badlogic/gdx/graphics/g2d/TextureRegion;IIII)V 
L101:   astore_1 
L102:   aload_0 
L103:   new com/badlogic/gdx/scenes/scene2d/ui/Image 
L106:   dup 
L107:   aload_1 
L108:   invokespecial Method com/badlogic/gdx/scenes/scene2d/ui/Image <init> (Lcom/badlogic/gdx/graphics/g2d/NinePatch;)V 
L111:   putfield Field com/cairn4/moonbase/ui/MiniMap hoverPanel Lcom/badlogic/gdx/scenes/scene2d/ui/Image; 
L114:   aload_0 
L115:   getfield Field com/cairn4/moonbase/ui/MiniMap hoverPanel Lcom/badlogic/gdx/scenes/scene2d/ui/Image; 
L118:   fconst_0 
L119:   fconst_0 
L120:   fconst_0 
L121:   ldc_w +0.800000011920929f 
L124:   invokevirtual Method com/badlogic/gdx/scenes/scene2d/ui/Image setColor (FFFF)V 
L127:   aload_0 
L128:   getfield Field com/cairn4/moonbase/ui/MiniMap hoverPanel Lcom/badlogic/gdx/scenes/scene2d/ui/Image; 
L131:   fconst_0 
L132:   fconst_0 
L133:   iconst_1 
L134:   invokevirtual Method com/badlogic/gdx/scenes/scene2d/ui/Image setPosition (FFI)V 
L137:   aload_0 
L138:   getfield Field com/cairn4/moonbase/ui/MiniMap hoverInnerGroup Lcom/badlogic/gdx/scenes/scene2d/Group; 
L141:   aload_0 
L142:   getfield Field com/cairn4/moonbase/ui/MiniMap hoverPanel Lcom/badlogic/gdx/scenes/scene2d/ui/Image; 
L145:   invokevirtual Method com/badlogic/gdx/scenes/scene2d/Group addActor (Lcom/badlogic/gdx/scenes/scene2d/Actor;)V 
L148:   aload_0 
L149:   getfield Field com/cairn4/moonbase/ui/MiniMap hoverPanel Lcom/badlogic/gdx/scenes/scene2d/ui/Image; 
L152:   getstatic Field com/badlogic/gdx/scenes/scene2d/Touchable disabled Lcom/badlogic/gdx/scenes/scene2d/Touchable; 
L155:   invokevirtual Method com/badlogic/gdx/scenes/scene2d/ui/Image setTouchable (Lcom/badlogic/gdx/scenes/scene2d/Touchable;)V 
L158:   aload_0 
L159:   new com/badlogic/gdx/scenes/scene2d/ui/Table 
L162:   dup 
L163:   invokespecial Method com/badlogic/gdx/scenes/scene2d/ui/Table <init> ()V 
L166:   putfield Field com/cairn4/moonbase/ui/MiniMap hoverTooltipTable Lcom/badlogic/gdx/scenes/scene2d/ui/Table; 
L169:   aload_0 
L170:   getfield Field com/cairn4/moonbase/ui/MiniMap hoverTooltipTable Lcom/badlogic/gdx/scenes/scene2d/ui/Table; 
L173:   fconst_0 
L174:   fconst_0 
L175:   invokevirtual Method com/badlogic/gdx/scenes/scene2d/ui/Table setPosition (FF)V 
L178:   aload_0 
L179:   getfield Field com/cairn4/moonbase/ui/MiniMap hoverTooltipTable Lcom/badlogic/gdx/scenes/scene2d/ui/Table; 
L182:   invokevirtual Method com/badlogic/gdx/scenes/scene2d/ui/Table center ()Lcom/badlogic/gdx/scenes/scene2d/ui/Table; 
L185:   pop 
L186:   aload_0 
L187:   getfield Field com/cairn4/moonbase/ui/MiniMap hoverInnerGroup Lcom/badlogic/gdx/scenes/scene2d/Group; 
L190:   aload_0 
L191:   getfield Field com/cairn4/moonbase/ui/MiniMap hoverTooltipTable Lcom/badlogic/gdx/scenes/scene2d/ui/Table; 
L194:   invokevirtual Method com/badlogic/gdx/scenes/scene2d/Group addActor (Lcom/badlogic/gdx/scenes/scene2d/Actor;)V 
L197:   aload_0 
L198:   new com/badlogic/gdx/scenes/scene2d/ui/Label 
L201:   dup 
L202:   ldc_w '---' 
L205:   aload_0 
L206:   getfield Field com/cairn4/moonbase/ui/MiniMap baseScreen Lcom/cairn4/moonbase/ui/BaseScreen; 
L209:   getfield Field com/cairn4/moonbase/ui/BaseScreen labelStyle Lcom/badlogic/gdx/scenes/scene2d/ui/Label$LabelStyle; 
L212:   invokespecial Method com/badlogic/gdx/scenes/scene2d/ui/Label <init> (Ljava/lang/CharSequence;Lcom/badlogic/gdx/scenes/scene2d/ui/Label$LabelStyle;)V 
L215:   putfield Field com/cairn4/moonbase/ui/MiniMap hoverLabel Lcom/badlogic/gdx/scenes/scene2d/ui/Label; 
L218:   aload_0 
L219:   getfield Field com/cairn4/moonbase/ui/MiniMap hoverLabel Lcom/badlogic/gdx/scenes/scene2d/ui/Label; 
L222:   ldc_w +0.3499999940395355f 
L225:   invokevirtual Method com/badlogic/gdx/scenes/scene2d/ui/Label setFontScale (F)V 
L228:   aload_0 
L229:   getfield Field com/cairn4/moonbase/ui/MiniMap hoverLabel Lcom/badlogic/gdx/scenes/scene2d/ui/Label; 
L232:   fconst_1 
L233:   fconst_1 
L234:   fconst_1 
L235:   ldc_w +0.800000011920929f 
L238:   invokevirtual Method com/badlogic/gdx/scenes/scene2d/ui/Label setColor (FFFF)V 
L241:   aload_0 
L242:   getfield Field com/cairn4/moonbase/ui/MiniMap hoverLabel Lcom/badlogic/gdx/scenes/scene2d/ui/Label; 
L245:   iconst_1 
L246:   iconst_1 
L247:   invokevirtual Method com/badlogic/gdx/scenes/scene2d/ui/Label setAlignment (II)V 
L250:   aload_0 
L251:   getfield Field com/cairn4/moonbase/ui/MiniMap hoverLabel Lcom/badlogic/gdx/scenes/scene2d/ui/Label; 
L254:   getstatic Field com/badlogic/gdx/scenes/scene2d/Touchable disabled Lcom/badlogic/gdx/scenes/scene2d/Touchable; 
L257:   invokevirtual Method com/badlogic/gdx/scenes/scene2d/ui/Label setTouchable (Lcom/badlogic/gdx/scenes/scene2d/Touchable;)V 
L260:   aload_0 
L261:   getfield Field com/cairn4/moonbase/ui/MiniMap hoverTooltipTable Lcom/badlogic/gdx/scenes/scene2d/ui/Table; 
L264:   aload_0 
L265:   getfield Field com/cairn4/moonbase/ui/MiniMap hoverLabel Lcom/badlogic/gdx/scenes/scene2d/ui/Label; 
L268:   invokevirtual Method com/badlogic/gdx/scenes/scene2d/ui/Table add (Lcom/badlogic/gdx/scenes/scene2d/Actor;)Lcom/badlogic/gdx/scenes/scene2d/ui/Cell; 
L271:   invokevirtual Method com/badlogic/gdx/scenes/scene2d/ui/Cell fillX ()Lcom/badlogic/gdx/scenes/scene2d/ui/Cell; 
L274:   pop 
L275:   aload_0 
L276:   getfield Field com/cairn4/moonbase/ui/MiniMap hoverTooltipTable Lcom/badlogic/gdx/scenes/scene2d/ui/Table; 
L279:   invokevirtual Method com/badlogic/gdx/scenes/scene2d/ui/Table layout ()V 
L282:   aload_0 
L283:   getfield Field com/cairn4/moonbase/ui/MiniMap hoverPanel Lcom/badlogic/gdx/scenes/scene2d/ui/Image; 
L286:   aload_0 
L287:   getfield Field com/cairn4/moonbase/ui/MiniMap hoverTooltipTable Lcom/badlogic/gdx/scenes/scene2d/ui/Table; 
L290:   invokevirtual Method com/badlogic/gdx/scenes/scene2d/ui/Table getPrefWidth ()F 
L293:   ldc +30.0f 
L295:   fadd 
L296:   aload_0 
L297:   getfield Field com/cairn4/moonbase/ui/MiniMap hoverTooltipTable Lcom/badlogic/gdx/scenes/scene2d/ui/Table; 
L300:   invokevirtual Method com/badlogic/gdx/scenes/scene2d/ui/Table getPrefHeight ()F 
L303:   ldc +20.0f 
L305:   fadd 
L306:   invokevirtual Method com/badlogic/gdx/scenes/scene2d/ui/Image setSize (FF)V 
L309:   aload_0 
L310:   getfield Field com/cairn4/moonbase/ui/MiniMap hoverPanel Lcom/badlogic/gdx/scenes/scene2d/ui/Image; 
L313:   ldc_w -15.0f 
L316:   ldc_w -10.0f 
L319:   invokevirtual Method com/badlogic/gdx/scenes/scene2d/ui/Image setPosition (FF)V 
L322:   return 
L323:   
        .linenumbertable 
            L0 1073 
            L11 1074 
            L27 1075 
            L38 1077 
            L49 1079 
            L62 1080 
            L73 1082 
            L102 1083 
            L114 1084 
            L127 1085 
            L137 1087 
            L148 1088 
            L158 1090 
            L169 1091 
            L178 1092 
            L186 1093 
            L197 1095 
            L218 1096 
            L228 1097 
            L241 1098 
            L250 1099 
            L260 1100 
            L275 1102 
            L282 1104 
            L309 1105 
            L322 1107 
        .end linenumbertable 
        .localvariabletable 
            0 is this Lcom/cairn4/moonbase/ui/MiniMap; from L0 to L323 
            1 is roundedbox Lcom/badlogic/gdx/graphics/g2d/NinePatch; from L102 to L323 
        .end localvariabletable 
    .end code 
.end method 

.method protected finishedShowAnim : ()V 
    .code stack 6 locals 2 
L0:     aload_0 
L1:     getfield Field com/cairn4/moonbase/ui/MiniMap chunkGroup Lcom/badlogic/gdx/scenes/scene2d/Group; 
L4:     new com/cairn4/moonbase/ui/MiniMap$5 
L7:     dup 
L8:     aload_0 
L9:     invokespecial Method com/cairn4/moonbase/ui/MiniMap$5 <init> (Lcom/cairn4/moonbase/ui/MiniMap;)V 
L12:    invokevirtual Method com/badlogic/gdx/scenes/scene2d/Group addListener (Lcom/badlogic/gdx/scenes/scene2d/EventListener;)Z 
L15:    pop 
L16:    aload_0 
L17:    getfield Field com/cairn4/moonbase/ui/MiniMap gameScreen Lcom/cairn4/moonbase/ui/GameScreen; 
L20:    getfield Field com/cairn4/moonbase/ui/GameScreen world Lcom/cairn4/moonbase/World; 
L23:    getfield Field com/cairn4/moonbase/World chunkLoader Lcom/cairn4/moonbase/worlddata/ChunkLoader; 
L26:    invokevirtual Method com/cairn4/moonbase/worlddata/ChunkLoader getMinMaxChunkCoords ()[I 
L29:    astore_1 
L30:    aload_0 
L31:    aload_1 
L32:    iconst_0 
L33:    iaload 
L34:    putfield Field com/cairn4/moonbase/ui/MiniMap minChunkX I 
L37:    aload_0 
L38:    aload_1 
L39:    iconst_1 
L40:    iaload 
L41:    putfield Field com/cairn4/moonbase/ui/MiniMap minChunkY I 
L44:    aload_0 
L45:    aload_1 
L46:    iconst_2 
L47:    iaload 
L48:    putfield Field com/cairn4/moonbase/ui/MiniMap maxChunkX I 
L51:    aload_0 
L52:    aload_1 
L53:    iconst_3 
L54:    iaload 
L55:    putfield Field com/cairn4/moonbase/ui/MiniMap maxChunkY I 
L58:    aload_0 
L59:    aload_0 
L60:    getfield Field com/cairn4/moonbase/ui/MiniMap minChunkX I 
L63:    bipush 10 
L65:    idiv 
L66:    i2f 
L67:    invokestatic Method com/badlogic/gdx/math/MathUtils floor (F)I 
L70:    putfield Field com/cairn4/moonbase/ui/MiniMap minMegaChunkX I 
L73:    aload_0 
L74:    aload_0 
L75:    getfield Field com/cairn4/moonbase/ui/MiniMap maxChunkX I 
L78:    bipush 10 
L80:    idiv 
L81:    i2f 
L82:    invokestatic Method com/badlogic/gdx/math/MathUtils floor (F)I 
L85:    putfield Field com/cairn4/moonbase/ui/MiniMap maxMegaChunkX I 
L88:    aload_0 
L89:    aload_0 
L90:    getfield Field com/cairn4/moonbase/ui/MiniMap minChunkY I 
L93:    bipush 10 
L95:    idiv 
L96:    i2f 
L97:    invokestatic Method com/badlogic/gdx/math/MathUtils floor (F)I 
L100:   putfield Field com/cairn4/moonbase/ui/MiniMap minMegaChunkY I 
L103:   aload_0 
L104:   aload_0 
L105:   getfield Field com/cairn4/moonbase/ui/MiniMap maxChunkY I 
L108:   bipush 10 
L110:   idiv 
L111:   i2f 
L112:   invokestatic Method com/badlogic/gdx/math/MathUtils floor (F)I 
L115:   putfield Field com/cairn4/moonbase/ui/MiniMap maxMegaChunkY I 
L118:   aload_0 
L119:   getfield Field com/cairn4/moonbase/ui/MiniMap minDragPos Lcom/badlogic/gdx/math/Vector2; 
L122:   aload_0 
L123:   getfield Field com/cairn4/moonbase/ui/MiniMap minMegaChunkX I 
L126:   bipush 100 
L128:   imul 
L129:   i2f 
L130:   aload_0 
L131:   getfield Field com/cairn4/moonbase/ui/MiniMap minMegaChunkY I 
L134:   bipush 100 
L136:   imul 
L137:   i2f 
L138:   invokevirtual Method com/badlogic/gdx/math/Vector2 set (FF)Lcom/badlogic/gdx/math/Vector2; 
L141:   pop 
L142:   aload_0 
L143:   getfield Field com/cairn4/moonbase/ui/MiniMap maxDragPos Lcom/badlogic/gdx/math/Vector2; 
L146:   aload_0 
L147:   getfield Field com/cairn4/moonbase/ui/MiniMap maxMegaChunkX I 
L150:   bipush 100 
L152:   imul 
L153:   i2f 
L154:   aload_0 
L155:   getfield Field com/cairn4/moonbase/ui/MiniMap maxMegaChunkY I 
L158:   bipush 100 
L160:   imul 
L161:   i2f 
L162:   invokevirtual Method com/badlogic/gdx/math/Vector2 set (FF)Lcom/badlogic/gdx/math/Vector2; 
L165:   pop 
L166:   aload_0 
L167:   invokespecial Method com/cairn4/moonbase/ui/MiniMap generateMap ()V 
L170:   aload_0 
L171:   invokespecial Method com/cairn4/moonbase/ui/MiniMap showMap ()V 
L174:   aload_0 
L175:   aload_0 
L176:   getfield Field com/cairn4/moonbase/ui/MiniMap minChunkX I 
L179:   i2f 
L180:   aload_0 
L181:   getfield Field com/cairn4/moonbase/ui/MiniMap minChunkY I 
L184:   i2f 
L185:   getstatic Field com/cairn4/moonbase/ui/MiniMap CHUNKS_RADIUS_FROM_CURRENT I 
L188:   iconst_2 
L189:   imul 
L190:   iconst_1 
L191:   iadd 
L192:   getstatic Field com/cairn4/moonbase/ui/MiniMap CHUNKS_RADIUS_FROM_CURRENT I 
L195:   iconst_2 
L196:   imul 
L197:   iconst_1 
L198:   iadd 
L199:   invokespecial Method com/cairn4/moonbase/ui/MiniMap showNavBeacons (FFII)V 
L202:   aload_0 
L203:   invokespecial Method com/cairn4/moonbase/ui/MiniMap showBuggies ()V 
L206:   aload_0 
L207:   aload_0 
L208:   getfield Field com/cairn4/moonbase/ui/MiniMap minChunkX I 
L211:   i2f 
L212:   aload_0 
L213:   getfield Field com/cairn4/moonbase/ui/MiniMap minChunkY I 
L216:   i2f 
L217:   invokespecial Method com/cairn4/moonbase/ui/MiniMap showLander (FF)V 
L220:   aload_0 
L221:   invokespecial Method com/cairn4/moonbase/ui/MiniMap addPlayerMarker ()V 
L224:   aload_0 
L225:   iconst_0 
L226:   invokespecial Method com/cairn4/moonbase/ui/MiniMap centerOnPlayer (Z)V 
L229:   aload_0 
L230:   invokespecial Method com/cairn4/moonbase/ui/MiniMap updateOffsetOrigin ()V 
L233:   return 
L234:   
        .linenumbertable 
            L0 1114 
            L16 1143 
            L30 1145 
            L37 1146 
            L44 1147 
            L51 1148 
            L58 1150 
            L73 1151 
            L88 1153 
            L103 1154 
            L118 1156 
            L142 1157 
            L166 1159 
            L170 1161 
            L174 1163 
            L202 1164 
            L206 1165 
            L220 1167 
            L224 1174 
            L229 1175 
            L233 1178 
        .end linenumbertable 
        .localvariabletable 
            0 is this Lcom/cairn4/moonbase/ui/MiniMap; from L0 to L234 
            1 is lim [I from L30 to L234 
        .end localvariabletable 
    .end code 
.end method 

.method private updatePosLabel : (Lcom/badlogic/gdx/math/Vector2;)V 
    .code stack 3 locals 2 
L0:     aload_0 
L1:     getfield Field com/cairn4/moonbase/ui/MiniMap pauseLabel Lcom/badlogic/gdx/scenes/scene2d/ui/Label; 
L4:     new java/lang/StringBuilder 
L7:     dup 
L8:     invokespecial Method java/lang/StringBuilder <init> ()V 
L11:    aload_1 
L12:    getfield Field com/badlogic/gdx/math/Vector2 x F 
L15:    invokevirtual Method java/lang/StringBuilder append (F)Ljava/lang/StringBuilder; 
L18:    ldc ', ' 
L20:    invokevirtual Method java/lang/StringBuilder append (Ljava/lang/String;)Ljava/lang/StringBuilder; 
L23:    aload_1 
L24:    getfield Field com/badlogic/gdx/math/Vector2 y F 
L27:    invokevirtual Method java/lang/StringBuilder append (F)Ljava/lang/StringBuilder; 
L30:    invokevirtual Method java/lang/StringBuilder toString ()Ljava/lang/String; 
L33:    invokevirtual Method com/badlogic/gdx/scenes/scene2d/ui/Label setText (Ljava/lang/CharSequence;)V 
L36:    return 
L37:    
        .linenumbertable 
            L0 1183 
            L36 1184 
        .end linenumbertable 
        .localvariabletable 
            0 is this Lcom/cairn4/moonbase/ui/MiniMap; from L0 to L37 
            1 is offset Lcom/badlogic/gdx/math/Vector2; from L0 to L37 
        .end localvariabletable 
    .end code 
.end method 

.method private updateOffsetOrigin : ()V 
    .code stack 0 locals 1 
L0:     return 
L1:     
        .linenumbertable 
            L0 1194 
        .end linenumbertable 
        .localvariabletable 
            0 is this Lcom/cairn4/moonbase/ui/MiniMap; from L0 to L1 
        .end localvariabletable 
    .end code 
.end method 

.method private worldTileToMapPos : (II)Lcom/badlogic/gdx/math/Vector2; 
    .code stack 4 locals 6 
L0:     new com/badlogic/gdx/math/Vector2 
L3:     dup 
L4:     fconst_0 
L5:     fconst_0 
L6:     invokespecial Method com/badlogic/gdx/math/Vector2 <init> (FF)V 
L9:     astore_3 
L10:    iload_1 
L11:    i2f 
L12:    ldc +10.0f 
L14:    getstatic Field com/cairn4/moonbase/ui/MiniMap MEGA_CHUNK I 
L17:    i2f 
L18:    fmul 
L19:    fdiv 
L20:    aload_0 
L21:    getfield Field com/cairn4/moonbase/ui/MiniMap minMegaChunkX I 
L24:    i2f 
L25:    fsub 
L26:    fstore 4 
L28:    fload 4 
L30:    bipush 100 
L32:    getstatic Field com/cairn4/moonbase/ui/MiniMap MEGA_CHUNK I 
L35:    imul 
L36:    i2f 
L37:    fmul 
L38:    fstore 4 
L40:    iload_2 
L41:    i2f 
L42:    ldc +10.0f 
L44:    getstatic Field com/cairn4/moonbase/ui/MiniMap MEGA_CHUNK I 
L47:    i2f 
L48:    fmul 
L49:    fdiv 
L50:    aload_0 
L51:    getfield Field com/cairn4/moonbase/ui/MiniMap minMegaChunkY I 
L54:    i2f 
L55:    fsub 
L56:    fstore 5 
L58:    fload 5 
L60:    bipush 100 
L62:    getstatic Field com/cairn4/moonbase/ui/MiniMap MEGA_CHUNK I 
L65:    imul 
L66:    i2f 
L67:    fmul 
L68:    fstore 5 
L70:    aload_3 
L71:    fload 4 
L73:    fload 5 
L75:    invokevirtual Method com/badlogic/gdx/math/Vector2 set (FF)Lcom/badlogic/gdx/math/Vector2; 
L78:    pop 
L79:    aload_3 
L80:    areturn 
L81:    
        .linenumbertable 
            L0 1201 
            L10 1203 
            L28 1204 
            L40 1206 
            L58 1207 
            L70 1209 
            L79 1210 
        .end linenumbertable 
        .localvariabletable 
            0 is this Lcom/cairn4/moonbase/ui/MiniMap; from L0 to L81 
            1 is worldX I from L0 to L81 
            2 is worldY I from L0 to L81 
            3 is mapPos Lcom/badlogic/gdx/math/Vector2; from L10 to L81 
            4 is pX F from L28 to L81 
            5 is pY F from L58 to L81 
        .end localvariabletable 
    .end code 
.end method 

.method private addPlayerMarker : ()V 
    .code stack 6 locals 3 
L0:     aload_0 
L1:     aload_0 
L2:     getfield Field com/cairn4/moonbase/ui/MiniMap gameScreen Lcom/cairn4/moonbase/ui/GameScreen; 
L5:     getfield Field com/cairn4/moonbase/ui/GameScreen world Lcom/cairn4/moonbase/World; 
L8:     getfield Field com/cairn4/moonbase/World player Lcom/cairn4/moonbase/Player; 
L11:    invokevirtual Method com/cairn4/moonbase/Player getX ()I 
L14:    aload_0 
L15:    getfield Field com/cairn4/moonbase/ui/MiniMap gameScreen Lcom/cairn4/moonbase/ui/GameScreen; 
L18:    getfield Field com/cairn4/moonbase/ui/GameScreen world Lcom/cairn4/moonbase/World; 
L21:    getfield Field com/cairn4/moonbase/World player Lcom/cairn4/moonbase/Player; 
L24:    invokevirtual Method com/cairn4/moonbase/Player getY ()I 
L27:    invokespecial Method com/cairn4/moonbase/ui/MiniMap worldTileToMapPos (II)Lcom/badlogic/gdx/math/Vector2; 
L30:    astore_1 
L31:    new com/badlogic/gdx/scenes/scene2d/ui/Image 
L34:    dup 
L35:    aload_0 
L36:    getfield Field com/cairn4/moonbase/ui/MiniMap gameScreen Lcom/cairn4/moonbase/ui/GameScreen; 
L39:    getfield Field com/cairn4/moonbase/ui/GameScreen skin Lcom/badlogic/gdx/scenes/scene2d/ui/Skin; 
L42:    ldc_w 'equippedFlag' 
L45:    invokevirtual Method com/badlogic/gdx/scenes/scene2d/ui/Skin getDrawable [u1078] 
L48:    invokespecial Method com/badlogic/gdx/scenes/scene2d/ui/Image <init> [u1079] 
L51:    astore_2 
L52:    aload_2 
L53:    ldc_w +48.0f 
L56:    ldc_w +48.0f 
L59:    invokevirtual Method com/badlogic/gdx/scenes/scene2d/ui/Image setSize (FF)V 
L62:    aload_2 
L63:    iconst_1 
L64:    invokevirtual Method com/badlogic/gdx/scenes/scene2d/ui/Image setOrigin (I)V 
L67:    aload_2 
L68:    ldc_w +0.8999999761581421f 
L71:    ldc_w +0.8999999761581421f 
L74:    fconst_1 
L75:    getstatic Field com/badlogic/gdx/math/Interpolation sine Lcom/badlogic/gdx/math/Interpolation; 
L78:    invokestatic Method com/badlogic/gdx/scenes/scene2d/actions/Actions scaleTo (FFFLcom/badlogic/gdx/math/Interpolation;)Lcom/badlogic/gdx/scenes/scene2d/actions/ScaleToAction; 
L81:    ldc_w +1.100000023841858f 
L84:    ldc_w +1.100000023841858f 
L87:    fconst_1 
L88:    getstatic Field com/badlogic/gdx/math/Interpolation sine Lcom/badlogic/gdx/math/Interpolation; 
L91:    invokestatic Method com/badlogic/gdx/scenes/scene2d/actions/Actions scaleTo (FFFLcom/badlogic/gdx/math/Interpolation;)Lcom/badlogic/gdx/scenes/scene2d/actions/ScaleToAction; 
L94:    invokestatic Method com/badlogic/gdx/scenes/scene2d/actions/Actions sequence (Lcom/badlogic/gdx/scenes/scene2d/Action;Lcom/badlogic/gdx/scenes/scene2d/Action;)Lcom/badlogic/gdx/scenes/scene2d/actions/SequenceAction; 
L97:    invokestatic Method com/badlogic/gdx/scenes/scene2d/actions/Actions forever (Lcom/badlogic/gdx/scenes/scene2d/Action;)Lcom/badlogic/gdx/scenes/scene2d/actions/RepeatAction; 
L100:   invokevirtual Method com/badlogic/gdx/scenes/scene2d/ui/Image addAction (Lcom/badlogic/gdx/scenes/scene2d/Action;)V 
L103:   aload_2 
L104:   aload_1 
L105:   getfield Field com/badlogic/gdx/math/Vector2 x F 
L108:   aload_1 
L109:   getfield Field com/badlogic/gdx/math/Vector2 y F 
L112:   iconst_1 
L113:   invokevirtual Method com/badlogic/gdx/scenes/scene2d/ui/Image setPosition (FFI)V 
L116:   aload_0 
L117:   getfield Field com/cairn4/moonbase/ui/MiniMap groupOffset Lcom/badlogic/gdx/scenes/scene2d/Group; 
L120:   aload_2 
L121:   invokevirtual Method com/badlogic/gdx/scenes/scene2d/Group addActor (Lcom/badlogic/gdx/scenes/scene2d/Actor;)V 
L124:   return 
L125:   
        .linenumbertable 
            L0 1217 
            L31 1219 
            L52 1220 
            L62 1221 
            L67 1222 
            L78 1225 
            L91 1226 
            L94 1224 
            L97 1223 
            L100 1222 
            L103 1230 
            L116 1231 
            L124 1232 
        .end linenumbertable 
        .localvariabletable 
            0 is this Lcom/cairn4/moonbase/ui/MiniMap; from L0 to L125 
            1 is playerMapPos Lcom/badlogic/gdx/math/Vector2; from L31 to L125 
            2 is playerPos Lcom/badlogic/gdx/scenes/scene2d/ui/Image; from L52 to L125 
        .end localvariabletable 
    .end code 
.end method 

.method private centerOnPlayer : (Z)V 
    .code stack 6 locals 3 
L0:     aload_0 
L1:     aload_0 
L2:     getfield Field com/cairn4/moonbase/ui/MiniMap gameScreen Lcom/cairn4/moonbase/ui/GameScreen; 
L5:     getfield Field com/cairn4/moonbase/ui/GameScreen world Lcom/cairn4/moonbase/World; 
L8:     getfield Field com/cairn4/moonbase/World player Lcom/cairn4/moonbase/Player; 
L11:    invokevirtual Method com/cairn4/moonbase/Player getX ()I 
L14:    aload_0 
L15:    getfield Field com/cairn4/moonbase/ui/MiniMap gameScreen Lcom/cairn4/moonbase/ui/GameScreen; 
L18:    getfield Field com/cairn4/moonbase/ui/GameScreen world Lcom/cairn4/moonbase/World; 
L21:    getfield Field com/cairn4/moonbase/World player Lcom/cairn4/moonbase/Player; 
L24:    invokevirtual Method com/cairn4/moonbase/Player getY ()I 
L27:    invokespecial Method com/cairn4/moonbase/ui/MiniMap worldTileToMapPos (II)Lcom/badlogic/gdx/math/Vector2; 
L30:    astore_2 
L31:    getstatic Field java/lang/System out Ljava/io/PrintStream; 
L34:    new java/lang/StringBuilder 
L37:    dup 
L38:    invokespecial Method java/lang/StringBuilder <init> ()V 
L41:    ldc_w 'Center map offset ' 
L44:    invokevirtual Method java/lang/StringBuilder append (Ljava/lang/String;)Ljava/lang/StringBuilder; 
L47:    aload_2 
L48:    getfield Field com/badlogic/gdx/math/Vector2 x F 
L51:    invokevirtual Method java/lang/StringBuilder append (F)Ljava/lang/StringBuilder; 
L54:    ldc ', ' 
L56:    invokevirtual Method java/lang/StringBuilder append (Ljava/lang/String;)Ljava/lang/StringBuilder; 
L59:    aload_2 
L60:    getfield Field com/badlogic/gdx/math/Vector2 y F 
L63:    invokevirtual Method java/lang/StringBuilder append (F)Ljava/lang/StringBuilder; 
L66:    invokevirtual Method java/lang/StringBuilder toString ()Ljava/lang/String; 
L69:    invokevirtual Method java/io/PrintStream println (Ljava/lang/String;)V 
L72:    iload_1 
L73:    ifne L104 
L76:    aload_0 
L77:    getfield Field com/cairn4/moonbase/ui/MiniMap groupOffset Lcom/badlogic/gdx/scenes/scene2d/Group; 
L80:    aload_2 
L81:    getfield Field com/badlogic/gdx/math/Vector2 x F 
L84:    fneg 
L85:    aload_2 
L86:    getfield Field com/badlogic/gdx/math/Vector2 y F 
L89:    fneg 
L90:    invokevirtual Method com/badlogic/gdx/scenes/scene2d/Group setPosition (FF)V 
L93:    aload_0 
L94:    getfield Field com/cairn4/moonbase/ui/MiniMap groupOffset Lcom/badlogic/gdx/scenes/scene2d/Group; 
L97:    fconst_1 
L98:    invokevirtual Method com/badlogic/gdx/scenes/scene2d/Group setScale (F)V 
L101:   goto L151 

        .stack append Object com/badlogic/gdx/math/Vector2 
L104:   aload_0 
L105:   getfield Field com/cairn4/moonbase/ui/MiniMap groupOffset Lcom/badlogic/gdx/scenes/scene2d/Group; 
L108:   invokevirtual Method com/badlogic/gdx/scenes/scene2d/Group clearActions ()V 
L111:   aload_0 
L112:   getfield Field com/cairn4/moonbase/ui/MiniMap groupOffset Lcom/badlogic/gdx/scenes/scene2d/Group; 
L115:   aload_2 
L116:   getfield Field com/badlogic/gdx/math/Vector2 x F 
L119:   fneg 
L120:   aload_2 
L121:   getfield Field com/badlogic/gdx/math/Vector2 y F 
L124:   fneg 
L125:   ldc_w +0.5f 
L128:   getstatic Field com/badlogic/gdx/math/Interpolation sine Lcom/badlogic/gdx/math/Interpolation; 
L131:   invokestatic Method com/badlogic/gdx/scenes/scene2d/actions/Actions moveTo (FFFLcom/badlogic/gdx/math/Interpolation;)Lcom/badlogic/gdx/scenes/scene2d/actions/MoveToAction; 
L134:   fconst_1 
L135:   fconst_1 
L136:   ldc_w +0.5f 
L139:   getstatic Field com/badlogic/gdx/math/Interpolation sine Lcom/badlogic/gdx/math/Interpolation; 
L142:   invokestatic Method com/badlogic/gdx/scenes/scene2d/actions/Actions scaleTo (FFFLcom/badlogic/gdx/math/Interpolation;)Lcom/badlogic/gdx/scenes/scene2d/actions/ScaleToAction; 
L145:   invokestatic Method com/badlogic/gdx/scenes/scene2d/actions/Actions parallel (Lcom/badlogic/gdx/scenes/scene2d/Action;Lcom/badlogic/gdx/scenes/scene2d/Action;)Lcom/badlogic/gdx/scenes/scene2d/actions/ParallelAction; 
L148:   invokevirtual Method com/badlogic/gdx/scenes/scene2d/Group addAction (Lcom/badlogic/gdx/scenes/scene2d/Action;)V 

        .stack same 
L151:   return 
L152:   
        .linenumbertable 
            L0 1238 
            L31 1240 
            L72 1242 
            L76 1243 
            L93 1244 
            L104 1247 
            L111 1248 
            L131 1249 
            L142 1250 
            L145 1248 
            L151 1255 
        .end linenumbertable 
        .localvariabletable 
            0 is this Lcom/cairn4/moonbase/ui/MiniMap; from L0 to L152 
            1 is animate Z from L0 to L152 
            2 is playerMapPos Lcom/badlogic/gdx/math/Vector2; from L31 to L152 
        .end localvariabletable 
    .end code 
.end method 

.method public back : ()V 
    .code stack 2 locals 3 
L0:     aload_0 
L1:     getfield Field com/cairn4/moonbase/ui/MiniMap gameScreen Lcom/cairn4/moonbase/ui/GameScreen; 
L4:     getfield Field com/cairn4/moonbase/ui/GameScreen world Lcom/cairn4/moonbase/World; 
L5:     getfield Field com/cairn4/moonbase/World player Lcom/cairn4/moonbase/Player; 
L6:     getfield Field com/cairn4/moonbase/Player playerStatus Lcom/cairn4/moonbase/PlayerStatus;
L7:     iconst_0
L8:     invokevirtual Method com/cairn4/moonbase/PlayerStatus setFlashlight (Z)V 
L11:    aload_0 
L12:    getfield Field com/cairn4/moonbase/ui/MiniMap disposableTextures Ljava/util/ArrayList; 
L15:    invokevirtual Method java/util/ArrayList iterator ()Ljava/util/Iterator; 
L18:    astore_1 

        .stack append Object java/util/Iterator 
L19:    aload_1 
L20:    invokeinterface InterfaceMethod java/util/Iterator hasNext ()Z 1 
L25:    ifeq L45 
L28:    aload_1 
L29:    invokeinterface InterfaceMethod java/util/Iterator next ()Ljava/lang/Object; 1 
L34:    checkcast com/badlogic/gdx/graphics/Texture 
L37:    astore_2 
L38:    aload_2 
L39:    invokevirtual Method com/badlogic/gdx/graphics/Texture dispose ()V 
L42:    goto L19 

        .stack chop 1 
L45:    aload_0 
L46:    getfield Field com/cairn4/moonbase/ui/MiniMap disposableTextures Ljava/util/ArrayList; 
L49:    invokevirtual Method java/util/ArrayList clear ()V 
L52:    aload_0 
L53:    getfield Field com/cairn4/moonbase/ui/MiniMap chunkColorState Ljava/util/HashMap; 
L56:    invokevirtual Method java/util/HashMap clear ()V 
L59:    aload_0 
L60:    getfield Field com/cairn4/moonbase/ui/MiniMap chunkTextures Ljava/util/HashMap; 
L63:    invokevirtual Method java/util/HashMap clear ()V 
L66:    aload_0 
L67:    invokespecial Method com/cairn4/moonbase/ui/Menu back ()V 
L70:    return 
L71:    
        .linenumbertable 
            L0 1264 
            L11 1266 
            L38 1267 
            L42 1268 
            L45 1270 
            L52 1271 
            L59 1272 
            L66 1275 
            L70 1276 
        .end linenumbertable 
        .localvariabletable 
            2 is t Lcom/badlogic/gdx/graphics/Texture; from L38 to L42 
            0 is this Lcom/cairn4/moonbase/ui/MiniMap; from L0 to L71 
        .end localvariabletable 
    .end code 
.end method 

.method public handleInput : ()V 
    .code stack 1 locals 1 
L0:     bipush 22 
L2:     invokestatic Method com/cairn4/moonbase/PlayerInput wasPressed (I)Z 
L5:     ifeq L12 
L8:     aload_0 
L9:     invokevirtual Method com/cairn4/moonbase/ui/MiniMap back ()V 

        .stack same 
L12:    aload_0 
L13:    invokespecial Method com/cairn4/moonbase/ui/Menu handleInput ()V 
L16:    return 
L17:    
        .linenumbertable 
            L0 1286 
            L8 1287 
            L12 1290 
            L16 1291 
        .end linenumbertable 
        .localvariabletable 
            0 is this Lcom/cairn4/moonbase/ui/MiniMap; from L0 to L17 
        .end localvariabletable 
    .end code 
.end method 

.method static synthetic access$000 : (Lcom/cairn4/moonbase/ui/MiniMap;Z)V 
    .code stack 2 locals 2 
L0:     aload_0 
L1:     iload_1 
L2:     invokespecial Method com/cairn4/moonbase/ui/MiniMap centerOnPlayer (Z)V 
L5:     return 
L6:     
        .linenumbertable 
            L0 53 
        .end linenumbertable 
        .localvariabletable 
            0 is x0 Lcom/cairn4/moonbase/ui/MiniMap; from L0 to L6 
            1 is x1 Z from L0 to L6 
        .end localvariabletable 
    .end code 
.end method 

.method static synthetic access$100 : (Lcom/cairn4/moonbase/ui/MiniMap;)V 
    .code stack 1 locals 1 
L0:     aload_0 
L1:     invokespecial Method com/cairn4/moonbase/ui/MiniMap updateOffsetOrigin ()V 
L4:     return 
L5:     
        .linenumbertable 
            L0 53 
        .end linenumbertable 
        .localvariabletable 
            0 is x0 Lcom/cairn4/moonbase/ui/MiniMap; from L0 to L5 
        .end localvariabletable 
    .end code 
.end method 

.method static synthetic access$200 : (Lcom/cairn4/moonbase/ui/MiniMap;)Lcom/badlogic/gdx/scenes/scene2d/Group; 
    .code stack 1 locals 1 
L0:     aload_0 
L1:     getfield Field com/cairn4/moonbase/ui/MiniMap groupOffset Lcom/badlogic/gdx/scenes/scene2d/Group; 
L4:     areturn 
L5:     
        .linenumbertable 
            L0 53 
        .end linenumbertable 
        .localvariabletable 
            0 is x0 Lcom/cairn4/moonbase/ui/MiniMap; from L0 to L5 
        .end localvariabletable 
    .end code 
.end method 

.method static <clinit> : ()V 
    .code stack 1 locals 0 
L0:     iconst_4 
L1:     putstatic Field com/cairn4/moonbase/ui/MiniMap CHUNKS_RADIUS_FROM_CURRENT I 
L4:     ldc_w +150.0f 
L7:     putstatic Field com/cairn4/moonbase/ui/MiniMap MAX_TILE_DISTANCE F 
L10:    bipush 10 
L12:    putstatic Field com/cairn4/moonbase/ui/MiniMap MEGA_CHUNK I 
L15:    fconst_1 
L16:    putstatic Field com/cairn4/moonbase/ui/MiniMap savedZoom F 
L19:    ldc_w +500.0f 
L22:    putstatic Field com/cairn4/moonbase/ui/MiniMap PAN_SPEED F 
L25:    return 
L26:    
        .linenumbertable 
            L0 56 
            L4 57 
            L10 60 
            L15 61 
            L19 120 
        .end linenumbertable 
    .end code 
.end method 
.sourcefile 'MiniMap.java' 
.innerclasses 
    com/cairn4/moonbase/ui/MiniMap$5 [0] [0] 
    com/cairn4/moonbase/ui/MiniMap$4 [0] [0] 
    com/cairn4/moonbase/ui/MiniMap$3 [0] [0] 
    com/cairn4/moonbase/ui/MiniMap$2 [0] [0] 
    com/cairn4/moonbase/ui/MiniMap$1 [0] [0] 
    java/util/Map$Entry java/util/Map Entry public static interface abstract 
    [c287] com/badlogic/gdx/scenes/scene2d/ui/Button ButtonStyle public static 
    com/badlogic/gdx/graphics/Pixmap$Format com/badlogic/gdx/graphics/Pixmap Format public static final enum 
    com/badlogic/gdx/graphics/Texture$TextureFilter com/badlogic/gdx/graphics/Texture TextureFilter public static final enum 
    com/badlogic/gdx/scenes/scene2d/ui/Label$LabelStyle com/badlogic/gdx/scenes/scene2d/ui/Label LabelStyle public static 
.end innerclasses 
.const [c287] = Class [u917] 
.const [u1078] = Utf8 (Ljava/lang/String;)Lcom/badlogic/gdx/scenes/scene2d/utils/Drawable; 
.const [u1079] = Utf8 (Lcom/badlogic/gdx/scenes/scene2d/utils/Drawable;)V 
.const [u1118] = Utf8 (F)Lcom/badlogic/gdx/scenes/scene2d/actions/AlphaAction; 
.const [u917] = Utf8 com/badlogic/gdx/scenes/scene2d/ui/Button$ButtonStyle 
.end class 
